Workbook

Sheet TOC
B1: KAROFI - MONTHLY SALES FORECAST
C3: Sales Forecast - Tháng 6 Tuần 0 | E3: Sales Forecast - Tháng 6 Tuần 1
B4: B1 | C4: Summary tháng | D4: B1 | E4: Summary tháng
B5: B1.1 | C5: MT | D5: B1.1 | E5: MT
B6: B1.1 | C6: GT1 | D6: B1.2 | E6: GT1
B7: B1.3 | C7: XK | D7: B1.3 | E7: XK
B8: B1.4 | C8: OEM | D8: B1.4 | E8: OEM
B9: B1.5 | C9: GT2 | D9: B1.5 | E9: GT2
B10: B1.6 | C10: Bán lẻ | D10: B1.6 | E10: Bán lẻ
B11: B1.7 | C11: Sales online | D11: B1.7 | E11: Sales online
B13: B5 | C13: Quy trình lập Sales forecast
B14: B6 | C14: Nguyên tắc và các giả định

Sheet B0.SUM (tuần 0)
A1: BẢNG 1: | B1: SALES FC - NGÀNH 1 (THÁNG 07.2026) | I1: Tháng 07- Sales FC | Q1: Tháng 08- Sales FC | Y1: Tháng 09- Sales FC | AG1: Tháng 10- Sales FC
I2: TỔNG | J2: MT | K2: XK | L2: MLT | M2: GT2 | N2: OEM | O2: Retail | P2: Online | Q2: TỔNG | R2: MT | S2: XK | T2: MLT | U2: GT2 | V2: OEM | W2: Retail | X2: Online | Y2: TỔNG | Z2: MT | AA2: XK | AB2: MLT | AC2: GT2 | AD2: OEM | AE2: Retail | AF2: Online | AG2: TỔNG | AH2: MT | AI2: XK | AJ2: MLT | AK2: GT2 | AL2: OEM | AM2: Retail | AN2: Online
A3: Ngày update: | B3: 46204 | G3: NHÓM 1 | H3: Máy TCM sx | I3: =SUM(J3:P3) -> 8205 | J3: =SUMIF($D$11:$D$2885,$H3,J$11:J$2885) -> 0 | K3: =SUMIF($D$11:$D$2885,$H3,K$11:K$2885) -> 3720 | L3: =SUMIF($D$11:$D$2885,$H3,L$11:L$2885) -> 0 | M3: =SUMIF($D$11:$D$2885,$H3,M$11:M$2885) -> 1400 | N3: =SUMIF($D$11:$D$2885,$H3,N$11:N$2885) -> 1430 | O3: =SUMIF($D$11:$D$2885,$H3,O$11:O$2885) -> 0 | P3: =SUMIF($D$11:$D$1062,$H3,P$11:P$1062) -> 1655 | Q3: =SUM(R3:X3) -> 11135 | R3: =SUMIF($D$11:$D$2885,$H3,R$11:R$2885) -> 0 | S3: =SUMIF($D$11:$D$2885,$H3,S$11:S$2885) -> 7075 | T3: =SUMIF($D$11:$D$2885,$H3,T$11:T$2885) -> 0 | U3: =SUMIF($D$11:$D$2885,$H3,U$11:U$2885) -> 1400 | V3: =SUMIF($D$11:$D$2885,$H3,V$11:V$2885) -> 1310 | W3: =SUMIF($D$11:$D$2885,$H3,W$11:W$2885) -> 0 | X3: =SUMIF($D$11:$D$1062,$H3,X$11:X$1062) -> 1350 | Y3: =SUM(Z3:AF3) -> 12011 | Z3: =SUMIF($D$11:$D$2885,$H3,Z$11:Z$2885) -> 0 | AA3: =SUMIF($D$11:$D$2885,$H3,AA$11:AA$2885) -> 7791 | AB3: =SUMIF($D$11:$D$2885,$H3,AB$11:AB$2885) -> 0 | AC3: =SUMIF($D$11:$D$2885,$H3,AC$11:AC$2885) -> 1450 | AD3: =SUMIF($D$11:$D$2885,$H3,AD$11:AD$2885) -> 1460 | AE3: =SUMIF($D$11:$D$2885,$H3,AE$11:AE$2885) -> 0 | AF3: =SUMIF($D$11:$D$1062,$H3,AF$11:AF$1062) -> 1310 | AG3: =SUM(AH3:AN3) -> 11840 | AH3: =SUMIF($D$11:$D$2885,$H3,AH$11:AH$2885) -> 0 | AI3: =SUMIF($D$11:$D$2885,$H3,AI$11:AI$2885) -> 8330 | AJ3: =SUMIF($D$11:$D$2885,$H3,AJ$11:AJ$2885) -> 0 | AK3: =SUMIF($D$11:$D$2885,$H3,AK$11:AK$2885) -> 1850 | AL3: =SUMIF($D$11:$D$2885,$H3,AL$11:AL$2885) -> 1660 | AM3: =SUMIF($D$11:$D$2885,$H3,AM$11:AM$2885) -> 0 | AN3: =SUMIF($D$11:$D$1062,$H3,AN$11:AN$1062) -> 0
A4: (Tuần 0 - tháng 07/2026) | G4: NHÓM 2 | H4: Máy nhập khẩu | I4: =SUM(J4:P4) -> 0 | J4: =SUMIF($D$11:$D$2885,$H4,J$11:J$2885) -> 0 | K4: =SUMIF($D$11:$D$2885,$H4,K$11:K$2885) -> 0 | L4: =SUMIF($D$11:$D$2885,$H4,L$11:L$2885) -> 0 | M4: =SUMIF($D$11:$D$2885,$H4,M$11:M$2885) -> 0 | N4: =SUMIF($D$11:$D$2885,$H4,N$11:N$2885) -> 0 | O4: =SUMIF($D$11:$D$2885,$H4,O$11:O$2885) -> 0 | P4: =SUMIF($D$11:$D$1062,$H4,P$11:P$1062) -> 0 | Q4: =SUM(R4:X4) -> 0 | R4: =SUMIF($D$11:$D$2885,$H4,R$11:R$2885) -> 0 | S4: =SUMIF($D$11:$D$2885,$H4,S$11:S$2885) -> 0 | T4: =SUMIF($D$11:$D$2885,$H4,T$11:T$2885) -> 0 | U4: =SUMIF($D$11:$D$2885,$H4,U$11:U$2885) -> 0 | V4: =SUMIF($D$11:$D$2885,$H4,V$11:V$2885) -> 0 | W4: =SUMIF($D$11:$D$2885,$H4,W$11:W$2885) -> 0 | X4: =SUMIF($D$11:$D$1062,$H4,X$11:X$1062) -> 0 | Y4: =SUM(Z4:AF4) -> 0 | Z4: =SUMIF($D$11:$D$2885,$H4,Z$11:Z$2885) -> 0 | AA4: =SUMIF($D$11:$D$2885,$H4,AA$11:AA$2885) -> 0 | AB4: =SUMIF($D$11:$D$2885,$H4,AB$11:AB$2885) -> 0 | AC4: =SUMIF($D$11:$D$2885,$H4,AC$11:AC$2885) -> 0 | AD4: =SUMIF($D$11:$D$2885,$H4,AD$11:AD$2885) -> 0 | AE4: =SUMIF($D$11:$D$2885,$H4,AE$11:AE$2885) -> 0 | AF4: =SUMIF($D$11:$D$1062,$H4,AF$11:AF$1062) -> 0 | AG4: =SUM(AH4:AN4) -> 0 | AH4: =SUMIF($D$11:$D$2885,$H4,AH$11:AH$2885) -> 0 | AI4: =SUMIF($D$11:$D$2885,$H4,AI$11:AI$2885) -> 0 | AJ4: =SUMIF($D$11:$D$2885,$H4,AJ$11:AJ$2885) -> 0 | AK4: =SUMIF($D$11:$D$2885,$H4,AK$11:AK$2885) -> 0 | AL4: =SUMIF($D$11:$D$2885,$H4,AL$11:AL$2885) -> 0 | AM4: =SUMIF($D$11:$D$2885,$H4,AM$11:AM$2885) -> 0 | AN4: =SUMIF($D$11:$D$1062,$H4,AN$11:AN$1062) -> 0
G5: NHÓM 3 | H5: Mockup | I5: =SUM(J5:P5) -> 0 | J5: =SUMIF($D$11:$D$2885,$H5,J$11:J$2885) -> 0 | K5: =SUMIF($D$11:$D$2885,$H5,K$11:K$2885) -> 0 | L5: =SUMIF($D$11:$D$2885,$H5,L$11:L$2885) -> 0 | M5: =SUMIF($D$11:$D$2885,$H5,M$11:M$2885) -> 0 | N5: =SUMIF($D$11:$D$2885,$H5,N$11:N$2885) -> 0 | O5: =SUMIF($D$11:$D$2885,$H5,O$11:O$2885) -> 0 | P5: =SUMIF($D$11:$D$1062,$H5,P$11:P$1062) -> 0 | Q5: =SUM(R5:X5) -> 0 | R5: =SUMIF($D$11:$D$2885,$H5,R$11:R$2885) -> 0 | S5: =SUMIF($D$11:$D$2885,$H5,S$11:S$2885) -> 0 | T5: =SUMIF($D$11:$D$2885,$H5,T$11:T$2885) -> 0 | U5: =SUMIF($D$11:$D$2885,$H5,U$11:U$2885) -> 0 | V5: =SUMIF($D$11:$D$2885,$H5,V$11:V$2885) -> 0 | W5: =SUMIF($D$11:$D$2885,$H5,W$11:W$2885) -> 0 | X5: =SUMIF($D$11:$D$1062,$H5,X$11:X$1062) -> 0 | Y5: =SUM(Z5:AF5) -> 0 | Z5: =SUMIF($D$11:$D$2885,$H5,Z$11:Z$2885) -> 0 | AA5: =SUMIF($D$11:$D$2885,$H5,AA$11:AA$2885) -> 0 | AB5: =SUMIF($D$11:$D$2885,$H5,AB$11:AB$2885) -> 0 | AC5: =SUMIF($D$11:$D$2885,$H5,AC$11:AC$2885) -> 0 | AD5: =SUMIF($D$11:$D$2885,$H5,AD$11:AD$2885) -> 0 | AE5: =SUMIF($D$11:$D$2885,$H5,AE$11:AE$2885) -> 0 | AF5: =SUMIF($D$11:$D$1062,$H5,AF$11:AF$1062) -> 0 | AG5: =SUM(AH5:AN5) -> 0 | AH5: =SUMIF($D$11:$D$2885,$H5,AH$11:AH$2885) -> 0 | AI5: =SUMIF($D$11:$D$2885,$H5,AI$11:AI$2885) -> 0 | AJ5: =SUMIF($D$11:$D$2885,$H5,AJ$11:AJ$2885) -> 0 | AK5: =SUMIF($D$11:$D$2885,$H5,AK$11:AK$2885) -> 0 | AL5: =SUMIF($D$11:$D$2885,$H5,AL$11:AL$2885) -> 0 | AM5: =SUMIF($D$11:$D$2885,$H5,AM$11:AM$2885) -> 0 | AN5: =SUMIF($D$11:$D$1062,$H5,AN$11:AN$1062) -> 0
G6: NHÓM 4 | H6: Lõi | I6: =SUM(J6:P6) -> 103479 | J6: =SUMIF($D$11:$D$2885,$H6,J$11:J$2885) -> 0 | K6: =SUMIF($D$11:$D$2885,$H6,K$11:K$2885) -> 101877 | L6: =SUMIF($D$11:$D$2885,$H6,L$11:L$2885) -> 0 | M6: =SUMIF($D$11:$D$2885,$H6,M$11:M$2885) -> 0 | N6: =SUMIF($D$11:$D$2885,$H6,N$11:N$2885) -> 0 | O6: =SUMIF($D$11:$D$2885,$H6,O$11:O$2885) -> 0 | P6: =SUMIF($D$11:$D$1062,$H6,P$11:P$1062) -> 1602 | Q6: =SUM(R6:X6) -> 45180 | R6: =SUMIF($D$11:$D$2885,$H6,R$11:R$2885) -> 0 | S6: =SUMIF($D$11:$D$2885,$H6,S$11:S$2885) -> 43340 | T6: =SUMIF($D$11:$D$2885,$H6,T$11:T$2885) -> 0 | U6: =SUMIF($D$11:$D$2885,$H6,U$11:U$2885) -> 0 | V6: =SUMIF($D$11:$D$2885,$H6,V$11:V$2885) -> 0 | W6: =SUMIF($D$11:$D$2885,$H6,W$11:W$2885) -> 0 | X6: =SUMIF($D$11:$D$1062,$H6,X$11:X$1062) -> 1840 | Y6: =SUM(Z6:AF6) -> 61020 | Z6: =SUMIF($D$11:$D$2885,$H6,Z$11:Z$2885) -> 0 | AA6: =SUMIF($D$11:$D$2885,$H6,AA$11:AA$2885) -> 59130 | AB6: =SUMIF($D$11:$D$2885,$H6,AB$11:AB$2885) -> 0 | AC6: =SUMIF($D$11:$D$2885,$H6,AC$11:AC$2885) -> 0 | AD6: =SUMIF($D$11:$D$2885,$H6,AD$11:AD$2885) -> 0 | AE6: =SUMIF($D$11:$D$2885,$H6,AE$11:AE$2885) -> 0 | AF6: =SUMIF($D$11:$D$1062,$H6,AF$11:AF$1062) -> 1890 | AG6: =SUM(AH6:AN6) -> 294033 | AH6: =SUMIF($D$11:$D$2885,$H6,AH$11:AH$2885) -> 0 | AI6: =SUMIF($D$11:$D$2885,$H6,AI$11:AI$2885) -> 292143 | AJ6: =SUMIF($D$11:$D$2885,$H6,AJ$11:AJ$2885) -> 0 | AK6: =SUMIF($D$11:$D$2885,$H6,AK$11:AK$2885) -> 0 | AL6: =SUMIF($D$11:$D$2885,$H6,AL$11:AL$2885) -> 0 | AM6: =SUMIF($D$11:$D$2885,$H6,AM$11:AM$2885) -> 0 | AN6: =SUMIF($D$11:$D$1062,$H6,AN$11:AN$1062) -> 1890
G7: NHÓM 5 | H7: Màng | I7: =SUM(J7:P7) -> 2630 | J7: =SUMIF($D$11:$D$2885,$H7,J$11:J$2885) -> 0 | K7: =SUMIF($D$11:$D$2885,$H7,K$11:K$2885) -> 2475 | L7: =SUMIF($D$11:$D$2885,$H7,L$11:L$2885) -> 0 | M7: =SUMIF($D$11:$D$2885,$H7,M$11:M$2885) -> 0 | N7: =SUMIF($D$11:$D$2885,$H7,N$11:N$2885) -> 0 | O7: =SUMIF($D$11:$D$2885,$H7,O$11:O$2885) -> 0 | P7: =SUMIF($D$11:$D$1062,$H7,P$11:P$1062) -> 155 | Q7: =SUM(R7:X7) -> 2162 | R7: =SUMIF($D$11:$D$2885,$H7,R$11:R$2885) -> 0 | S7: =SUMIF($D$11:$D$2885,$H7,S$11:S$2885) -> 1975 | T7: =SUMIF($D$11:$D$2885,$H7,T$11:T$2885) -> 0 | U7: =SUMIF($D$11:$D$2885,$H7,U$11:U$2885) -> 0 | V7: =SUMIF($D$11:$D$2885,$H7,V$11:V$2885) -> 0 | W7: =SUMIF($D$11:$D$2885,$H7,W$11:W$2885) -> 0 | X7: =SUMIF($D$11:$D$1062,$H7,X$11:X$1062) -> 187 | Y7: =SUM(Z7:AF7) -> 1637 | Z7: =SUMIF($D$11:$D$2885,$H7,Z$11:Z$2885) -> 0 | AA7: =SUMIF($D$11:$D$2885,$H7,AA$11:AA$2885) -> 1450 | AB7: =SUMIF($D$11:$D$2885,$H7,AB$11:AB$2885) -> 0 | AC7: =SUMIF($D$11:$D$2885,$H7,AC$11:AC$2885) -> 0 | AD7: =SUMIF($D$11:$D$2885,$H7,AD$11:AD$2885) -> 0 | AE7: =SUMIF($D$11:$D$2885,$H7,AE$11:AE$2885) -> 0 | AF7: =SUMIF($D$11:$D$1062,$H7,AF$11:AF$1062) -> 187 | AG7: =SUM(AH7:AN7) -> 2217 | AH7: =SUMIF($D$11:$D$2885,$H7,AH$11:AH$2885) -> 0 | AI7: =SUMIF($D$11:$D$2885,$H7,AI$11:AI$2885) -> 2030 | AJ7: =SUMIF($D$11:$D$2885,$H7,AJ$11:AJ$2885) -> 0 | AK7: =SUMIF($D$11:$D$2885,$H7,AK$11:AK$2885) -> 0 | AL7: =SUMIF($D$11:$D$2885,$H7,AL$11:AL$2885) -> 0 | AM7: =SUMIF($D$11:$D$2885,$H7,AM$11:AM$2885) -> 0 | AN7: =SUMIF($D$11:$D$1062,$H7,AN$11:AN$1062) -> 187
I8: =SUMPRODUCT(I11:I1916,$H$11:$H$1916) -> 19058770710 | J8: =SUMPRODUCT(J11:J1916,$H$11:$H$1916) -> 0 | K8: =SUMPRODUCT(K11:K1916,$H$11:$H$1916) -> 10527725363 | L8: =SUMPRODUCT(L11:L1916,$H$11:$H$1916) -> 0 | M8: =SUMPRODUCT(M11:M1916,$H$11:$H$1916) -> 0 | N8: =SUMPRODUCT(N11:N1916,$H$11:$H$1916) -> 8356029325 | O8: =SUMPRODUCT(O11:O1916,$H$11:$H$1916) -> 0 | P8: =SUMPRODUCT(P11:P1916,$H$11:$H$1916) -> 175016022 | ... AM8: =SUMPRODUCT(AM11:AM1916,$H$11:$H$1916) -> 0 | AN8: =SUMPRODUCT(AN11:AN762,$H$11:$H$762) -> 195099456
A9: Mã sp | B9: Tên sp | C9: Tên gọi tắt | D9: Nhóm | E9: Công nghệ | F9: Kênh | G9: Đ.quyền | H9: Giá bán BQ | I9: Tổng | J9: MT | K9: XK | L9: MLT | M9: GT2 | N9: OEM | O9: Retail | P9: Online | Q9: Tổng | R9: MT | S9: XK | T9: MLT | U9: GT2 | V9: OEM | W9: Retail | X9: Online | Y9: Tổng | Z9: MT | AA9: XK | AB9: MLT | AC9: GT2 | AD9: OEM | AE9: Retail | AF9: Online | AG9: Tổng | AH9: MT | AI9: XK | AJ9: MLT | AK9: GT2 | AL9: OEM | AM9: Retail | AN9: Online | AO9: LƯU Ý
I10: =SUBTOTAL(9,I11:I1902) -> 821861 | J10: =SUBTOTAL(9,J11:J1902) -> 0 | K10: =SUBTOTAL(9,K11:K1902) -> 146808 | L10: =SUBTOTAL(9,L11:L1902) -> 0 | M10: =SUBTOTAL(9,M11:M1902) -> 1400 | N10: =SUBTOTAL(9,N11:N1902) -> 652590 | O10: =SUBTOTAL(9,O11:O1902) -> 0 | P10: =SUBTOTAL(9,P11:P1902) -> 21063 | ... AM10: =SUBTOTAL(9,AM11:AM1902) -> 0
A11: 1001010040 | B11: Máy lọc nước KoriHome WPK-606 | C11: WPK-606 | D11: Máy TCM Sx | E11: 10L | F11: XK | H11: 3025631 | I11: =SUM(J11:P11) -> 100 | K11: =SUMIFS('B0.3.XK'!J:J,'B0.3.XK'!A:A,'B0.SUM (tuần 0)'!$A11) -> 100 | M11: =SUMIFS('B0.5.GT2'!K:K,'B0.5.GT2'!A:A,'B0.SUM (tuần 0)'!$A11) -> 0 | N11: =SUMIFS('B0.4.OEM'!J:J,'B0.4.OEM'!A:A,'B0.SUM (tuần 0)'!$A11) -> 0 | P11: =SUMIFS('B0.8.Online'!J:J,'B0.8.Online'!A:A,'B0.SUM (tuần 0)'!$A11) -> 0 | Q11: =SUM(R11:X11) -> 0 | S11: =SUMIFS('B0.3.XK'!K:K,'B0.3.XK'!A:A,'B0.SUM (tuần 0)'!$A11) -> 0 | U11: =SUMIFS('B0.5.GT2'!K:K,'B0.5.GT2'!A:A,'B0.SUM (tuần 0)'!$A11) -> 0 | V11: =SUMIFS('B0.4.OEM'!K:K,'B0.4.OEM'!A:A,'B0.SUM (tuần 0)'!$A11) -> 0 | X11: =SUMIFS('B0.8.Online'!K:K,'B0.8.Online'!A:A,'B0.SUM (tuần 0)'!$A11) -> 0 | Y11: =SUM(Z11:AF11) -> 0 | AA11: =SUMIFS('B0.3.XK'!L:L,'B0.3.XK'!A:A,'B0.SUM (tuần 0)'!$A11) -> 0 | AC11: =SUMIFS('B0.5.GT2'!L:L,'B0.5.GT2'!A:A,'B0.SUM (tuần 0)'!$A11) -> 0 | AD11: =SUMIFS('B0.4.OEM'!L:L,'B0.4.OEM'!A:A,'B0.SUM (tuần 0)'!$A11) -> 0 | AF11: =SUMIFS('B0.8.Online'!L:L,'B0.8.Online'!A:A,'B0.SUM (tuần 0)'!$A11) -> 0 | AG11: =SUM(AH11:AN11) -> 0 | AI11: =SUMIFS('B0.3.XK'!M:M,'B0.3.XK'!A:A,'B0.SUM (tuần 0)'!$A11) -> 0 | AK11: =SUMIFS('B0.5.GT2'!M:M,'B0.5.GT2'!A:A,'B0.SUM (tuần 0)'!$A11) -> 0 | AL11: =SUMIFS('B0.4.OEM'!M:M,'B0.4.OEM'!A:A,'B0.SUM (tuần 0)'!$A11) -> 0 | AN11: =SUMIFS('B0.8.Online'!M:M,'B0.8.Online'!A:A,'B0.SUM (tuần 0)'!$A11) -> 0 | AO11: Model clear tại nguyễn Kim | AP11: =SUMIFS('B1.SUM (tuần 4)'!$I:$I,'B1.SUM (tuần 4)'!$A:$A,'B0.SUM (tuần 0)'!$A11) -> 0 | AQ11: =I11-AP11 -> 100
A12: 1001020018 | B12: Bộ lọc thô 2 stages GRANDSAFE | C12: Prefilter2S10" | D12: Máy TCM Sx | E12: Bộ lọc thô | F12: XK | H12: 210479 | I12: =SUM(J12:P12) -> 0 | K12: =SUMIFS('B0.3.XK'!J:J,'B0.3.XK'!A:A,'B0.SUM (tuần 0)'!$A12) -> 0 | M12: =SUMIFS('B0.5.GT2'!K:K,'B0.5.GT2'!A:A,'B0.SUM (tuần 0)'!$A12) -> 0 | N12: =SUMIFS('B0.4.OEM'!J:J,'B0.4.OEM'!A:A,'B0.SUM (tuần 0)'!$A12) -> 0 | P12: =SUMIFS('B0.8.Online'!J:J,'B0.8.Online'!A:A,'B0.SUM (tuần 0)'!$A12) -> 0 | Q12: =SUM(R12:X12) -> 2 | S12: =SUMIFS('B0.3.XK'!K:K,'B0.3.XK'!A:A,'B0.SUM (tuần 0)'!$A12) -> 2 | U12: =SUMIFS('B0.5.GT2'!K:K,'B0.5.GT2'!A:A,'B0.SUM (tuần 0)'!$A12) -> 0 | V12: =SUMIFS('B0.4.OEM'!K:K,'B0.4.OEM'!A:A,'B0.SUM (tuần 0)'!$A12) -> 0 | X12: =SUMIFS('B0.8.Online'!K:K,'B0.8.Online'!A:A,'B0.SUM (tuần 0)'!$A12) -> 0 | Y12: =SUM(Z12:AF12) -> 0 | AA12: =SUMIFS('B0.3.XK'!L:L,'B0.3.XK'!A:A,'B0.SUM (tuần 0)'!$A12) -> 0 | AC12: =SUMIFS('B0.5.GT2'!L:L,'B0.5.GT2'!A:A,'B0.SUM (tuần 0)'!$A12) -> 0 | AD12: =SUMIFS('B0.4.OEM'!L:L,'B0.4.OEM'!A:A,'B0.SUM (tuần 0)'!$A12) -> 0 | AF12: =SUMIFS('B0.8.Online'!L:L,'B0.8.Online'!A:A,'B0.SUM (tuần 0)'!$A12) -> 0 | AG12: =SUM(AH12:AN12) -> 0 | AI12: =SUMIFS('B0.3.XK'!M:M,'B0.3.XK'!A:A,'B0.SUM (tuần 0)'!$A12) -> 0 | AK12: =SUMIFS('B0.5.GT2'!M:M,'B0.5.GT2'!A:A,'B0.SUM (tuần 0)'!$A12) -> 0 | AL12: =SUMIFS('B0.4.OEM'!M:M,'B0.4.OEM'!A:A,'B0.SUM (tuần 0)'!$A12) -> 0 | AN12: =SUMIFS('B0.8.Online'!M:M,'B0.8.Online'!A:A,'B0.SUM (tuần 0)'!$A12) -> 0 | AP12: =SUMIFS('B1.SUM (tuần 4)'!$I:$I,'B1.SUM (tuần 4)'!$A:$A,'B0.SUM (tuần 0)'!$A12) -> 0 | AQ12: =I12-AP12 -> 0
A13: 1001020019 | B13: Bộ lọc thô 1 stage GRANDSAFE | C13: Prefilter1S10" | D13: Máy TCM Sx | E13: Bộ lọc thô | F13: XK | H13: 152860 | I13: =SUM(J13:P13) -> 0 | K13: =SUMIFS('B0.3.XK'!J:J,'B0.3.XK'!A:A,'B0.SUM (tuần 0)'!$A13) -> 0 | M13: =SUMIFS('B0.5.GT2'!K:K,'B0.5.GT2'!A:A,'B0.SUM (tuần 0)'!$A13) -> 0 | N13: =SUMIFS('B0.4.OEM'!J:J,'B0.4.OEM'!A:A,'B0.SUM (tuần 0)'!$A13) -> 0 | P13: =SUMIFS('B0.8.Online'!J:J,'B0.8.Online'!A:A,'B0.SUM (tuần 0)'!$A13) -> 0 | Q13: =SUM(R13:X13) -> 0 | S13: =SUMIFS('B0.3.XK'!K:K,'B0.3.XK'!A:A,'B0.SUM (tuần 0)'!$A13) -> 0 | U13: =SUMIFS('B0.5.GT2'!K:K,'B0.5.GT2'!A:A,'B0.SUM (tuần 0)'!$A13) -> 0 | V13: =SUMIFS('B0.4.OEM'!K:K,'B0.4.OEM'!A:A,'B0.SUM (tuần 0)'!$A13) -> 0 | X13: =SUMIFS('B0.8.Online'!K:K,'B0.8.Online'!A:A,'B0.SUM (tuần 0)'!$A13) -> 0 | Y13: =SUM(Z13:AF13) -> 0 | AA13: =SUMIFS('B0.3.XK'!L:L,'B0.3.XK'!A:A,'B0.SUM (tuần 0)'!$A13) -> 0 | AC13: =SUMIFS('B0.5.GT2'!L:L,'B0.5.GT2'!A:A,'B0.SUM (tuần 0)'!$A13) -> 0 | AD13: =SUMIFS('B0.4.OEM'!L:L,'B0.4.OEM'!A:A,'B0.SUM (tuần 0)'!$A13) -> 0 | AF13: =SUMIFS('B0.8.Online'!L:L,'B0.8.Online'!A:A,'B0.SUM (tuần 0)'!$A13) -> 0 | AG13: =SUM(AH13:AN13) -> 0 | AI13: =SUMIFS('B0.3.XK'!M:M,'B0.3.XK'!A:A,'B0.SUM (tuần 0)'!$A13) -> 0 | AK13: =SUMIFS('B0.5.GT2'!M:M,'B0.5.GT2'!A:A,'B0.SUM (tuần 0)'!$A13) -> 0 | AL13: =SUMIFS('B0.4.OEM'!M:M,'B0.4.OEM'!A:A,'B0.SUM (tuần 0)'!$A13) -> 0 | AN13: =SUMIFS('B0.8.Online'!M:M,'B0.8.Online'!A:A,'B0.SUM (tuần 0)'!$A13) -> 0 | AO13: Hàng clear, CEO yêu cầu dừng mã | AP13: =SUMIFS('B1.SUM (tuần 4)'!$I:$I,'B1.SUM (tuần 4)'!$A:$A,'B0.SUM (tuần 0)'!$A13) -> 0 | AQ13: =I13-AP13 -> 0
A14: 1001020027 | B14: Bộ lọc thô 1 stage AQUALAND | C14: Prefilter1S10" | D14: Máy TCM Sx | E14: Bộ lọc thô | F14: XK | H14: 132865 | I14: =SUM(J14:P14) -> 0 | K14: =SUMIFS('B0.3.XK'!J:J,'B0.3.XK'!A:A,'B0.SUM (tuần 0)'!$A14) -> 0 | M14: =SUMIFS('B0.5.GT2'!K:K,'B0.5.GT2'!A:A,'B0.SUM (tuần 0)'!$A14) -> 0 | N14: =SUMIFS('B0.4.OEM'!J:J,'B0.4.OEM'!A:A,'B0.SUM (tuần 0)'!$A14) -> 0 | P14: =SUMIFS('B0.8.Online'!J:J,'B0.8.Online'!A:A,'B0.SUM (tuần 0)'!$A14) -> 0 | Q14: =SUM(R14:X14) -> 0 | S14: =SUMIFS('B0.3.XK'!K:K,'B0.3.XK'!A:A,'B0.SUM (tuần 0)'!$A14) -> 0 | U14: =SUMIFS('B0.5.GT2'!K:K,'B0.5.GT2'!A:A,'B0.SUM (tuần 0)'!$A14) -> 0 | V14: =SUMIFS('B0.4.OEM'!K:K,'B0.4.OEM'!A:A,'B0.SUM (tuần 0)'!$A14) -> 0 | X14: =SUMIFS('B0.8.Online'!K:K,'B0.8.Online'!A:A,'B0.SUM (tuần 0)'!$A14) -> 0 | Y14: =SUM(Z14:AF14) -> 0 | AA14: =SUMIFS('B0.3.XK'!L:L,'B0.3.XK'!A:A,'B0.SUM (tuần 0)'!$A14) -> 0 | AC14: =SUMIFS('B0.5.GT2'!L:L,'B0.5.GT2'!A:A,'B0.SUM (tuần 0)'!$A14) -> 0 | AD14: =SUMIFS('B0.4.OEM'!L:L,'B0.4.OEM'!A:A,'B0.SUM (tuần 0)'!$A14) -> 0 | AF14: =SUMIFS('B0.8.Online'!L:L,'B0.8.Online'!A:A,'B0.SUM (tuần 0)'!$A14) -> 0 | AG14: =SUM(AH14:AN14) -> 0 | AI14: =SUMIFS('B0.3.XK'!M:M,'B0.3.XK'!A:A,'B0.SUM (tuần 0)'!$A14) -> 0 | AK14: =SUMIFS('B0.5.GT2'!M:M,'B0.5.GT2'!A:A,'B0.SUM (tuần 0)'!$A14) -> 0 | AL14: =SUMIFS('B0.4.OEM'!M:M,'B0.4.OEM'!A:A,'B0.SUM (tuần 0)'!$A14) -> 0 | AN14: =SUMIFS('B0.8.Online'!M:M,'B0.8.Online'!A:A,'B0.SUM (tuần 0)'!$A14) -> 0 | AP14: =SUMIFS('B1.SUM (tuần 4)'!$I:$I,'B1.SUM (tuần 4)'!$A:$A,'B0.SUM (tuần 0)'!$A14) -> 0 | AQ14: =I14-AP14 -> 0
A15: 1001040396 | B15: Water purifier KAROFI S-s156 MT (KBA) | C15: S-S156 | D15: Máy TCM Sx | E15: BCN | F15: XK | H15: 5393516 | I15: =SUM(J15:P15) -> 0 | K15: =SUMIFS('B0.3.XK'!J:J,'B0.3.XK'!A:A,'B0.SUM (tuần 0)'!$A15) -> 0 | M15: =SUMIFS('B0.5.GT2'!K:K,'B0.5.GT2'!A:A,'B0.SUM (tuần 0)'!$A15) -> 0 | N15: =SUMIFS('B0.4.OEM'!J:J,'B0.4.OEM'!A:A,'B0.SUM (tuần 0)'!$A15) -> 0 | P15: =SUMIFS('B0.8.Online'!J:J,'B0.8.Online'!A:A,'B0.SUM (tuần 0)'!$A15) -> 0 | Q15: =SUM(R15:X15) -> 0 | S15: =SUMIFS('B0.3.XK'!K:K,'B0.3.XK'!A:A,'B0.SUM (tuần 0)'!$A15) -> 0 | U15: =SUMIFS('B0.5.GT2'!K:K,'B0.5.GT2'!A:A,'B0.SUM (tuần 0)'!$A15) -> 0 | V15: =SUMIFS('B0.4.OEM'!K:K,'B0.4.OEM'!A:A,'B0.SUM (tuần 0)'!$A15) -> 0 | X15: =SUMIFS('B0.8.Online'!K:K,'B0.8.Online'!A:A,'B0.SUM (tuần 0)'!$A15) -> 0 | Y15: =SUM(Z15:AF15) -> 0 | AA15: =SUMIFS('B0.3.XK'!L:L,'B0.3.XK'!A:A,'B0.SUM (tuần 0)'!$A15) -> 0 | AC15: =SUMIFS('B0.5.GT2'!L:L,'B0.5.GT2'!A:A,'B0.SUM (tuần 0)'!$A15) -> 0 | AD15: =SUMIFS('B0.4.OEM'!L:L,'B0.4.OEM'!A:A,'B0.SUM (tuần 0)'!$A15) -> 0 | AF15: =SUMIFS('B0.8.Online'!L:L,'B0.8.Online'!A:A,'B0.SUM (tuần 0)'!$A15) -> 0 | AG15: =SUM(AH15:AN15) -> 0 | AI15: =SUMIFS('B0.3.XK'!M:M,'B0.3.XK'!A:A,'B0.SUM (tuần 0)'!$A15) -> 0 | AK15: =SUMIFS('B0.5.GT2'!M:M,'B0.5.GT2'!A:A,'B0.SUM (tuần 0)'!$A15) -> 0 | AL15: =SUMIFS('B0.4.OEM'!M:M,'B0.4.OEM'!A:A,'B0.SUM (tuần 0)'!$A15) -> 0 | AN15: =SUMIFS('B0.8.Online'!M:M,'B0.8.Online'!A:A,'B0.SUM (tuần 0)'!$A15) -> 0 | AP15: =SUMIFS('B1.SUM (tuần 4)'!$I:$I,'B1.SUM (tuần 4)'!$A:$A,'B0.SUM (tuần 0)'!$A15) -> 0 | AQ15: =I15-AP15 -> 0
A16: 1001040483 | B16: Máy lọc nước KAROFI KAQ-X16 | C16: KAQ-X16 | D16: Máy TCM Sx | E16: 10L Tủ | F16: XK | H16: 2853039 | I16: =SUM(J16:P16) -> 0 | K16: =SUMIFS('B0.3.XK'!J:J,'B0.3.XK'!A:A,'B0.SUM (tuần 0)'!$A16) -> 0 | M16: =SUMIFS('B0.5.GT2'!K:K,'B0.5.GT2'!A:A,'B0.SUM (tuần 0)'!$A16) -> 0 | N16: =SUMIFS('B0.4.OEM'!J:J,'B0.4.OEM'!A:A,'B0.SUM (tuần 0)'!$A16) -> 0 | P16: =SUMIFS('B0.8.Online'!J:J,'B0.8.Online'!A:A,'B0.SUM (tuần 0)'!$A16) -> 0 | Q16: =SUM(R16:X16) -> 0 | S16: =SUMIFS('B0.3.XK'!K:K,'B0.3.XK'!A:A,'B0.SUM (tuần 0)'!$A16) -> 0 | U16: =SUMIFS('B0.5.GT2'!K:K,'B0.5.GT2'!A:A,'B0.SUM (tuần 0)'!$A16) -> 0 | V16: =SUMIFS('B0.4.OEM'!K:K,'B0.4.OEM'!A:A,'B0.SUM (tuần 0)'!$A16) -> 0 | X16: =SUMIFS('B0.8.Online'!K:K,'B0.8.Online'!A:A,'B0.SUM (tuần 0)'!$A16) -> 0 | Y16: =SUM(Z16:AF16) -> 0 | AA16: =SUMIFS('B0.3.XK'!L:L,'B0.3.XK'!A:A,'B0.SUM (tuần 0)'!$A16) -> 0 | AC16: =SUMIFS('B0.5.GT2'!L:L,'B0.5.GT2'!A:A,'B0.SUM (tuần 0)'!$A16) -> 0 | AD16: =SUMIFS('B0.4.OEM'!L:L,'B0.4.OEM'!A:A,'B0.SUM (tuần 0)'!$A16) -> 0 | AF16: =SUMIFS('B0.8.Online'!L:L,'B0.8.Online'!A:A,'B0.SUM (tuần 0)'!$A16) -> 0 | AG16: =SUM(AH16:AN16) -> 0 | AI16: =SUMIFS('B0.3.XK'!M:M,'B0.3.XK'!A:A,'B0.SUM (tuần 0)'!$A16) -> 0 | AK16: =SUMIFS('B0.5.GT2'!M:M,'B0.5.GT2'!A:A,'B0.SUM (tuần 0)'!$A16) -> 0 | AL16: =SUMIFS('B0.4.OEM'!M:M,'B0.4.OEM'!A:A,'B0.SUM (tuần 0)'!$A16) -> 0 | AN16: =SUMIFS('B0.8.Online'!M:M,'B0.8.Online'!A:A,'B0.SUM (tuần 0)'!$A16) -> 0 | AP16: =SUMIFS('B1.SUM (tuần 4)'!$I:$I,'B1.SUM (tuần 4)'!$A:$A,'B0.SUM (tuần 0)'!$A16) -> 0 | AQ16: =I16-AP16 -> 0
A17: 1001040513 | B17: Máy lọc nước nóng lạnh KAROFI HCV-208RO | C17: HCV-208RO | D17: Máy TCM Sx | E17: Block | F17: XK | H17: 2044274 | I17: =SUM(J17:P17) -> 30 | K17: =SUMIFS('B0.3.XK'!J:J,'B0.3.XK'!A:A,'B0.SUM (tuần 0)'!$A17) -> 30 | M17: =SUMIFS('B0.5.GT2'!K:K,'B0.5.GT2'!A:A,'B0.SUM (tuần 0)'!$A17) -> 0 | N17: =SUMIFS('B0.4.OEM'!J:J,'B0.4.OEM'!A:A,'B0.SUM (tuần 0)'!$A17) -> 0 | P17: =SUMIFS('B0.8.Online'!J:J,'B0.8.Online'!A:A,'B0.SUM (tuần 0)'!$A17) -> 0 | Q17: =SUM(R17:X17) -> 0 | S17: =SUMIFS('B0.3.XK'!K:K,'B0.3.XK'!A:A,'B0.SUM (tuần 0)'!$A17) -> 0 | U17: =SUMIFS('B0.5.GT2'!K:K,'B0.5.GT2'!A:A,'B0.SUM (tuần 0)'!$A17) -> 0 | V17: =SUMIFS('B0.4.OEM'!K:K,'B0.4.OEM'!A:A,'B0.SUM (tuần 0)'!$A17) -> 0 | X17: =SUMIFS('B0.8.Online'!K:K,'B0.8.Online'!A:A,'B0.SUM (tuần 0)'!$A17) -> 0 | Y17: =SUM(Z17:AF17) -> 0 | AA17: =SUMIFS('B0.3.XK'!L:L,'B0.3.XK'!A:A,'B0.SUM (tuần 0)'!$A17) -> 0 | AC17: =SUMIFS('B0.5.GT2'!L:L,'B0.5.GT2'!A:A,'B0.SUM (tuần 0)'!$A17) -> 0 | AD17: =SUMIFS('B0.4.OEM'!L:L,'B0.4.OEM'!A:A,'B0.SUM (tuần 0)'!$A17) -> 0 | AF17: =SUMIFS('B0.8.Online'!L:L,'B0.8.Online'!A:A,'B0.SUM (tuần 0)'!$A17) -> 0 | AG17: =SUM(AH17:AN17) -> 0 | AI17: =SUMIFS('B0.3.XK'!M:M,'B0.3.XK'!A:A,'B0.SUM (tuần 0)'!$A17) -> 0 | AK17: =SUMIFS('B0.5.GT2'!M:M,'B0.5.GT2'!A:A,'B0.SUM (tuần 0)'!$A17) -> 0 | AL17: =SUMIFS('B0.4.OEM'!M:M,'B0.4.OEM'!A:A,'B0.SUM (tuần 0)'!$A17) -> 0 | AN17: =SUMIFS('B0.8.Online'!M:M,'B0.8.Online'!A:A,'B0.SUM (tuần 0)'!$A17) -> 0 | AP17: =SUMIFS('B1.SUM (tuần 4)'!$I:$I,'B1.SUM (tuần 4)'!$A:$A,'B0.SUM (tuần 0)'!$A17) -> 0 | AQ17: =I17-AP17 -> 30
A18: 1001040537 | B18: Máy lọc nước KAROFI KAQ-U05 Pro | C18: KAQ-U05 Pro | D18: Máy TCM Sx | E18: 10L | F18: XK | H18: 1310192 | I18: =SUM(J18:P18) -> 0 | K18: =SUMIFS('B0.3.XK'!J:J,'B0.3.XK'!A:A,'B0.SUM (tuần 0)'!$A18) -> 0 | M18: =SUMIFS('B0.5.GT2'!K:K,'B0.5.GT2'!A:A,'B0.SUM (tuần 0)'!$A18) -> 0 | N18: =SUMIFS('B0.4.OEM'!J:J,'B0.4.OEM'!A:A,'B0.SUM (tuần 0)'!$A18) -> 0 | P18: =SUMIFS('B0.8.Online'!J:J,'B0.8.Online'!A:A,'B0.SUM (tuần 0)'!$A18) -> 0 | Q18: =SUM(R18:X18) -> 0 | S18: =SUMIFS('B0.3.XK'!K:K,'B0.3.XK'!A:A,'B0.SUM (tuần 0)'!$A18) -> 0 | U18: =SUMIFS('B0.5.GT2'!K:K,'B0.5.GT2'!A:A,'B0.SUM (tuần 0)'!$A18) -> 0 | V18: =SUMIFS('B0.4.OEM'!K:K,'B0.4.OEM'!A:A,'B0.SUM (tuần 0)'!$A18) -> 0 | X18: =SUMIFS('B0.8.Online'!K:K,'B0.8.Online'!A:A,'B0.SUM (tuần 0)'!$A18) -> 0 | Y18: =SUM(Z18:AF18) -> 0 | AA18: =SUMIFS('B0.3.XK'!L:L,'B0.3.XK'!A:A,'B0.SUM (tuần 0)'!$A18) -> 0 | AC18: =SUMIFS('B0.5.GT2'!L:L,'B0.5.GT2'!A:A,'B0.SUM (tuần 0)'!$A18) -> 0 | AD18: =SUMIFS('B0.4.OEM'!L:L,'B0.4.OEM'!A:A,'B0.SUM (tuần 0)'!$A18) -> 0 | AF18: =SUMIFS('B0.8.Online'!L:L,'B0.8.Online'!A:A,'B0.SUM (tuần 0)'!$A18) -> 0 | AG18: =SUM(AH18:AN18) -> 0 | AI18: =SUMIFS('B0.3.XK'!M:M,'B0.3.XK'!A:A,'B0.SUM (tuần 0)'!$A18) -> 0 | AK18: =SUMIFS('B0.5.GT2'!M:M,'B0.5.GT2'!A:A,'B0.SUM (tuần 0)'!$A18) -> 0 | AL18: =SUMIFS('B0.4.OEM'!M:M,'B0.4.OEM'!A:A,'B0.SUM (tuần 0)'!$A18) -> 0 | AN18: =SUMIFS('B0.8.Online'!M:M,'B0.8.Online'!A:A,'B0.SUM (tuần 0)'!$A18) -> 0 | AP18: =SUMIFS('B1.SUM (tuần 4)'!$I:$I,'B1.SUM (tuần 4)'!$A:$A,'B0.SUM (tuần 0)'!$A18) -> 0 | AQ18: =I18-AP18 -> 0
A19: 1001040549 | B19: Máy lọc nước nóng lạnh KAROFI KAD-X58 | C19: KAD-X58 | D19: Máy TCM Sx | E19: Block | F19: XK | H19: 4505559 | I19: =SUM(J19:P19) -> 0 | K19: =SUMIFS('B0.3.XK'!J:J,'B0.3.XK'!A:A,'B0.SUM (tuần 0)'!$A19) -> 0 | M19: =SUMIFS('B0.5.GT2'!K:K,'B0.5.GT2'!A:A,'B0.SUM (tuần 0)'!$A19) -> 0 | N19: =SUMIFS('B0.4.OEM'!J:J,'B0.4.OEM'!A:A,'B0.SUM (tuần 0)'!$A19) -> 0 | P19: =SUMIFS('B0.8.Online'!J:J,'B0.8.Online'!A:A,'B0.SUM (tuần 0)'!$A19) -> 0 | Q19: =SUM(R19:X19) -> 0 | S19: =SUMIFS('B0.3.XK'!K:K,'B0.3.XK'!A:A,'B0.SUM (tuần 0)'!$A19) -> 0 | U19: =SUMIFS('B0.5.GT2'!K:K,'B0.5.GT2'!A:A,'B0.SUM (tuần 0)'!$A19) -> 0 | V19: =SUMIFS('B0.4.OEM'!K:K,'B0.4.OEM'!A:A,'B0.SUM (tuần 0)'!$A19) -> 0 | X19: =SUMIFS('B0.8.Online'!K:K,'B0.8.Online'!A:A,'B0.SUM (tuần 0)'!$A19) -> 0 | Y19: =SUM(Z19:AF19) -> 20 | AA19: =SUMIFS('B0.3.XK'!L:L,'B0.3.XK'!A:A,'B0.SUM (tuần 0)'!$A19) -> 20 | AC19: =SUMIFS('B0.5.GT2'!L:L,'B0.5.GT2'!A:A,'B0.SUM (tuần 0)'!$A19) -> 0 | AD19: =SUMIFS('B0.4.OEM'!L:L,'B0.4.OEM'!A:A,'B0.SUM (tuần 0)'!$A19) -> 0 | AF19: =SUMIFS('B0.8.Online'!L:L,'B0.8.Online'!A:A,'B0.SUM (tuần 0)'!$A19) -> 0 | AG19: =SUM(AH19:AN19) -> 0 | AI19: =SUMIFS('B0.3.XK'!M:M,'B0.3.XK'!A:A,'B0.SUM (tuần 0)'!$A19) -> 0 | AK19: =SUMIFS('B0.5.GT2'!M:M,'B0.5.GT2'!A:A,'B0.SUM (tuần 0)'!$A19) -> 0 | AL19: =SUMIFS('B0.4.OEM'!M:M,'B0.4.OEM'!A:A,'B0.SUM (tuần 0)'!$A19) -> 0 | AN19: =SUMIFS('B0.8.Online'!M:M,'B0.8.Online'!A:A,'B0.SUM (tuần 0)'!$A19) -> 0 | AP19: =SUMIFS('B1.SUM (tuần 4)'!$I:$I,'B1.SUM (tuần 4)'!$A:$A,'B0.SUM (tuần 0)'!$A19) -> 0 | AQ19: =I19-AP19 -> 0
A20: 1001040625 | B20: Máy LN-NL ion kiềm KRF KAE-S88 PROMAX | C20: S88 Promax | D20: Máy TCM Sx | E20: Block | F20: XK | H20: 13949475 | I20: =SUM(J20:P20) -> 0 | K20: =SUMIFS('B0.3.XK'!J:J,'B0.3.XK'!A:A,'B0.SUM (tuần 0)'!$A20) -> 0 | M20: =SUMIFS('B0.5.GT2'!K:K,'B0.5.GT2'!A:A,'B0.SUM (tuần 0)'!$A20) -> 0 | N20: =SUMIFS('B0.4.OEM'!J:J,'B0.4.OEM'!A:A,'B0.SUM (tuần 0)'!$A20) -> 0 | P20: =SUMIFS('B0.8.Online'!J:J,'B0.8.Online'!A:A,'B0.SUM (tuần 0)'!$A20) -> 0 | Q20: =SUM(R20:X20) -> 0 | S20: =SUMIFS('B0.3.XK'!K:K,'B0.3.XK'!A:A,'B0.SUM (tuần 0)'!$A20) -> 0 | U20: =SUMIFS('B0.5.GT2'!K:K,'B0.5.GT2'!A:A,'B0.SUM (tuần 0)'!$A20) -> 0 | V20: =SUMIFS('B0.4.OEM'!K:K,'B0.4.OEM'!A:A,'B0.SUM (tuần 0)'!$A20) -> 0 | X20: =SUMIFS('B0.8.Online'!K:K,'B0.8.Online'!A:A,'B0.SUM (tuần 0)'!$A20) -> 0 | Y20: =SUM(Z20:AF20) -> 0 | AA20: =SUMIFS('B0.3.XK'!L:L,'B0.3.XK'!A:A,'B0.SUM (tuần 0)'!$A20) -> 0 | AC20: =SUMIFS('B0.5.GT2'!L:L,'B0.5.GT2'!A:A,'B0.SUM (tuần 0)'!$A20) -> 0 | AD20: =SUMIFS('B0.4.OEM'!L:L,'B0.4.OEM'!A:A,'B0.SUM (tuần 0)'!$A20) -> 0 | AF20: =SUMIFS('B0.8.Online'!L:L,'B0.8.Online'!A:A,'B0.SUM (tuần 0)'!$A20) -> 0 | AG20: =SUM(AH20:AN20) -> 0 | AI20: =SUMIFS('B0.3.XK'!M:M,'B0.3.XK'!A:A,'B0.SUM (tuần 0)'!$A20) -> 0 | AK20: =SUMIFS('B0.5.GT2'!M:M,'B0.5.GT2'!A:A,'B0.SUM (tuần 0)'!$A20) -> 0 | AL20: =SUMIFS('B0.4.OEM'!M:M,'B0.4.OEM'!A:A,'B0.SUM (tuần 0)'!$A20) -> 0 | AN20: =SUMIFS('B0.8.Online'!M:M,'B0.8.Online'!A:A,'B0.SUM (tuần 0)'!$A20) -> 0 | AP20: =SUMIFS('B1.SUM (tuần 4)'!$I:$I,'B1.SUM (tuần 4)'!$A:$A,'B0.SUM (tuần 0)'!$A20) -> 0 | AQ20: =I20-AP20 -> 0
A21: 1001040673 | B21: Máy lọc tổng Karofi KTF-P02 (SF-T2) | C21: KTF-P02 | D21: Máy TCM Sx | E21: LK khác | F21: XK | H21: 9968336 | I21: =SUM(J21:P21) -> 0 | K21: =SUMIFS('B0.3.XK'!J:J,'B0.3.XK'!A:A,'B0.SUM (tuần 0)'!$A21) -> 0 | M21: =SUMIFS('B0.5.GT2'!K:K,'B0.5.GT2'!A:A,'B0.SUM (tuần 0)'!$A21) -> 0 | N21: =SUMIFS('B0.4.OEM'!J:J,'B0.4.OEM'!A:A,'B0.SUM (tuần 0)'!$A21) -> 0 | P21: =SUMIFS('B0.8.Online'!J:J,'B0.8.Online'!A:A,'B0.SUM (tuần 0)'!$A21) -> 0 | Q21: =SUM(R21:X21) -> 0 | S21: =SUMIFS('B0.3.XK'!K:K,'B0.3.XK'!A:A,'B0.SUM (tuần 0)'!$A21) -> 0 | U21: =SUMIFS('B0.5.GT2'!K:K,'B0.5.GT2'!A:A,'B0.SUM (tuần 0)'!$A21) -> 0 | V21: =SUMIFS('B0.4.OEM'!K:K,'B0.4.OEM'!A:A,'B0.SUM (tuần 0)'!$A21) -> 0 | X21: =SUMIFS('B0.8.Online'!K:K,'B0.8.Online'!A:A,'B0.SUM (tuần 0)'!$A21) -> 0 | Y21: =SUM(Z21:AF21) -> 0 | AA21: =SUMIFS('B0.3.XK'!L:L,'B0.3.XK'!A:A,'B0.SUM (tuần 0)'!$A21) -> 0 | AC21: =SUMIFS('B0.5.GT2'!L:L,'B0.5.GT2'!A:A,'B0.SUM (tuần 0)'!$A21) -> 0 | AD21: =SUMIFS('B0.4.OEM'!L:L,'B0.4.OEM'!A:A,'B0.SUM (tuần 0)'!$A21) -> 0 | AF21: =SUMIFS('B0.8.Online'!L:L,'B0.8.Online'!A:A,'B0.SUM (tuần 0)'!$A21) -> 0 | AG21: =SUM(AH21:AN21) -> 0 | AI21: =SUMIFS('B0.3.XK'!M:M,'B0.3.XK'!A:A,'B0.SUM (tuần 0)'!$A21) -> 0 | AK21: =SUMIFS('B0.5.GT2'!M:M,'B0.5.GT2'!A:A,'B0.SUM (tuần 0)'!$A21) -> 0 | AL21: =SUMIFS('B0.4.OEM'!M:M,'B0.4.OEM'!A:A,'B0.SUM (tuần 0)'!$A21) -> 0 | AN21: =SUMIFS('B0.8.Online'!M:M,'B0.8.Online'!A:A,'B0.SUM (tuần 0)'!$A21) -> 0 | AP21: =SUMIFS('B1.SUM (tuần 4)'!$I:$I,'B1.SUM (tuần 4)'!$A:$A,'B0.SUM (tuần 0)'!$A21) -> 0 | AQ21: =I21-AP21 -> 0
A22: 1001110006 | B22: MÁY RO-01 Tecomen 7S | C22: RO-01 | D22: Máy TCM Sx | E22: 10L | F22: XK | H22: 1735791 | I22: =SUM(J22:P22) -> 0 | K22: =SUMIFS('B0.3.XK'!J:J,'B0.3.XK'!A:A,'B0.SUM (tuần 0)'!$A22) -> 0 | M22: =SUMIFS('B0.5.GT2'!K:K,'B0.5.GT2'!A:A,'B0.SUM (tuần 0)'!$A22) -> 0 | N22: =SUMIFS('B0.4.OEM'!J:J,'B0.4.OEM'!A:A,'B0.SUM (tuần 0)'!$A22) -> 0 | P22: =SUMIFS('B0.8.Online'!J:J,'B0.8.Online'!A:A,'B0.SUM (tuần 0)'!$A22) -> 0 | Q22: =SUM(R22:X22) -> 0 | S22: =SUMIFS('B0.3.XK'!K:K,'B0.3.XK'!A:A,'B0.SUM (tuần 0)'!$A22) -> 0 | U22: =SUMIFS('B0.5.GT2'!K:K,'B0.5.GT2'!A:A,'B0.SUM (tuần 0)'!$A22) -> 0 | V22: =SUMIFS('B0.4.OEM'!K:K,'B0.4.OEM'!A:A,'B0.SUM (tuần 0)'!$A22) -> 0 | X22: =SUMIFS('B0.8.Online'!K:K,'B0.8.Online'!A:A,'B0.SUM (tuần 0)'!$A22) -> 0 | Y22: =SUM(Z22:AF22) -> 0 | AA22: =SUMIFS('B0.3.XK'!L:L,'B0.3.XK'!A:A,'B0.SUM (tuần 0)'!$A22) -> 0 | AC22: =SUMIFS('B0.5.GT2'!L:L,'B0.5.GT2'!A:A,'B0.SUM (tuần 0)'!$A22) -> 0 | AD22: =SUMIFS('B0.4.OEM'!L:L,'B0.4.OEM'!A:A,'B0.SUM (tuần 0)'!$A22) -> 0 | AF22: =SUMIFS('B0.8.Online'!L:L,'B0.8.Online'!A:A,'B0.SUM (tuần 0)'!$A22) -> 0 | AG22: =SUM(AH22:AN22) -> 0 | AI22: =SUMIFS('B0.3.XK'!M:M,'B0.3.XK'!A:A,'B0.SUM (tuần 0)'!$A22) -> 0 | AK22: =SUMIFS('B0.5.GT2'!M:M,'B0.5.GT2'!A:A,'B0.SUM (tuần 0)'!$A22) -> 0 | AL22: =SUMIFS('B0.4.OEM'!M:M,'B0.4.OEM'!A:A,'B0.SUM (tuần 0)'!$A22) -> 0 | AN22: =SUMIFS('B0.8.Online'!M:M,'B0.8.Online'!A:A,'B0.SUM (tuần 0)'!$A22) -> 0 | AP22: =SUMIFS('B1.SUM (tuần 4)'!$I:$I,'B1.SUM (tuần 4)'!$A:$A,'B0.SUM (tuần 0)'!$A22) -> 0 | AQ22: =I22-AP22 -> 0
A23: 1001110019 | B23: Máy lọc nước UNDERSINK GRANDSAFE | C23: S-S027 | D23: Máy TCM Sx | E23: 10L | F23: XK | H23: 2514694 | I23: =SUM(J23:P23) -> 0 | K23: =SUMIFS('B0.3.XK'!J:J,'B0.3.XK'!A:A,'B0.SUM (tuần 0)'!$A23) -> 0 | M23: =SUMIFS('B0.5.GT2'!K:K,'B0.5.GT2'!A:A,'B0.SUM (tuần 0)'!$A23) -> 0 | N23: =SUMIFS('B0.4.OEM'!J:J,'B0.4.OEM'!A:A,'B0.SUM (tuần 0)'!$A23) -> 0 | P23: =SUMIFS('B0.8.Online'!J:J,'B0.8.Online'!A:A,'B0.SUM (tuần 0)'!$A23) -> 0 | Q23: =SUM(R23:X23) -> 0 | S23: =SUMIFS('B0.3.XK'!K:K,'B0.3.XK'!A:A,'B0.SUM (tuần 0)'!$A23) -> 0 | U23: =SUMIFS('B0.5.GT2'!K:K,'B0.5.GT2'!A:A,'B0.SUM (tuần 0)'!$A23) -> 0 | V23: =SUMIFS('B0.4.OEM'!K:K,'B0.4.OEM'!A:A,'B0.SUM (tuần 0)'!$A23) -> 0 | X23: =SUMIFS('B0.8.Online'!K:K,'B0.8.Online'!A:A,'B0.SUM (tuần 0)'!$A23) -> 0 | Y23: =SUM(Z23:AF23) -> 120 | AA23: =SUMIFS('B0.3.XK'!L:L,'B0.3.XK'!A:A,'B0.SUM (tuần 0)'!$A23) -> 120 | AC23: =SUMIFS('B0.5.GT2'!L:L,'B0.5.GT2'!A:A,'B0.SUM (tuần 0)'!$A23) -> 0 | AD23: =SUMIFS('B0.4.OEM'!L:L,'B0.4.OEM'!A:A,'B0.SUM (tuần 0)'!$A23) -> 0 | AF23: =SUMIFS('B0.8.Online'!L:L,'B0.8.Online'!A:A,'B0.SUM (tuần 0)'!$A23) -> 0 | AG23: =SUM(AH23:AN23) -> 0 | AI23: =SUMIFS('B0.3.XK'!M:M,'B0.3.XK'!A:A,'B0.SUM (tuần 0)'!$A23) -> 0 | AK23: =SUMIFS('B0.5.GT2'!M:M,'B0.5.GT2'!A:A,'B0.SUM (tuần 0)'!$A23) -> 0 | AL23: =SUMIFS('B0.4.OEM'!M:M,'B0.4.OEM'!A:A,'B0.SUM (tuần 0)'!$A23) -> 0 | AN23: =SUMIFS('B0.8.Online'!M:M,'B0.8.Online'!A:A,'B0.SUM (tuần 0)'!$A23) -> 0 | AP23: =SUMIFS('B1.SUM (tuần 4)'!$I:$I,'B1.SUM (tuần 4)'!$A:$A,'B0.SUM (tuần 0)'!$A23) -> 0 | AQ23: =I23-AP23 -> 0
A24: 1001110020 | B24: Máy RO-100 GRANDSAFE | C24: RO-100 | D24: Máy TCM Sx | E24: 10L | F24: XK | H24: 2002968 | I24: =SUM(J24:P24) -> 0 | K24: =SUMIFS('B0.3.XK'!J:J,'B0.3.XK'!A:A,'B0.SUM (tuần 0)'!$A24) -> 0 | M24: =SUMIFS('B0.5.GT2'!K:K,'B0.5.GT2'!A:A,'B0.SUM (tuần 0)'!$A24) -> 0 | N24: =SUMIFS('B0.4.OEM'!J:J,'B0.4.OEM'!A:A,'B0.SUM (tuần 0)'!$A24) -> 0 | P24: =SUMIFS('B0.8.Online'!J:J,'B0.8.Online'!A:A,'B0.SUM (tuần 0)'!$A24) -> 0 | Q24: =SUM(R24:X24) -> 0 | S24: =SUMIFS('B0.3.XK'!K:K,'B0.3.XK'!A:A,'B0.SUM (tuần 0)'!$A24) -> 0 | U24: =SUMIFS('B0.5.GT2'!K:K,'B0.5.GT2'!A:A,'B0.SUM (tuần 0)'!$A24) -> 0 | V24: =SUMIFS('B0.4.OEM'!K:K,'B0.4.OEM'!A:A,'B0.SUM (tuần 0)'!$A24) -> 0 | X24: =SUMIFS('B0.8.Online'!K:K,'B0.8.Online'!A:A,'B0.SUM (tuần 0)'!$A24) -> 0 | Y24: =SUM(Z24:AF24) -> 70 | AA24: =SUMIFS('B0.3.XK'!L:L,'B0.3.XK'!A:A,'B0.SUM (tuần 0)'!$A24) -> 70 | AC24: =SUMIFS('B0.5.GT2'!L:L,'B0.5.GT2'!A:A,'B0.SUM (tuần 0)'!$A24) -> 0 | AD24: =SUMIFS('B0.4.OEM'!L:L,'B0.4.OEM'!A:A,'B0.SUM (tuần 0)'!$A24) -> 0 | AF24: =SUMIFS('B0.8.Online'!L:L,'B0.8.Online'!A:A,'B0.SUM (tuần 0)'!$A24) -> 0 | AG24: =SUM(AH24:AN24) -> 0 | AI24: =SUMIFS('B0.3.XK'!M:M,'B0.3.XK'!A:A,'B0.SUM (tuần 0)'!$A24) -> 0 | AK24: =SUMIFS('B0.5.GT2'!M:M,'B0.5.GT2'!A:A,'B0.SUM (tuần 0)'!$A24) -> 0 | AL24: =SUMIFS('B0.4.OEM'!M:M,'B0.4.OEM'!A:A,'B0.SUM (tuần 0)'!$A24) -> 0 | AN24: =SUMIFS('B0.8.Online'!M:M,'B0.8.Online'!A:A,'B0.SUM (tuần 0)'!$A24) -> 0 | AP24: =SUMIFS('B1.SUM (tuần 4)'!$I:$I,'B1.SUM (tuần 4)'!$A:$A,'B0.SUM (tuần 0)'!$A24) -> 0 | AQ24: =I24-AP24 -> 0
A25: 1001110035 | B25: Máy BCN-400 GPD ANMAX | C25: BCN-400 | D25: Máy TCM Sx | E25: BCN | F25: XK | H25: 4854165 | I25: =SUM(J25:P25) -> 0 | K25: =SUMIFS('B0.3.XK'!J:J,'B0.3.XK'!A:A,'B0.SUM (tuần 0)'!$A25) -> 0 | M25: =SUMIFS('B0.5.GT2'!K:K,'B0.5.GT2'!A:A,'B0.SUM (tuần 0)'!$A25) -> 0 | N25: =SUMIFS('B0.4.OEM'!J:J,'B0.4.OEM'!A:A,'B0.SUM (tuần 0)'!$A25) -> 0 | P25: =SUMIFS('B0.8.Online'!J:J,'B0.8.Online'!A:A,'B0.SUM (tuần 0)'!$A25) -> 0 | Q25: =SUM(R25:X25) -> 0 | S25: =SUMIFS('B0.3.XK'!K:K,'B0.3.XK'!A:A,'B0.SUM (tuần 0)'!$A25) -> 0 | U25: =SUMIFS('B0.5.GT2'!K:K,'B0.5.GT2'!A:A,'B0.SUM (tuần 0)'!$A25) -> 0 | V25: =SUMIFS('B0.4.OEM'!K:K,'B0.4.OEM'!A:A,'B0.SUM (tuần 0)'!$A25) -> 0 | X25: =SUMIFS('B0.8.Online'!K:K,'B0.8.Online'!A:A,'B0.SUM (tuần 0)'!$A25) -> 0 | Y25: =SUM(Z25:AF25) -> 0 | AA25: =SUMIFS('B0.3.XK'!L:L,'B0.3.XK'!A:A,'B0.SUM (tuần 0)'!$A25) -> 0 | AC25: =SUMIFS('B0.5.GT2'!L:L,'B0.5.GT2'!A:A,'B0.SUM (tuần 0)'!$A25) -> 0 | AD25: =SUMIFS('B0.4.OEM'!L:L,'B0.4.OEM'!A:A,'B0.SUM (tuần 0)'!$A25) -> 0 | AF25: =SUMIFS('B0.8.Online'!L:L,'B0.8.Online'!A:A,'B0.SUM (tuần 0)'!$A25) -> 0 | AG25: =SUM(AH25:AN25) -> 300 | AI25: =SUMIFS('B0.3.XK'!M:M,'B0.3.XK'!A:A,'B0.SUM (tuần 0)'!$A25) -> 300 | AK25: =SUMIFS('B0.5.GT2'!M:M,'B0.5.GT2'!A:A,'B0.SUM (tuần 0)'!$A25) -> 0 | AL25: =SUMIFS('B0.4.OEM'!M:M,'B0.4.OEM'!A:A,'B0.SUM (tuần 0)'!$A25) -> 0 | AN25: =SUMIFS('B0.8.Online'!M:M,'B0.8.Online'!A:A,'B0.SUM (tuần 0)'!$A25) -> 0 | AP25: =SUMIFS('B1.SUM (tuần 4)'!$I:$I,'B1.SUM (tuần 4)'!$A:$A,'B0.SUM (tuần 0)'!$A25) -> 0 | AQ25: =I25-AP25 -> 0
... A32: 1001110058 | B32: Máy RO-35 Tecomen (7S) | C32: RO-35 | D32: Máy TCM Sx | E32: 10L | F32: XK | H32: 1723294 | I32: =SUM(J32:P32) -> 0 | K32: =SUMIFS('B0.3.XK'!J:J,'B0.3.XK'!A:A,'B0.SUM (tuần 0)'!$A32) -> 0 | M32: =SUMIFS('B0.5.GT2'!K:K,'B0.5.GT2'!A:A,'B0.SUM (tuần 0)'!$A32) -> 0 | N32: =SUMIFS('B0.4.OEM'!J:J,'B0.4.OEM'!A:A,'B0.SUM (tuần 0)'!$A32) -> 0 | P32: =SUMIFS('B0.8.Online'!J:J,'B0.8.Online'!A:A,'B0.SUM (tuần 0)'!$A32) -> 0 | Q32: =SUM(R32:X32) -> 100 | S32: =SUMIFS('B0.3.XK'!K:K,'B0.3.XK'!A:A,'B0.SUM (tuần 0)'!$A32) -> 100 | U32: =SUMIFS('B0.5.GT2'!K:K,'B0.5.GT2'!A:A,'B0.SUM (tuần 0)'!$A32) -> 0 | V32: =SUMIFS('B0.4.OEM'!K:K,'B0.4.OEM'!A:A,'B0.SUM (tuần 0)'!$A32) -> 0 | X32: =SUMIFS('B0.8.Online'!K:K,'B0.8.Online'!A:A,'B0.SUM (tuần 0)'!$A32) -> 0 | Y32: =SUM(Z32:AF32) -> 0 | AA32: =SUMIFS('B0.3.XK'!L:L,'B0.3.XK'!A:A,'B0.SUM (tuần 0)'!$A32) -> 0 | AC32: =SUMIFS('B0.5.GT2'!L:L,'B0.5.GT2'!A:A,'B0.SUM (tuần 0)'!$A32) -> 0 | AD32: =SUMIFS('B0.4.OEM'!L:L,'B0.4.OEM'!A:A,'B0.SUM (tuần 0)'!$A32) -> 0 | AF32: =SUMIFS('B0.8.Online'!L:L,'B0.8.Online'!A:A,'B0.SUM (tuần 0)'!$A32) -> 0 | AG32: =SUM(AH32:AN32) -> 0 | AI32: =SUMIFS('B0.3.XK'!M:M,'B0.3.XK'!A:A,'B0.SUM (tuần 0)'!$A32) -> 0 | AK32: =SUMIFS('B0.5.GT2'!M:M,'B0.5.GT2'!A:A,'B0.SUM (tuần 0)'!$A32) -> 0 | AL32: =SUMIFS('B0.4.OEM'!M:M,'B0.4.OEM'!A:A,'B0.SUM (tuần 0)'!$A32) -> 0 | AN32: =SUMIFS('B0.8.Online'!M:M,'B0.8.Online'!A:A,'B0.SUM (tuần 0)'!$A32) -> 0 | AP32: =SUMIFS('B1.SUM (tuần 4)'!$I:$I,'B1.SUM (tuần 4)'!$A:$A,'B0.SUM (tuần 0)'!$A32) -> 0 | AQ32: =I32-AP32 -> 0
A33: 1001110083 | B33: Máy lọc nước UNDERSINK đen v3 PURE LIFE | C33: S-S027 | D33: Máy TCM Sx | E33: 10L | F33: XK | H33: 2275801 | I33: =SUM(J33:P33) -> 0 | K33: =SUMIFS('B0.3.XK'!J:J,'B0.3.XK'!A:A,'B0.SUM (tuần 0)'!$A33) -> 0 | M33: =SUMIFS('B0.5.GT2'!K:K,'B0.5.GT2'!A:A,'B0.SUM (tuần 0)'!$A33) -> 0 | N33: =SUMIFS('B0.4.OEM'!J:J,'B0.4.OEM'!A:A,'B0.SUM (tuần 0)'!$A33) -> 0 | P33: =SUMIFS('B0.8.Online'!J:J,'B0.8.Online'!A:A,'B0.SUM (tuần 0)'!$A33) -> 0 | Q33: =SUM(R33:X33) -> 0 | S33: =SUMIFS('B0.3.XK'!K:K,'B0.3.XK'!A:A,'B0.SUM (tuần 0)'!$A33) -> 0 | U33: =SUMIFS('B0.5.GT2'!K:K,'B0.5.GT2'!A:A,'B0.SUM (tuần 0)'!$A33) -> 0 | V33: =SUMIFS('B0.4.OEM'!K:K,'B0.4.OEM'!A:A,'B0.SUM (tuần 0)'!$A33) -> 0 | X33: =SUMIFS('B0.8.Online'!K:K,'B0.8.Online'!A:A,'B0.SUM (tuần 0)'!$A33) -> 0 | Y33: =SUM(Z33:AF33) -> 400 | AA33: =SUMIFS('B0.3.XK'!L:L,'B0.3.XK'!A:A,'B0.SUM (tuần 0)'!$A33) -> 400 | AC33: =SUMIFS('B0.5.GT2'!L:L,'B0.5.GT2'!A:A,'B0.SUM (tuần 0)'!$A33) -> 0 | AD33: =SUMIFS('B0.4.OEM'!L:L,'B0.4.OEM'!A:A,'B0.SUM (tuần 0)'!$A33) -> 0 | AF33: =SUMIFS('B0.8.Online'!L:L,'B0.8.Online'!A:A,'B0.SUM (tuần 0)'!$A33) -> 0 | AG33: =SUM(AH33:AN33) -> 0 | AI33: =SUMIFS('B0.3.XK'!M:M,'B0.3.XK'!A:A,'B0.SUM (tuần 0)'!$A33) -> 0 | AK33: =SUMIFS('B0.5.GT2'!M:M,'B0.5.GT2'!A:A,'B0.SUM (tuần 0)'!$A33) -> 0 | AL33: =SUMIFS('B0.4.OEM'!M:M,'B0.4.OEM'!A:A,'B0.SUM (tuần 0)'!$A33) -> 0 | AN33: =SUMIFS('B0.8.Online'!M:M,'B0.8.Online'!A:A,'B0.SUM (tuần 0)'!$A33) -> 0 | AP33: =SUMIFS('B1.SUM (tuần 4)'!$I:$I,'B1.SUM (tuần 4)'!$A:$A,'B0.SUM (tuần 0)'!$A33) -> 0 | AQ33: =I33-AP33 -> 0
A34: 1001110086 | B34: Bộ lọc thô 1 stage PURE LIFE | C34: Prefilter1S10" | D34: Máy TCM Sx | E34: Bộ lọc thô | F34: XK | H34: 124446 | I34: =SUM(J34:P34) -> 0 | K34: =SUMIFS('B0.3.XK'!J:J,'B0.3.XK'!A:A,'B0.SUM (tuần 0)'!$A34) -> 0 | M34: =SUMIFS('B0.5.GT2'!K:K,'B0.5.GT2'!A:A,'B0.SUM (tuần 0)'!$A34) -> 0 | N34: =SUMIFS('B0.4.OEM'!J:J,'B0.4.OEM'!A:A,'B0.SUM (tuần 0)'!$A34) -> 0 | P34: =SUMIFS('B0.8.Online'!J:J,'B0.8.Online'!A:A,'B0.SUM (tuần 0)'!$A34) -> 0 | Q34: =SUM(R34:X34) -> 0 | S34: =SUMIFS('B0.3.XK'!K:K,'B0.3.XK'!A:A,'B0.SUM (tuần 0)'!$A34) -> 0 | U34: =SUMIFS('B0.5.GT2'!K:K,'B0.5.GT2'!A:A,'B0.SUM (tuần 0)'!$A34) -> 0 | V34: =SUMIFS('B0.4.OEM'!K:K,'B0.4.OEM'!A:A,'B0.SUM (tuần 0)'!$A34) -> 0 | X34: =SUMIFS('B0.8.Online'!K:K,'B0.8.Online'!A:A,'B0.SUM (tuần 0)'!$A34) -> 0 | Y34: =SUM(Z34:AF34) -> 100 | AA34: =SUMIFS('B0.3.XK'!L:L,'B0.3.XK'!A:A,'B0.SUM (tuần 0)'!$A34) -> 100 | AC34: =SUMIFS('B0.5.GT2'!L:L,'B0.5.GT2'!A:A,'B0.SUM (tuần 0)'!$A34) -> 0 | AD34: =SUMIFS('B0.4.OEM'!L:L,'B0.4.OEM'!A:A,'B0.SUM (tuần 0)'!$A34) -> 0 | AF34: =SUMIFS('B0.8.Online'!L:L,'B0.8.Online'!A:A,'B0.SUM (tuần 0)'!$A34) -> 0 | AG34: =SUM(AH34:AN34) -> 0 | AI34: =SUMIFS('B0.3.XK'!M:M,'B0.3.XK'!A:A,'B0.SUM (tuần 0)'!$A34) -> 0 | AK34: =SUMIFS('B0.5.GT2'!M:M,'B0.5.GT2'!A:A,'B0.SUM (tuần 0)'!$A34) -> 0 | AL34: =SUMIFS('B0.4.OEM'!M:M,'B0.4.OEM'!A:A,'B0.SUM (tuần 0)'!$A34) -> 0 | AN34: =SUMIFS('B0.8.Online'!M:M,'B0.8.Online'!A:A,'B0.SUM (tuần 0)'!$A34) -> 0 | AP34: =SUMIFS('B1.SUM (tuần 4)'!$I:$I,'B1.SUM (tuần 4)'!$A:$A,'B0.SUM (tuần 0)'!$A34) -> 0 | AQ34: =I34-AP34 -> 0
A35: 1001110088 | B35: Bộ lọc thô 3 stages Pure Life | C35: Prefilter3S10" | D35: Máy TCM Sx | E35: Bộ lọc thô | F35: XK | H35: 400699 | I35: =SUM(J35:P35) -> 0 | K35: =SUMIFS('B0.3.XK'!J:J,'B0.3.XK'!A:A,'B0.SUM (tuần 0)'!$A35) -> 0 | M35: =SUMIFS('B0.5.GT2'!K:K,'B0.5.GT2'!A:A,'B0.SUM (tuần 0)'!$A35) -> 0 | N35: =SUMIFS('B0.4.OEM'!J:J,'B0.4.OEM'!A:A,'B0.SUM (tuần 0)'!$A35) -> 0 | P35: =SUMIFS('B0.8.Online'!J:J,'B0.8.Online'!A:A,'B0.SUM (tuần 0)'!$A35) -> 0 | Q35: =SUM(R35:X35) -> 0 | S35: =SUMIFS('B0.3.XK'!K:K,'B0.3.XK'!A:A,'B0.SUM (tuần 0)'!$A35) -> 0 | U35: =SUMIFS('B0.5.GT2'!K:K,'B0.5.GT2'!A:A,'B0.SUM (tuần 0)'!$A35) -> 0 | V35: =SUMIFS('B0.4.OEM'!K:K,'B0.4.OEM'!A:A,'B0.SUM (tuần 0)'!$A35) -> 0 | X35: =SUMIFS('B0.8.Online'!K:K,'B0.8.Online'!A:A,'B0.SUM (tuần 0)'!$A35) -> 0 | Y35: =SUM(Z35:AF35) -> 100 | AA35: =SUMIFS('B0.3.XK'!L:L,'B0.3.XK'!A:A,'B0.SUM (tuần 0)'!$A35) -> 100 | AC35: =SUMIFS('B0.5.GT2'!L:L,'B0.5.GT2'!A:A,'B0.SUM (tuần 0)'!$A35) -> 0 | AD35: =SUMIFS('B0.4.OEM'!L:L,'B0.4.OEM'!A:A,'B0.SUM (tuần 0)'!$A35) -> 0 | AF35: =SUMIFS('B0.8.Online'!L:L,'B0.8.Online'!A:A,'B0.SUM (tuần 0)'!$A35) -> 0 | AG35: =SUM(AH35:AN35) -> 0 | AI35: =SUMIFS('B0.3.XK'!M:M,'B0.3.XK'!A:A,'B0.SUM (tuần 0)'!$A35) -> 0 | AK35: =SUMIFS('B0.5.GT2'!M:M,'B0.5.GT2'!A:A,'B0.SUM (tuần 0)'!$A35) -> 0 | AL35: =SUMIFS('B0.4.OEM'!M:M,'B0.4.OEM'!A:A,'B0.SUM (tuần 0)'!$A35) -> 0 | AN35: =SUMIFS('B0.8.Online'!M:M,'B0.8.Online'!A:A,'B0.SUM (tuần 0)'!$A35) -> 0 | AP35: =SUMIFS('B1.SUM (tuần 4)'!$I:$I,'B1.SUM (tuần 4)'!$A:$A,'B0.SUM (tuần 0)'!$A35) -> 0 | AQ35: =I35-AP35 -> 0
A36: 1001110090 | B36: Máy RO BCN-300 Tecomen | C36: BCN-300 | D36: Máy TCM Sx | E36: BCN | F36: XK | H36: 6081518 | I36: =SUM(J36:P36) -> 0 | K36: =SUMIFS('B0.3.XK'!J:J,'B0.3.XK'!A:A,'B0.SUM (tuần 0)'!$A36) -> 0 | M36: =SUMIFS('B0.5.GT2'!K:K,'B0.5.GT2'!A:A,'B0.SUM (tuần 0)'!$A36) -> 0 | N36: =SUMIFS('B0.4.OEM'!J:J,'B0.4.OEM'!A:A,'B0.SUM (tuần 0)'!$A36) -> 0 | P36: =SUMIFS('B0.8.Online'!J:J,'B0.8.Online'!A:A,'B0.SUM (tuần 0)'!$A36) -> 0 | Q36: =SUM(R36:X36) -> 0 | S36: =SUMIFS('B0.3.XK'!K:K,'B0.3.XK'!A:A,'B0.SUM (tuần 0)'!$A36) -> 0 | U36: =SUMIFS('B0.5.GT2'!K:K,'B0.5.GT2'!A:A,'B0.SUM (tuần 0)'!$A36) -> 0 | V36: =SUMIFS('B0.4.OEM'!K:K,'B0.4.OEM'!A:A,'B0.SUM (tuần 0)'!$A36) -> 0 | X36: =SUMIFS('B0.8.Online'!K:K,'B0.8.Online'!A:A,'B0.SUM (tuần 0)'!$A36) -> 0 | Y36: =SUM(Z36:AF36) -> 0 | AA36: =SUMIFS('B0.3.XK'!L:L,'B0.3.XK'!A:A,'B0.SUM (tuần 0)'!$A36) -> 0 | AC36: =SUMIFS('B0.5.GT2'!L:L,'B0.5.GT2'!A:A,'B0.SUM (tuần 0)'!$A36) -> 0 | AD36: =SUMIFS('B0.4.OEM'!L:L,'B0.4.OEM'!A:A,'B0.SUM (tuần 0)'!$A36) -> 0 | AF36: =SUMIFS('B0.8.Online'!L:L,'B0.8.Online'!A:A,'B0.SUM (tuần 0)'!$A36) -> 0 | AG36: =SUM(AH36:AN36) -> 0 | AI36: =SUMIFS('B0.3.XK'!M:M,'B0.3.XK'!A:A,'B0.SUM (tuần 0)'!$A36) -> 0 | AK36: =SUMIFS('B0.5.GT2'!M:M,'B0.5.GT2'!A:A,'B0.SUM (tuần 0)'!$A36) -> 0 | AL36: =SUMIFS('B0.4.OEM'!M:M,'B0.4.OEM'!A:A,'B0.SUM (tuần 0)'!$A36) -> 0 | AN36: =SUMIFS('B0.8.Online'!M:M,'B0.8.Online'!A:A,'B0.SUM (tuần 0)'!$A36) -> 0 | AP36: =SUMIFS('B1.SUM (tuần 4)'!$I:$I,'B1.SUM (tuần 4)'!$A:$A,'B0.SUM (tuần 0)'!$A36) -> 0 | AQ36: =I36-AP36 -> 0
A37: 1001110092 | B37: Máy RO Undersink US | C37: UDSUS | D37: Máy TCM Sx | E37: 10L | F37: XK | H37: 1595034 | I37: =SUM(J37:P37) -> 0 | K37: =SUMIFS('B0.3.XK'!J:J,'B0.3.XK'!A:A,'B0.SUM (tuần 0)'!$A37) -> 0 | M37: =SUMIFS('B0.5.GT2'!K:K,'B0.5.GT2'!A:A,'B0.SUM (tuần 0)'!$A37) -> 0 | N37: =SUMIFS('B0.4.OEM'!J:J,'B0.4.OEM'!A:A,'B0.SUM (tuần 0)'!$A37) -> 0 | P37: =SUMIFS('B0.8.Online'!J:J,'B0.8.Online'!A:A,'B0.SUM (tuần 0)'!$A37) -> 0 | Q37: =SUM(R37:X37) -> 0 | S37: =SUMIFS('B0.3.XK'!K:K,'B0.3.XK'!A:A,'B0.SUM (tuần 0)'!$A37) -> 0 | U37: =SUMIFS('B0.5.GT2'!K:K,'B0.5.GT2'!A:A,'B0.SUM (tuần 0)'!$A37) -> 0 | V37: =SUMIFS('B0.4.OEM'!K:K,'B0.4.OEM'!A:A,'B0.SUM (tuần 0)'!$A37) -> 0 | X37: =SUMIFS('B0.8.Online'!K:K,'B0.8.Online'!A:A,'B0.SUM (tuần 0)'!$A37) -> 0 | Y37: =SUM(Z37:AF37) -> 612 | AA37: =SUMIFS('B0.3.XK'!L:L,'B0.3.XK'!A:A,'B0.SUM (tuần 0)'!$A37) -> 612 | AC37: =SUMIFS('B0.5.GT2'!L:L,'B0.5.GT2'!A:A,'B0.SUM (tuần 0)'!$A37) -> 0 | AD37: =SUMIFS('B0.4.OEM'!L:L,'B0.4.OEM'!A:A,'B0.SUM (tuần 0)'!$A37) -> 0 | AF37: =SUMIFS('B0.8.Online'!L:L,'B0.8.Online'!A:A,'B0.SUM (tuần 0)'!$A37) -> 0 | AG37: =SUM(AH37:AN37) -> 0 | AI37: =SUMIFS('B0.3.XK'!M:M,'B0.3.XK'!A:A,'B0.SUM (tuần 0)'!$A37) -> 0 | AK37: =SUMIFS('B0.5.GT2'!M:M,'B0.5.GT2'!A:A,'B0.SUM (tuần 0)'!$A37) -> 0 | AL37: =SUMIFS('B0.4.OEM'!M:M,'B0.4.OEM'!A:A,'B0.SUM (tuần 0)'!$A37) -> 0 | AN37: =SUMIFS('B0.8.Online'!M:M,'B0.8.Online'!A:A,'B0.SUM (tuần 0)'!$A37) -> 0 | AP37: =SUMIFS('B1.SUM (tuần 4)'!$I:$I,'B1.SUM (tuần 4)'!$A:$A,'B0.SUM (tuần 0)'!$A37) -> 0 | AQ37: =I37-AP37 -> 0
A38: 1001110097 | B38: MÁY BCN-400 GPD GRANDSAFE | C38: BCN-400 | D38: Máy TCM Sx | E38: BCN | F38: XK | H38: 6735318 | I38: =SUM(J38:P38) -> 0 | K38: =SUMIFS('B0.3.XK'!J:J,'B0.3.XK'!A:A,'B0.SUM (tuần 0)'!$A38) -> 0 | M38: =SUMIFS('B0.5.GT2'!K:K,'B0.5.GT2'!A:A,'B0.SUM (tuần 0)'!$A38) -> 0 | N38: =SUMIFS('B0.4.OEM'!J:J,'B0.4.OEM'!A:A,'B0.SUM (tuần 0)'!$A38) -> 0 | P38: =SUMIFS('B0.8.Online'!J:J,'B0.8.Online'!A:A,'B0.SUM (tuần 0)'!$A38) -> 0 | Q38: =SUM(R38:X38) -> 0 | S38: =SUMIFS('B0.3.XK'!K:K,'B0.3.XK'!A:A,'B0.SUM (tuần 0)'!$A38) -> 0 | U38: =SUMIFS('B0.5.GT2'!K:K,'B0.5.GT2'!A:A,'B0.SUM (tuần 0)'!$A38) -> 0 | V38: =SUMIFS('B0.4.OEM'!K:K,'B0.4.OEM'!A:A,'B0.SUM (tuần 0)'!$A38) -> 0 | X38: =SUMIFS('B0.8.Online'!K:K,'B0.8.Online'!A:A,'B0.SUM (tuần 0)'!$A38) -> 0 | Y38: =SUM(Z38:AF38) -> 20 | AA38: =SUMIFS('B0.3.XK'!L:L,'B0.3.XK'!A:A,'B0.SUM (tuần 0)'!$A38) -> 20 | AC38: =SUMIFS('B0.5.GT2'!L:L,'B0.5.GT2'!A:A,'B0.SUM (tuần 0)'!$A38) -> 0 | AD38: =SUMIFS('B0.4.OEM'!L:L,'B0.4.OEM'!A:A,'B0.SUM (tuần 0)'!$A38) -> 0 | AF38: =SUMIFS('B0.8.Online'!L:L,'B0.8.Online'!A:A,'B0.SUM (tuần 0)'!$A38) -> 0 | AG38: =SUM(AH38:AN38) -> 0 | AI38: =SUMIFS('B0.3.XK'!M:M,'B0.3.XK'!A:A,'B0.SUM (tuần 0)'!$A38) -> 0 | AK38: =SUMIFS('B0.5.GT2'!M:M,'B0.5.GT2'!A:A,'B0.SUM (tuần 0)'!$A38) -> 0 | AL38: =SUMIFS('B0.4.OEM'!M:M,'B0.4.OEM'!A:A,'B0.SUM (tuần 0)'!$A38) -> 0 | AN38: =SUMIFS('B0.8.Online'!M:M,'B0.8.Online'!A:A,'B0.SUM (tuần 0)'!$A38) -> 0 | AP38: =SUMIFS('B1.SUM (tuần 4)'!$I:$I,'B1.SUM (tuần 4)'!$A:$A,'B0.SUM (tuần 0)'!$A38) -> 0 | AQ38: =I38-AP38 -> 0
A39: 1001110128 | B39: Bộ lọc thô 2 stages LALANKA | C39: Prefilter2S10" | D39: Máy TCM Sx | E39: Bộ lọc thô | F39: XK | H39: 230474 | I39: =SUM(J39:P39) -> 0 | K39: =SUMIFS('B0.3.XK'!J:J,'B0.3.XK'!A:A,'B0.SUM (tuần 0)'!$A39) -> 0 | M39: =SUMIFS('B0.5.GT2'!K:K,'B0.5.GT2'!A:A,'B0.SUM (tuần 0)'!$A39) -> 0 | N39: =SUMIFS('B0.4.OEM'!J:J,'B0.4.OEM'!A:A,'B0.SUM (tuần 0)'!$A39) -> 0 | P39: =SUMIFS('B0.8.Online'!J:J,'B0.8.Online'!A:A,'B0.SUM (tuần 0)'!$A39) -> 0 | Q39: =SUM(R39:X39) -> 0 | S39: =SUMIFS('B0.3.XK'!K:K,'B0.3.XK'!A:A,'B0.SUM (tuần 0)'!$A39) -> 0 | U39: =SUMIFS('B0.5.GT2'!K:K,'B0.5.GT2'!A:A,'B0.SUM (tuần 0)'!$A39) -> 0 | V39: =SUMIFS('B0.4.OEM'!K:K,'B0.4.OEM'!A:A,'B0.SUM (tuần 0)'!$A39) -> 0 | X39: =SUMIFS('B0.8.Online'!K:K,'B0.8.Online'!A:A,'B0.SUM (tuần 0)'!$A39) -> 0 | Y39: =SUM(Z39:AF39) -> 0 | AA39: =SUMIFS('B0.3.XK'!L:L,'B0.3.XK'!A:A,'B0.SUM (tuần 0)'!$A39) -> 0 | AC39: =SUMIFS('B0.5.GT2'!L:L,'B0.5.GT2'!A:A,'B0.SUM (tuần 0)'!$A39) -> 0 | AD39: =SUMIFS('B0.4.OEM'!L:L,'B0.4.OEM'!A:A,'B0.SUM (tuần 0)'!$A39) -> 0 | AF39: =SUMIFS('B0.8.Online'!L:L,'B0.8.Online'!A:A,'B0.SUM (tuần 0)'!$A39) -> 0 | AG39: =SUM(AH39:AN39) -> 0 | AI39: =SUMIFS('B0.3.XK'!M:M,'B0.3.XK'!A:A,'B0.SUM (tuần 0)'!$A39) -> 0 | AK39: =SUMIFS('B0.5.GT2'!M:M,'B0.5.GT2'!A:A,'B0.SUM (tuần 0)'!$A39) -> 0 | AL39: =SUMIFS('B0.4.OEM'!M:M,'B0.4.OEM'!A:A,'B0.SUM (tuần 0)'!$A39) -> 0 | AN39: =SUMIFS('B0.8.Online'!M:M,'B0.8.Online'!A:A,'B0.SUM (tuần 0)'!$A39) -> 0 | AP39: =SUMIFS('B1.SUM (tuần 4)'!$I:$I,'B1.SUM (tuần 4)'!$A:$A,'B0.SUM (tuần 0)'!$A39) -> 0 | AQ39: =I39-AP39 -> 0
A40: 1001110129 | B40: Bộ lọc thô 3 stages LALANKA | C40: Prefilter3S10" | D40: Máy TCM Sx | E40: Bộ lọc thô | F40: XK | H40: 358866 | I40: =SUM(J40:P40) -> 0 | K40: =SUMIFS('B0.3.XK'!J:J,'B0.3.XK'!A:A,'B0.SUM (tuần 0)'!$A40) -> 0 | M40: =SUMIFS('B0.5.GT2'!K:K,'B0.5.GT2'!A:A,'B0.SUM (tuần 0)'!$A40) -> 0 | N40: =SUMIFS('B0.4.OEM'!J:J,'B0.4.OEM'!A:A,'B0.SUM (tuần 0)'!$A40) -> 0 | P40: =SUMIFS('B0.8.Online'!J:J,'B0.8.Online'!A:A,'B0.SUM (tuần 0)'!$A40) -> 0 | Q40: =SUM(R40:X40) -> 0 | S40: =SUMIFS('B0.3.XK'!K:K,'B0.3.XK'!A:A,'B0.SUM (tuần 0)'!$A40) -> 0 | U40: =SUMIFS('B0.5.GT2'!K:K,'B0.5.GT2'!A:A,'B0.SUM (tuần 0)'!$A40) -> 0 | V40: =SUMIFS('B0.4.OEM'!K:K,'B0.4.OEM'!A:A,'B0.SUM (tuần 0)'!$A40) -> 0 | X40: =SUMIFS('B0.8.Online'!K:K,'B0.8.Online'!A:A,'B0.SUM (tuần 0)'!$A40) -> 0 | Y40: =SUM(Z40:AF40) -> 0 | AA40: =SUMIFS('B0.3.XK'!L:L,'B0.3.XK'!A:A,'B0.SUM (tuần 0)'!$A40) -> 0 | AC40: =SUMIFS('B0.5.GT2'!L:L,'B0.5.GT2'!A:A,'B0.SUM (tuần 0)'!$A40) -> 0 | AD40: =SUMIFS('B0.4.OEM'!L:L,'B0.4.OEM'!A:A,'B0.SUM (tuần 0)'!$A40) -> 0 | AF40: =SUMIFS('B0.8.Online'!L:L,'B0.8.Online'!A:A,'B0.SUM (tuần 0)'!$A40) -> 0 | AG40: =SUM(AH40:AN40) -> 0 | AI40: =SUMIFS('B0.3.XK'!M:M,'B0.3.XK'!A:A,'B0.SUM (tuần 0)'!$A40) -> 0 | AK40: =SUMIFS('B0.5.GT2'!M:M,'B0.5.GT2'!A:A,'B0.SUM (tuần 0)'!$A40) -> 0 | AL40: =SUMIFS('B0.4.OEM'!M:M,'B0.4.OEM'!A:A,'B0.SUM (tuần 0)'!$A40) -> 0 | AN40: =SUMIFS('B0.8.Online'!M:M,'B0.8.Online'!A:A,'B0.SUM (tuần 0)'!$A40) -> 0 | AP40: =SUMIFS('B1.SUM (tuần 4)'!$I:$I,'B1.SUM (tuần 4)'!$A:$A,'B0.SUM (tuần 0)'!$A40) -> 0 | AQ40: =I40-AP40 -> 0
A41: 1001110132 | B41: Máy RO-30 MAXPURE | C41: RO-30 | D41: Máy TCM Sx | E41: 10L | F41: XK | H41: 1447041 | I41: =SUM(J41:P41) -> 0 | K41: =SUMIFS('B0.3.XK'!J:J,'B0.3.XK'!A:A,'B0.SUM (tuần 0)'!$A41) -> 0 | M41: =SUMIFS('B0.5.GT2'!K:K,'B0.5.GT2'!A:A,'B0.SUM (tuần 0)'!$A41) -> 0 | N41: =SUMIFS('B0.4.OEM'!J:J,'B0.4.OEM'!A:A,'B0.SUM (tuần 0)'!$A41) -> 0 | P41: =SUMIFS('B0.8.Online'!J:J,'B0.8.Online'!A:A,'B0.SUM (tuần 0)'!$A41) -> 0 | Q41: =SUM(R41:X41) -> 0 | S41: =SUMIFS('B0.3.XK'!K:K,'B0.3.XK'!A:A,'B0.SUM (tuần 0)'!$A41) -> 0 | U41: =SUMIFS('B0.5.GT2'!K:K,'B0.5.GT2'!A:A,'B0.SUM (tuần 0)'!$A41) -> 0 | V41: =SUMIFS('B0.4.OEM'!K:K,'B0.4.OEM'!A:A,'B0.SUM (tuần 0)'!$A41) -> 0 | X41: =SUMIFS('B0.8.Online'!K:K,'B0.8.Online'!A:A,'B0.SUM (tuần 0)'!$A41) -> 0 | Y41: =SUM(Z41:AF41) -> 500 | AA41: =SUMIFS('B0.3.XK'!L:L,'B0.3.XK'!A:A,'B0.SUM (tuần 0)'!$A41) -> 500 | AC41: =SUMIFS('B0.5.GT2'!L:L,'B0.5.GT2'!A:A,'B0.SUM (tuần 0)'!$A41) -> 0 | AD41: =SUMIFS('B0.4.OEM'!L:L,'B0.4.OEM'!A:A,'B0.SUM (tuần 0)'!$A41) -> 0 | AF41: =SUMIFS('B0.8.Online'!L:L,'B0.8.Online'!A:A,'B0.SUM (tuần 0)'!$A41) -> 0 | AG41: =SUM(AH41:AN41) -> 0 | AI41: =SUMIFS('B0.3.XK'!M:M,'B0.3.XK'!A:A,'B0.SUM (tuần 0)'!$A41) -> 0 | AK41: =SUMIFS('B0.5.GT2'!M:M,'B0.5.GT2'!A:A,'B0.SUM (tuần 0)'!$A41) -> 0 | AL41: =SUMIFS('B0.4.OEM'!M:M,'B0.4.OEM'!A:A,'B0.SUM (tuần 0)'!$A41) -> 0 | AN41: =SUMIFS('B0.8.Online'!M:M,'B0.8.Online'!A:A,'B0.SUM (tuần 0)'!$A41) -> 0 | AP41: =SUMIFS('B1.SUM (tuần 4)'!$I:$I,'B1.SUM (tuần 4)'!$A:$A,'B0.SUM (tuần 0)'!$A41) -> 0 | AQ41: =I41-AP41 -> 0
A42: 1001110139 | B42: Máy lọc nước UNDERSINK AQUA PURE (7S) | C42: S-S027 | D42: Máy TCM Sx | E42: 10L | F42: XK | H42: 2630984 | I42: =SUM(J42:P42) -> 0 | K42: =SUMIFS('B0.3.XK'!J:J,'B0.3.XK'!A:A,'B0.SUM (tuần 0)'!$A42) -> 0 | M42: =SUMIFS('B0.5.GT2'!K:K,'B0.5.GT2'!A:A,'B0.SUM (tuần 0)'!$A42) -> 0 | N42: =SUMIFS('B0.4.OEM'!J:J,'B0.4.OEM'!A:A,'B0.SUM (tuần 0)'!$A42) -> 0 | P42: =SUMIFS('B0.8.Online'!J:J,'B0.8.Online'!A:A,'B0.SUM (tuần 0)'!$A42) -> 0 | Q42: =SUM(R42:X42) -> 0 | S42: =SUMIFS('B0.3.XK'!K:K,'B0.3.XK'!A:A,'B0.SUM (tuần 0)'!$A42) -> 0 | U42: =SUMIFS('B0.5.GT2'!K:K,'B0.5.GT2'!A:A,'B0.SUM (tuần 0)'!$A42) -> 0 | V42: =SUMIFS('B0.4.OEM'!K:K,'B0.4.OEM'!A:A,'B0.SUM (tuần 0)'!$A42) -> 0 | X42: =SUMIFS('B0.8.Online'!K:K,'B0.8.Online'!A:A,'B0.SUM (tuần 0)'!$A42) -> 0 | Y42: =SUM(Z42:AF42) -> 0 | AA42: =SUMIFS('B0.3.XK'!L:L,'B0.3.XK'!A:A,'B0.SUM (tuần 0)'!$A42) -> 0 | AC42: =SUMIFS('B0.5.GT2'!L:L,'B0.5.GT2'!A:A,'B0.SUM (tuần 0)'!$A42) -> 0 | AD42: =SUMIFS('B0.4.OEM'!L:L,'B0.4.OEM'!A:A,'B0.SUM (tuần 0)'!$A42) -> 0 | AF42: =SUMIFS('B0.8.Online'!L:L,'B0.8.Online'!A:A,'B0.SUM (tuần 0)'!$A42) -> 0 | AG42: =SUM(AH42:AN42) -> 0 | AI42: =SUMIFS('B0.3.XK'!M:M,'B0.3.XK'!A:A,'B0.SUM (tuần 0)'!$A42) -> 0 | AK42: =SUMIFS('B0.5.GT2'!M:M,'B0.5.GT2'!A:A,'B0.SUM (tuần 0)'!$A42) -> 0 | AL42: =SUMIFS('B0.4.OEM'!M:M,'B0.4.OEM'!A:A,'B0.SUM (tuần 0)'!$A42) -> 0 | AN42: =SUMIFS('B0.8.Online'!M:M,'B0.8.Online'!A:A,'B0.SUM (tuần 0)'!$A42) -> 0 | AP42: =SUMIFS('B1.SUM (tuần 4)'!$I:$I,'B1.SUM (tuần 4)'!$A:$A,'B0.SUM (tuần 0)'!$A42) -> 0 | AQ42: =I42-AP42 -> 0
A43: 1001110151 | B43: Máy BCN-200 GPD Karofi (NATURAL) | C43: BCN-200 | D43: Máy TCM Sx | E43: BCN | F43: XK | H43: 4612991 | I43: =SUM(J43:P43) -> 0 | K43: =SUMIFS('B0.3.XK'!J:J,'B0.3.XK'!A:A,'B0.SUM (tuần 0)'!$A43) -> 0 | M43: =SUMIFS('B0.5.GT2'!K:K,'B0.5.GT2'!A:A,'B0.SUM (tuần 0)'!$A43) -> 0 | N43: =SUMIFS('B0.4.OEM'!J:J,'B0.4.OEM'!A:A,'B0.SUM (tuần 0)'!$A43) -> 0 | P43: =SUMIFS('B0.8.Online'!J:J,'B0.8.Online'!A:A,'B0.SUM (tuần 0)'!$A43) -> 0 | Q43: =SUM(R43:X43) -> 0 | S43: =SUMIFS('B0.3.XK'!K:K,'B0.3.XK'!A:A,'B0.SUM (tuần 0)'!$A43) -> 0 | U43: =SUMIFS('B0.5.GT2'!K:K,'B0.5.GT2'!A:A,'B0.SUM (tuần 0)'!$A43) -> 0 | V43: =SUMIFS('B0.4.OEM'!K:K,'B0.4.OEM'!A:A,'B0.SUM (tuần 0)'!$A43) -> 0 | X43: =SUMIFS('B0.8.Online'!K:K,'B0.8.Online'!A:A,'B0.SUM (tuần 0)'!$A43) -> 0 | Y43: =SUM(Z43:AF43) -> 0 | AA43: =SUMIFS('B0.3.XK'!L:L,'B0.3.XK'!A:A,'B0.SUM (tuần 0)'!$A43) -> 0 | AC43: =SUMIFS('B0.5.GT2'!L:L,'B0.5.GT2'!A:A,'B0.SUM (tuần 0)'!$A43) -> 0 | AD43: =SUMIFS('B0.4.OEM'!L:L,'B0.4.OEM'!A:A,'B0.SUM (tuần 0)'!$A43) -> 0 | AF43: =SUMIFS('B0.8.Online'!L:L,'B0.8.Online'!A:A,'B0.SUM (tuần 0)'!$A43) -> 0 | AG43: =SUM(AH43:AN43) -> 0 | AI43: =SUMIFS('B0.3.XK'!M:M,'B0.3.XK'!A:A,'B0.SUM (tuần 0)'!$A43) -> 0 | AK43: =SUMIFS('B0.5.GT2'!M:M,'B0.5.GT2'!A:A,'B0.SUM (tuần 0)'!$A43) -> 0 | AL43: =SUMIFS('B0.4.OEM'!M:M,'B0.4.OEM'!A:A,'B0.SUM (tuần 0)'!$A43) -> 0 | AN43: =SUMIFS('B0.8.Online'!M:M,'B0.8.Online'!A:A,'B0.SUM (tuần 0)'!$A43) -> 0 | AP43: =SUMIFS('B1.SUM (tuần 4)'!$I:$I,'B1.SUM (tuần 4)'!$A:$A,'B0.SUM (tuần 0)'!$A43) -> 0 | AQ43: =I43-AP43 -> 0
A44: 1001110152 | B44: Máy BCN-300 GPD Karofi (NATURAL) | C44: BCN-300 | D44: Máy TCM Sx | E44: BCN | F44: XK | H44: 5426403 | I44: =SUM(J44:P44) -> 0 | K44: =SUMIFS('B0.3.XK'!J:J,'B0.3.XK'!A:A,'B0.SUM (tuần 0)'!$A44) -> 0 | M44: =SUMIFS('B0.5.GT2'!K:K,'B0.5.GT2'!A:A,'B0.SUM (tuần 0)'!$A44) -> 0 | N44: =SUMIFS('B0.4.OEM'!J:J,'B0.4.OEM'!A:A,'B0.SUM (tuần 0)'!$A44) -> 0 | P44: =SUMIFS('B0.8.Online'!J:J,'B0.8.Online'!A:A,'B0.SUM (tuần 0)'!$A44) -> 0 | Q44: =SUM(R44:X44) -> 0 | S44: =SUMIFS('B0.3.XK'!K:K,'B0.3.XK'!A:A,'B0.SUM (tuần 0)'!$A44) -> 0 | U44: =SUMIFS('B0.5.GT2'!K:K,'B0.5.GT2'!A:A,'B0.SUM (tuần 0)'!$A44) -> 0 | V44: =SUMIFS('B0.4.OEM'!K:K,'B0.4.OEM'!A:A,'B0.SUM (tuần 0)'!$A44) -> 0 | X44: =SUMIFS('B0.8.Online'!K:K,'B0.8.Online'!A:A,'B0.SUM (tuần 0)'!$A44) -> 0 | Y44: =SUM(Z44:AF44) -> 0 | AA44: =SUMIFS('B0.3.XK'!L:L,'B0.3.XK'!A:A,'B0.SUM (tuần 0)'!$A44) -> 0 | AC44: =SUMIFS('B0.5.GT2'!L:L,'B0.5.GT2'!A:A,'B0.SUM (tuần 0)'!$A44) -> 0 | AD44: =SUMIFS('B0.4.OEM'!L:L,'B0.4.OEM'!A:A,'B0.SUM (tuần 0)'!$A44) -> 0 | AF44: =SUMIFS('B0.8.Online'!L:L,'B0.8.Online'!A:A,'B0.SUM (tuần 0)'!$A44) -> 0 | AG44: =SUM(AH44:AN44) -> 150 | AI44: =SUMIFS('B0.3.XK'!M:M,'B0.3.XK'!A:A,'B0.SUM (tuần 0)'!$A44) -> 150 | AK44: =SUMIFS('B0.5.GT2'!M:M,'B0.5.GT2'!A:A,'B0.SUM (tuần 0)'!$A44) -> 0 | AL44: =SUMIFS('B0.4.OEM'!M:M,'B0.4.OEM'!A:A,'B0.SUM (tuần 0)'!$A44) -> 0 | AN44: =SUMIFS('B0.8.Online'!M:M,'B0.8.Online'!A:A,'B0.SUM (tuần 0)'!$A44) -> 0 | AP44: =SUMIFS('B1.SUM (tuần 4)'!$I:$I,'B1.SUM (tuần 4)'!$A:$A,'B0.SUM (tuần 0)'!$A44) -> 0 | AQ44: =I44-AP44 -> 0
A45: 1001110153 | B45: Máy BCN-400 GPD Karofi (NATURAL) | C45: BCN-400 | D45: Máy TCM Sx | E45: BCN | F45: XK | H45: 5867093 | I45: =SUM(J45:P45) -> 0 | K45: =SUMIFS('B0.3.XK'!J:J,'B0.3.XK'!A:A,'B0.SUM (tuần 0)'!$A45) -> 0 | M45: =SUMIFS('B0.5.GT2'!K:K,'B0.5.GT2'!A:A,'B0.SUM (tuần 0)'!$A45) -> 0 | N45: =SUMIFS('B0.4.OEM'!J:J,'B0.4.OEM'!A:A,'B0.SUM (tuần 0)'!$A45) -> 0 | P45: =SUMIFS('B0.8.Online'!J:J,'B0.8.Online'!A:A,'B0.SUM (tuần 0)'!$A45) -> 0 | Q45: =SUM(R45:X45) -> 0 | S45: =SUMIFS('B0.3.XK'!K:K,'B0.3.XK'!A:A,'B0.SUM (tuần 0)'!$A45) -> 0 | U45: =SUMIFS('B0.5.GT2'!K:K,'B0.5.GT2'!A:A,'B0.SUM (tuần 0)'!$A45) -> 0 | V45: =SUMIFS('B0.4.OEM'!K:K,'B0.4.OEM'!A:A,'B0.SUM (tuần 0)'!$A45) -> 0 | X45: =SUMIFS('B0.8.Online'!K:K,'B0.8.Online'!A:A,'B0.SUM (tuần 0)'!$A45) -> 0 | Y45: =SUM(Z45:AF45) -> 20 | AA45: =SUMIFS('B0.3.XK'!L:L,'B0.3.XK'!A:A,'B0.SUM (tuần 0)'!$A45) -> 20 | AC45: =SUMIFS('B0.5.GT2'!L:L,'B0.5.GT2'!A:A,'B0.SUM (tuần 0)'!$A45) -> 0 | AD45: =SUMIFS('B0.4.OEM'!L:L,'B0.4.OEM'!A:A,'B0.SUM (tuần 0)'!$A45) -> 0 | AF45: =SUMIFS('B0.8.Online'!L:L,'B0.8.Online'!A:A,'B0.SUM (tuần 0)'!$A45) -> 0 | AG45: =SUM(AH45:AN45) -> 0 | AI45: =SUMIFS('B0.3.XK'!M:M,'B0.3.XK'!A:A,'B0.SUM (tuần 0)'!$A45) -> 0 | AK45: =SUMIFS('B0.5.GT2'!M:M,'B0.5.GT2'!A:A,'B0.SUM (tuần 0)'!$A45) -> 0 | AL45: =SUMIFS('B0.4.OEM'!M:M,'B0.4.OEM'!A:A,'B0.SUM (tuần 0)'!$A45) -> 0 | AN45: =SUMIFS('B0.8.Online'!M:M,'B0.8.Online'!A:A,'B0.SUM (tuần 0)'!$A45) -> 0 | AP45: =SUMIFS('B1.SUM (tuần 4)'!$I:$I,'B1.SUM (tuần 4)'!$A:$A,'B0.SUM (tuần 0)'!$A45) -> 0 | AQ45: =I45-AP45 -> 0
A46: 1001110156 | B46: Máy BCN-400 GPD Tecomen | C46: BCN-400 | D46: Máy TCM Sx | E46: BCN | F46: XK | H46: 6850818 | I46: =SUM(J46:P46) -> 0 | K46: =SUMIFS('B0.3.XK'!J:J,'B0.3.XK'!A:A,'B0.SUM (tuần 0)'!$A46) -> 0 | M46: =SUMIFS('B0.5.GT2'!K:K,'B0.5.GT2'!A:A,'B0.SUM (tuần 0)'!$A46) -> 0 | N46: =SUMIFS('B0.4.OEM'!J:J,'B0.4.OEM'!A:A,'B0.SUM (tuần 0)'!$A46) -> 0 | P46: =SUMIFS('B0.8.Online'!J:J,'B0.8.Online'!A:A,'B0.SUM (tuần 0)'!$A46) -> 0 | Q46: =SUM(R46:X46) -> 0 | S46: =SUMIFS('B0.3.XK'!K:K,'B0.3.XK'!A:A,'B0.SUM (tuần 0)'!$A46) -> 0 | U46: =SUMIFS('B0.5.GT2'!K:K,'B0.5.GT2'!A:A,'B0.SUM (tuần 0)'!$A46) -> 0 | V46: =SUMIFS('B0.4.OEM'!K:K,'B0.4.OEM'!A:A,'B0.SUM (tuần 0)'!$A46) -> 0 | X46: =SUMIFS('B0.8.Online'!K:K,'B0.8.Online'!A:A,'B0.SUM (tuần 0)'!$A46) -> 0 | Y46: =SUM(Z46:AF46) -> 0 | AA46: =SUMIFS('B0.3.XK'!L:L,'B0.3.XK'!A:A,'B0.SUM (tuần 0)'!$A46) -> 0 | AC46: =SUMIFS('B0.5.GT2'!L:L,'B0.5.GT2'!A:A,'B0.SUM (tuần 0)'!$A46) -> 0 | AD46: =SUMIFS('B0.4.OEM'!L:L,'B0.4.OEM'!A:A,'B0.SUM (tuần 0)'!$A46) -> 0 | AF46: =SUMIFS('B0.8.Online'!L:L,'B0.8.Online'!A:A,'B0.SUM (tuần 0)'!$A46) -> 0 | AG46: =SUM(AH46:AN46) -> 50 | AI46: =SUMIFS('B0.3.XK'!M:M,'B0.3.XK'!A:A,'B0.SUM (tuần 0)'!$A46) -> 50 | AK46: =SUMIFS('B0.5.GT2'!M:M,'B0.5.GT2'!A:A,'B0.SUM (tuần 0)'!$A46) -> 0 | AL46: =SUMIFS('B0.4.OEM'!M:M,'B0.4.OEM'!A:A,'B0.SUM (tuần 0)'!$A46) -> 0 | AN46: =SUMIFS('B0.8.Online'!M:M,'B0.8.Online'!A:A,'B0.SUM (tuần 0)'!$A46) -> 0 | AP46: =SUMIFS('B1.SUM (tuần 4)'!$I:$I,'B1.SUM (tuần 4)'!$A:$A,'B0.SUM (tuần 0)'!$A46) -> 0 | AQ46: =I46-AP46 -> 0
... A104: 1001110534 | B104: Máy RO-100 Helsy (7s) | C104: RO-100 | D104: Máy TCM Sx | E104: 10L | F104: XK | H104: 1720663 | I104: =SUM(J104:P104) -> 0 | K104: =SUMIFS('B0.3.XK'!J:J,'B0.3.XK'!A:A,'B0.SUM (tuần 0)'!$A104) -> 0 | M104: =SUMIFS('B0.5.GT2'!K:K,'B0.5.GT2'!A:A,'B0.SUM (tuần 0)'!$A104) -> 0 | N104: =SUMIFS('B0.4.OEM'!J:J,'B0.4.OEM'!A:A,'B0.SUM (tuần 0)'!$A104) -> 0 | P104: =SUMIFS('B0.8.Online'!J:J,'B0.8.Online'!A:A,'B0.SUM (tuần 0)'!$A104) -> 0 | Q104: =SUM(R104:X104) -> 0 | S104: =SUMIFS('B0.3.XK'!K:K,'B0.3.XK'!A:A,'B0.SUM (tuần 0)'!$A104) -> 0 | U104: =SUMIFS('B0.5.GT2'!K:K,'B0.5.GT2'!A:A,'B0.SUM (tuần 0)'!$A104) -> 0 | V104: =SUMIFS('B0.4.OEM'!K:K,'B0.4.OEM'!A:A,'B0.SUM (tuần 0)'!$A104) -> 0 | X104: =SUMIFS('B0.8.Online'!K:K,'B0.8.Online'!A:A,'B0.SUM (tuần 0)'!$A104) -> 0 | Y104: =SUM(Z104:AF104) -> 0 | AA104: =SUMIFS('B0.3.XK'!L:L,'B0.3.XK'!A:A,'B0.SUM (tuần 0)'!$A104) -> 0 | AC104: =SUMIFS('B0.5.GT2'!L:L,'B0.5.GT2'!A:A,'B0.SUM (tuần 0)'!$A104) -> 0 | AD104: =SUMIFS('B0.4.OEM'!L:L,'B0.4.OEM'!A:A,'B0.SUM (tuần 0)'!$A104) -> 0 | AF104: =SUMIFS('B0.8.Online'!L:L,'B0.8.Online'!A:A,'B0.SUM (tuần 0)'!$A104) -> 0 | AG104: =SUM(AH104:AN104) -> 0 | AI104: =SUMIFS('B0.3.XK'!M:M,'B0.3.XK'!A:A,'B0.SUM (tuần 0)'!$A104) -> 0 | AK104: =SUMIFS('B0.5.GT2'!M:M,'B0.5.GT2'!A:A,'B0.SUM (tuần 0)'!$A104) -> 0 | AL104: =SUMIFS('B0.4.OEM'!M:M,'B0.4.OEM'!A:A,'B0.SUM (tuần 0)'!$A104) -> 0 | AN104: =SUMIFS('B0.8.Online'!M:M,'B0.8.Online'!A:A,'B0.SUM (tuần 0)'!$A104) -> 0 | AP104: =SUMIFS('B1.SUM (tuần 4)'!$I:$I,'B1.SUM (tuần 4)'!$A:$A,'B0.SUM (tuần 0)'!$A104) -> 0 | AQ104: =I104-AP104 -> 0
A105: 1001110536 | B105: Máy lọc nước U05 Pro Karofi (Anh) v3 | C105: KAQ-U05 Pro | D105: Máy TCM Sx | E105: 10L | F105: XK | H105: 1847535 | I105: =SUM(J105:P105) -> 0 | K105: =SUMIFS('B0.3.XK'!J:J,'B0.3.XK'!A:A,'B0.SUM (tuần 0)'!$A105) -> 0 | M105: =SUMIFS('B0.5.GT2'!K:K,'B0.5.GT2'!A:A,'B0.SUM (tuần 0)'!$A105) -> 0 | N105: =SUMIFS('B0.4.OEM'!J:J,'B0.4.OEM'!A:A,'B0.SUM (tuần 0)'!$A105) -> 0 | P105: =SUMIFS('B0.8.Online'!J:J,'B0.8.Online'!A:A,'B0.SUM (tuần 0)'!$A105) -> 0 | Q105: =SUM(R105:X105) -> 0 | S105: =SUMIFS('B0.3.XK'!K:K,'B0.3.XK'!A:A,'B0.SUM (tuần 0)'!$A105) -> 0 | U105: =SUMIFS('B0.5.GT2'!K:K,'B0.5.GT2'!A:A,'B0.SUM (tuần 0)'!$A105) -> 0 | V105: =SUMIFS('B0.4.OEM'!K:K,'B0.4.OEM'!A:A,'B0.SUM (tuần 0)'!$A105) -> 0 | X105: =SUMIFS('B0.8.Online'!K:K,'B0.8.Online'!A:A,'B0.SUM (tuần 0)'!$A105) -> 0 | Y105: =SUM(Z105:AF105) -> 0 | AA105: =SUMIFS('B0.3.XK'!L:L,'B0.3.XK'!A:A,'B0.SUM (tuần 0)'!$A105) -> 0 | AC105: =SUMIFS('B0.5.GT2'!L:L,'B0.5.GT2'!A:A,'B0.SUM (tuần 0)'!$A105) -> 0 | AD105: =SUMIFS('B0.4.OEM'!L:L,'B0.4.OEM'!A:A,'B0.SUM (tuần 0)'!$A105) -> 0 | AF105: =SUMIFS('B0.8.Online'!L:L,'B0.8.Online'!A:A,'B0.SUM (tuần 0)'!$A105) -> 0 | AG105: =SUM(AH105:AN105) -> 0 | AI105: =SUMIFS('B0.3.XK'!M:M,'B0.3.XK'!A:A,'B0.SUM (tuần 0)'!$A105) -> 0 | AK105: =SUMIFS('B0.5.GT2'!M:M,'B0.5.GT2'!A:A,'B0.SUM (tuần 0)'!$A105) -> 0 | AL105: =SUMIFS('B0.4.OEM'!M:M,'B0.4.OEM'!A:A,'B0.SUM (tuần 0)'!$A105) -> 0 | AN105: =SUMIFS('B0.8.Online'!M:M,'B0.8.Online'!A:A,'B0.SUM (tuần 0)'!$A105) -> 0 | AP105: =SUMIFS('B1.SUM (tuần 4)'!$I:$I,'B1.SUM (tuần 4)'!$A:$A,'B0.SUM (tuần 0)'!$A105) -> 0 | AQ105: =I105-AP105 -> 0
A106: 1001110537 | B106: Máy RO-100 Karofi Eco | C106: RO-100 | D106: Máy TCM Sx | E106: 10L | F106: XK | H106: 1723294 | I106: =SUM(J106:P106) -> 0 | K106: =SUMIFS('B0.3.XK'!J:J,'B0.3.XK'!A:A,'B0.SUM (tuần 0)'!$A106) -> 0 | M106: =SUMIFS('B0.5.GT2'!K:K,'B0.5.GT2'!A:A,'B0.SUM (tuần 0)'!$A106) -> 0 | N106: =SUMIFS('B0.4.OEM'!J:J,'B0.4.OEM'!A:A,'B0.SUM (tuần 0)'!$A106) -> 0 | P106: =SUMIFS('B0.8.Online'!J:J,'B0.8.Online'!A:A,'B0.SUM (tuần 0)'!$A106) -> 0 | Q106: =SUM(R106:X106) -> 212 | S106: =SUMIFS('B0.3.XK'!K:K,'B0.3.XK'!A:A,'B0.SUM (tuần 0)'!$A106) -> 212 | U106: =SUMIFS('B0.5.GT2'!K:K,'B0.5.GT2'!A:A,'B0.SUM (tuần 0)'!$A106) -> 0 | V106: =SUMIFS('B0.4.OEM'!K:K,'B0.4.OEM'!A:A,'B0.SUM (tuần 0)'!$A106) -> 0 | X106: =SUMIFS('B0.8.Online'!K:K,'B0.8.Online'!A:A,'B0.SUM (tuần 0)'!$A106) -> 0 | Y106: =SUM(Z106:AF106) -> 100 | AA106: =SUMIFS('B0.3.XK'!L:L,'B0.3.XK'!A:A,'B0.SUM (tuần 0)'!$A106) -> 100 | AC106: =SUMIFS('B0.5.GT2'!L:L,'B0.5.GT2'!A:A,'B0.SUM (tuần 0)'!$A106) -> 0 | AD106: =SUMIFS('B0.4.OEM'!L:L,'B0.4.OEM'!A:A,'B0.SUM (tuần 0)'!$A106) -> 0 | AF106: =SUMIFS('B0.8.Online'!L:L,'B0.8.Online'!A:A,'B0.SUM (tuần 0)'!$A106) -> 0 | AG106: =SUM(AH106:AN106) -> 0 | AI106: =SUMIFS('B0.3.XK'!M:M,'B0.3.XK'!A:A,'B0.SUM (tuần 0)'!$A106) -> 0 | AK106: =SUMIFS('B0.5.GT2'!M:M,'B0.5.GT2'!A:A,'B0.SUM (tuần 0)'!$A106) -> 0 | AL106: =SUMIFS('B0.4.OEM'!M:M,'B0.4.OEM'!A:A,'B0.SUM (tuần 0)'!$A106) -> 0 | AN106: =SUMIFS('B0.8.Online'!M:M,'B0.8.Online'!A:A,'B0.SUM (tuần 0)'!$A106) -> 0 | AP106: =SUMIFS('B1.SUM (tuần 4)'!$I:$I,'B1.SUM (tuần 4)'!$A:$A,'B0.SUM (tuần 0)'!$A106) -> 0 | AQ106: =I106-AP106 -> 0
A107: 1001110541 | B107: Máy lọc nước RO-104 UV (6S) | C107: RO-104 | D107: Máy TCM Sx | E107: 10L | F107: XK | H107: 1479928 | I107: =SUM(J107:P107) -> 0 | K107: =SUMIFS('B0.3.XK'!J:J,'B0.3.XK'!A:A,'B0.SUM (tuần 0)'!$A107) -> 0 | M107: =SUMIFS('B0.5.GT2'!K:K,'B0.5.GT2'!A:A,'B0.SUM (tuần 0)'!$A107) -> 0 | N107: =SUMIFS('B0.4.OEM'!J:J,'B0.4.OEM'!A:A,'B0.SUM (tuần 0)'!$A107) -> 0 | P107: =SUMIFS('B0.8.Online'!J:J,'B0.8.Online'!A:A,'B0.SUM (tuần 0)'!$A107) -> 0 | Q107: =SUM(R107:X107) -> 155 | S107: =SUMIFS('B0.3.XK'!K:K,'B0.3.XK'!A:A,'B0.SUM (tuần 0)'!$A107) -> 155 | U107: =SUMIFS('B0.5.GT2'!K:K,'B0.5.GT2'!A:A,'B0.SUM (tuần 0)'!$A107) -> 0 | V107: =SUMIFS('B0.4.OEM'!K:K,'B0.4.OEM'!A:A,'B0.SUM (tuần 0)'!$A107) -> 0 | X107: =SUMIFS('B0.8.Online'!K:K,'B0.8.Online'!A:A,'B0.SUM (tuần 0)'!$A107) -> 0 | Y107: =SUM(Z107:AF107) -> 0 | AA107: =SUMIFS('B0.3.XK'!L:L,'B0.3.XK'!A:A,'B0.SUM (tuần 0)'!$A107) -> 0 | AC107: =SUMIFS('B0.5.GT2'!L:L,'B0.5.GT2'!A:A,'B0.SUM (tuần 0)'!$A107) -> 0 | AD107: =SUMIFS('B0.4.OEM'!L:L,'B0.4.OEM'!A:A,'B0.SUM (tuần 0)'!$A107) -> 0 | AF107: =SUMIFS('B0.8.Online'!L:L,'B0.8.Online'!A:A,'B0.SUM (tuần 0)'!$A107) -> 0 | AG107: =SUM(AH107:AN107) -> 0 | AI107: =SUMIFS('B0.3.XK'!M:M,'B0.3.XK'!A:A,'B0.SUM (tuần 0)'!$A107) -> 0 | AK107: =SUMIFS('B0.5.GT2'!M:M,'B0.5.GT2'!A:A,'B0.SUM (tuần 0)'!$A107) -> 0 | AL107: =SUMIFS('B0.4.OEM'!M:M,'B0.4.OEM'!A:A,'B0.SUM (tuần 0)'!$A107) -> 0 | AN107: =SUMIFS('B0.8.Online'!M:M,'B0.8.Online'!A:A,'B0.SUM (tuần 0)'!$A107) -> 0 | AP107: =SUMIFS('B1.SUM (tuần 4)'!$I:$I,'B1.SUM (tuần 4)'!$A:$A,'B0.SUM (tuần 0)'!$A107) -> 0 | AQ107: =I107-AP107 -> 0
A108: 1001110542 | B108: Máy lọc nước RO-31 UV (6S) | C108: RO-31 | D108: Máy TCM Sx | E108: 10L | F108: XK | H108: 674190 | I108: =SUM(J108:P108) -> 0 | K108: =SUMIFS('B0.3.XK'!J:J,'B0.3.XK'!A:A,'B0.SUM (tuần 0)'!$A108) -> 0 | M108: =SUMIFS('B0.5.GT2'!K:K,'B0.5.GT2'!A:A,'B0.SUM (tuần 0)'!$A108) -> 0 | N108: =SUMIFS('B0.4.OEM'!J:J,'B0.4.OEM'!A:A,'B0.SUM (tuần 0)'!$A108) -> 0 | P108: =SUMIFS('B0.8.Online'!J:J,'B0.8.Online'!A:A,'B0.SUM (tuần 0)'!$A108) -> 0 | Q108: =SUM(R108:X108) -> 197 | S108: =SUMIFS('B0.3.XK'!K:K,'B0.3.XK'!A:A,'B0.SUM (tuần 0)'!$A108) -> 197 | U108: =SUMIFS('B0.5.GT2'!K:K,'B0.5.GT2'!A:A,'B0.SUM (tuần 0)'!$A108) -> 0 | V108: =SUMIFS('B0.4.OEM'!K:K,'B0.4.OEM'!A:A,'B0.SUM (tuần 0)'!$A108) -> 0 | X108: =SUMIFS('B0.8.Online'!K:K,'B0.8.Online'!A:A,'B0.SUM (tuần 0)'!$A108) -> 0 | Y108: =SUM(Z108:AF108) -> 0 | AA108: =SUMIFS('B0.3.XK'!L:L,'B0.3.XK'!A:A,'B0.SUM (tuần 0)'!$A108) -> 0 | AC108: =SUMIFS('B0.5.GT2'!L:L,'B0.5.GT2'!A:A,'B0.SUM (tuần 0)'!$A108) -> 0 | AD108: =SUMIFS('B0.4.OEM'!L:L,'B0.4.OEM'!A:A,'B0.SUM (tuần 0)'!$A108) -> 0 | AF108: =SUMIFS('B0.8.Online'!L:L,'B0.8.Online'!A:A,'B0.SUM (tuần 0)'!$A108) -> 0 | AG108: =SUM(AH108:AN108) -> 0 | AI108: =SUMIFS('B0.3.XK'!M:M,'B0.3.XK'!A:A,'B0.SUM (tuần 0)'!$A108) -> 0 | AK108: =SUMIFS('B0.5.GT2'!M:M,'B0.5.GT2'!A:A,'B0.SUM (tuần 0)'!$A108) -> 0 | AL108: =SUMIFS('B0.4.OEM'!M:M,'B0.4.OEM'!A:A,'B0.SUM (tuần 0)'!$A108) -> 0 | AN108: =SUMIFS('B0.8.Online'!M:M,'B0.8.Online'!A:A,'B0.SUM (tuần 0)'!$A108) -> 0 | AP108: =SUMIFS('B1.SUM (tuần 4)'!$I:$I,'B1.SUM (tuần 4)'!$A:$A,'B0.SUM (tuần 0)'!$A108) -> 0 | AQ108: =I108-AP108 -> 0
A109: 1001110543 | B109: Máy lọc nước ERO70 KAROFI ECO | C109: ERO70 | D109: Máy TCM Sx | E109: 10L Tủ | F109: XK | H109: 2214630 | I109: =SUM(J109:P109) -> 100 | K109: =SUMIFS('B0.3.XK'!J:J,'B0.3.XK'!A:A,'B0.SUM (tuần 0)'!$A109) -> 100 | M109: =SUMIFS('B0.5.GT2'!K:K,'B0.5.GT2'!A:A,'B0.SUM (tuần 0)'!$A109) -> 0 | N109: =SUMIFS('B0.4.OEM'!J:J,'B0.4.OEM'!A:A,'B0.SUM (tuần 0)'!$A109) -> 0 | P109: =SUMIFS('B0.8.Online'!J:J,'B0.8.Online'!A:A,'B0.SUM (tuần 0)'!$A109) -> 0 | Q109: =SUM(R109:X109) -> 0 | S109: =SUMIFS('B0.3.XK'!K:K,'B0.3.XK'!A:A,'B0.SUM (tuần 0)'!$A109) -> 0 | U109: =SUMIFS('B0.5.GT2'!K:K,'B0.5.GT2'!A:A,'B0.SUM (tuần 0)'!$A109) -> 0 | V109: =SUMIFS('B0.4.OEM'!K:K,'B0.4.OEM'!A:A,'B0.SUM (tuần 0)'!$A109) -> 0 | X109: =SUMIFS('B0.8.Online'!K:K,'B0.8.Online'!A:A,'B0.SUM (tuần 0)'!$A109) -> 0 | Y109: =SUM(Z109:AF109) -> 100 | AA109: =SUMIFS('B0.3.XK'!L:L,'B0.3.XK'!A:A,'B0.SUM (tuần 0)'!$A109) -> 100 | AC109: =SUMIFS('B0.5.GT2'!L:L,'B0.5.GT2'!A:A,'B0.SUM (tuần 0)'!$A109) -> 0 | AD109: =SUMIFS('B0.4.OEM'!L:L,'B0.4.OEM'!A:A,'B0.SUM (tuần 0)'!$A109) -> 0 | AF109: =SUMIFS('B0.8.Online'!L:L,'B0.8.Online'!A:A,'B0.SUM (tuần 0)'!$A109) -> 0 | AG109: =SUM(AH109:AN109) -> 0 | AI109: =SUMIFS('B0.3.XK'!M:M,'B0.3.XK'!A:A,'B0.SUM (tuần 0)'!$A109) -> 0 | AK109: =SUMIFS('B0.5.GT2'!M:M,'B0.5.GT2'!A:A,'B0.SUM (tuần 0)'!$A109) -> 0 | AL109: =SUMIFS('B0.4.OEM'!M:M,'B0.4.OEM'!A:A,'B0.SUM (tuần 0)'!$A109) -> 0 | AN109: =SUMIFS('B0.8.Online'!M:M,'B0.8.Online'!A:A,'B0.SUM (tuần 0)'!$A109) -> 0 | AP109: =SUMIFS('B1.SUM (tuần 4)'!$I:$I,'B1.SUM (tuần 4)'!$A:$A,'B0.SUM (tuần 0)'!$A109) -> 0 | AQ109: =I109-AP109 -> 100
A110: 1001110545 | B110: Máy RO-01 Helsy | C110: RO-01 | D110: Máy TCM Sx | E110: 10L | F110: XK | H110: 1470720 | I110: =SUM(J110:P110) -> 0 | K110: =SUMIFS('B0.3.XK'!J:J,'B0.3.XK'!A:A,'B0.SUM (tuần 0)'!$A110) -> 0 | M110: =SUMIFS('B0.5.GT2'!K:K,'B0.5.GT2'!A:A,'B0.SUM (tuần 0)'!$A110) -> 0 | N110: =SUMIFS('B0.4.OEM'!J:J,'B0.4.OEM'!A:A,'B0.SUM (tuần 0)'!$A110) -> 0 | P110: =SUMIFS('B0.8.Online'!J:J,'B0.8.Online'!A:A,'B0.SUM (tuần 0)'!$A110) -> 0 | Q110: =SUM(R110:X110) -> 0 | S110: =SUMIFS('B0.3.XK'!K:K,'B0.3.XK'!A:A,'B0.SUM (tuần 0)'!$A110) -> 0 | U110: =SUMIFS('B0.5.GT2'!K:K,'B0.5.GT2'!A:A,'B0.SUM (tuần 0)'!$A110) -> 0 | V110: =SUMIFS('B0.4.OEM'!K:K,'B0.4.OEM'!A:A,'B0.SUM (tuần 0)'!$A110) -> 0 | X110: =SUMIFS('B0.8.Online'!K:K,'B0.8.Online'!A:A,'B0.SUM (tuần 0)'!$A110) -> 0 | Y110: =SUM(Z110:AF110) -> 0 | AA110: =SUMIFS('B0.3.XK'!L:L,'B0.3.XK'!A:A,'B0.SUM (tuần 0)'!$A110) -> 0 | AC110: =SUMIFS('B0.5.GT2'!L:L,'B0.5.GT2'!A:A,'B0.SUM (tuần 0)'!$A110) -> 0 | AD110: =SUMIFS('B0.4.OEM'!L:L,'B0.4.OEM'!A:A,'B0.SUM (tuần 0)'!$A110) -> 0 | AF110: =SUMIFS('B0.8.Online'!L:L,'B0.8.Online'!A:A,'B0.SUM (tuần 0)'!$A110) -> 0 | AG110: =SUM(AH110:AN110) -> 0 | AI110: =SUMIFS('B0.3.XK'!M:M,'B0.3.XK'!A:A,'B0.SUM (tuần 0)'!$A110) -> 0 | AK110: =SUMIFS('B0.5.GT2'!M:M,'B0.5.GT2'!A:A,'B0.SUM (tuần 0)'!$A110) -> 0 | AL110: =SUMIFS('B0.4.OEM'!M:M,'B0.4.OEM'!A:A,'B0.SUM (tuần 0)'!$A110) -> 0 | AN110: =SUMIFS('B0.8.Online'!M:M,'B0.8.Online'!A:A,'B0.SUM (tuần 0)'!$A110) -> 0 | AP110: =SUMIFS('B1.SUM (tuần 4)'!$I:$I,'B1.SUM (tuần 4)'!$A:$A,'B0.SUM (tuần 0)'!$A110) -> 0 | AQ110: =I110-AP110 -> 0
A111: 1001110547 | B111: Máy lọc nước RO-01 AQUALAND (6S) | C111: RO-01 | D111: Máy TCM Sx | E111: 10L | F111: XK | H111: 1325489 | I111: =SUM(J111:P111) -> 0 | K111: =SUMIFS('B0.3.XK'!J:J,'B0.3.XK'!A:A,'B0.SUM (tuần 0)'!$A111) -> 0 | M111: =SUMIFS('B0.5.GT2'!K:K,'B0.5.GT2'!A:A,'B0.SUM (tuần 0)'!$A111) -> 0 | N111: =SUMIFS('B0.4.OEM'!J:J,'B0.4.OEM'!A:A,'B0.SUM (tuần 0)'!$A111) -> 0 | P111: =SUMIFS('B0.8.Online'!J:J,'B0.8.Online'!A:A,'B0.SUM (tuần 0)'!$A111) -> 0 | Q111: =SUM(R111:X111) -> 0 | S111: =SUMIFS('B0.3.XK'!K:K,'B0.3.XK'!A:A,'B0.SUM (tuần 0)'!$A111) -> 0 | U111: =SUMIFS('B0.5.GT2'!K:K,'B0.5.GT2'!A:A,'B0.SUM (tuần 0)'!$A111) -> 0 | V111: =SUMIFS('B0.4.OEM'!K:K,'B0.4.OEM'!A:A,'B0.SUM (tuần 0)'!$A111) -> 0 | X111: =SUMIFS('B0.8.Online'!K:K,'B0.8.Online'!A:A,'B0.SUM (tuần 0)'!$A111) -> 0 | Y111: =SUM(Z111:AF111) -> 0 | AA111: =SUMIFS('B0.3.XK'!L:L,'B0.3.XK'!A:A,'B0.SUM (tuần 0)'!$A111) -> 0 | AC111: =SUMIFS('B0.5.GT2'!L:L,'B0.5.GT2'!A:A,'B0.SUM (tuần 0)'!$A111) -> 0 | AD111: =SUMIFS('B0.4.OEM'!L:L,'B0.4.OEM'!A:A,'B0.SUM (tuần 0)'!$A111) -> 0 | AF111: =SUMIFS('B0.8.Online'!L:L,'B0.8.Online'!A:A,'B0.SUM (tuần 0)'!$A111) -> 0 | AG111: =SUM(AH111:AN111) -> 0 | AI111: =SUMIFS('B0.3.XK'!M:M,'B0.3.XK'!A:A,'B0.SUM (tuần 0)'!$A111) -> 0 | AK111: =SUMIFS('B0.5.GT2'!M:M,'B0.5.GT2'!A:A,'B0.SUM (tuần 0)'!$A111) -> 0 | AL111: =SUMIFS('B0.4.OEM'!M:M,'B0.4.OEM'!A:A,'B0.SUM (tuần 0)'!$A111) -> 0 | AN111: =SUMIFS('B0.8.Online'!M:M,'B0.8.Online'!A:A,'B0.SUM (tuần 0)'!$A111) -> 0 | AP111: =SUMIFS('B1.SUM (tuần 4)'!$I:$I,'B1.SUM (tuần 4)'!$A:$A,'B0.SUM (tuần 0)'!$A111) -> 0 | AQ111: =I111-AP111 -> 0
A112: 1001110548 | B112: Máy lọc nước RO-01 POLAR | C112: RO-01 | D112: Máy TCM Sx | E112: 10L | F112: XK | H112: 1368111 | I112: =SUM(J112:P112) -> 0 | K112: =SUMIFS('B0.3.XK'!J:J,'B0.3.XK'!A:A,'B0.SUM (tuần 0)'!$A112) -> 0 | M112: =SUMIFS('B0.5.GT2'!K:K,'B0.5.GT2'!A:A,'B0.SUM (tuần 0)'!$A112) -> 0 | N112: =SUMIFS('B0.4.OEM'!J:J,'B0.4.OEM'!A:A,'B0.SUM (tuần 0)'!$A112) -> 0 | P112: =SUMIFS('B0.8.Online'!J:J,'B0.8.Online'!A:A,'B0.SUM (tuần 0)'!$A112) -> 0 | Q112: =SUM(R112:X112) -> 400 | S112: =SUMIFS('B0.3.XK'!K:K,'B0.3.XK'!A:A,'B0.SUM (tuần 0)'!$A112) -> 400 | U112: =SUMIFS('B0.5.GT2'!K:K,'B0.5.GT2'!A:A,'B0.SUM (tuần 0)'!$A112) -> 0 | V112: =SUMIFS('B0.4.OEM'!K:K,'B0.4.OEM'!A:A,'B0.SUM (tuần 0)'!$A112) -> 0 | X112: =SUMIFS('B0.8.Online'!K:K,'B0.8.Online'!A:A,'B0.SUM (tuần 0)'!$A112) -> 0 | Y112: =SUM(Z112:AF112) -> 0 | AA112: =SUMIFS('B0.3.XK'!L:L,'B0.3.XK'!A:A,'B0.SUM (tuần 0)'!$A112) -> 0 | AC112: =SUMIFS('B0.5.GT2'!L:L,'B0.5.GT2'!A:A,'B0.SUM (tuần 0)'!$A112) -> 0 | AD112: =SUMIFS('B0.4.OEM'!L:L,'B0.4.OEM'!A:A,'B0.SUM (tuần 0)'!$A112) -> 0 | AF112: =SUMIFS('B0.8.Online'!L:L,'B0.8.Online'!A:A,'B0.SUM (tuần 0)'!$A112) -> 0 | AG112: =SUM(AH112:AN112) -> 0 | AI112: =SUMIFS('B0.3.XK'!M:M,'B0.3.XK'!A:A,'B0.SUM (tuần 0)'!$A112) -> 0 | AK112: =SUMIFS('B0.5.GT2'!M:M,'B0.5.GT2'!A:A,'B0.SUM (tuần 0)'!$A112) -> 0 | AL112: =SUMIFS('B0.4.OEM'!M:M,'B0.4.OEM'!A:A,'B0.SUM (tuần 0)'!$A112) -> 0 | AN112: =SUMIFS('B0.8.Online'!M:M,'B0.8.Online'!A:A,'B0.SUM (tuần 0)'!$A112) -> 0 | AP112: =SUMIFS('B1.SUM (tuần 4)'!$I:$I,'B1.SUM (tuần 4)'!$A:$A,'B0.SUM (tuần 0)'!$A112) -> 0 | AQ112: =I112-AP112 -> 0
A113: 1001110563 | B113: Máy RO-01 PURE SPRING | C113: RO-01 | D113: Máy TCM Sx | E113: 10L | F113: XK | H113: 1389159 | I113: =SUM(J113:P113) -> 0 | K113: =SUMIFS('B0.3.XK'!J:J,'B0.3.XK'!A:A,'B0.SUM (tuần 0)'!$A113) -> 0 | M113: =SUMIFS('B0.5.GT2'!K:K,'B0.5.GT2'!A:A,'B0.SUM (tuần 0)'!$A113) -> 0 | N113: =SUMIFS('B0.4.OEM'!J:J,'B0.4.OEM'!A:A,'B0.SUM (tuần 0)'!$A113) -> 0 | P113: =SUMIFS('B0.8.Online'!J:J,'B0.8.Online'!A:A,'B0.SUM (tuần 0)'!$A113) -> 0 | Q113: =SUM(R113:X113) -> 0 | S113: =SUMIFS('B0.3.XK'!K:K,'B0.3.XK'!A:A,'B0.SUM (tuần 0)'!$A113) -> 0 | U113: =SUMIFS('B0.5.GT2'!K:K,'B0.5.GT2'!A:A,'B0.SUM (tuần 0)'!$A113) -> 0 | V113: =SUMIFS('B0.4.OEM'!K:K,'B0.4.OEM'!A:A,'B0.SUM (tuần 0)'!$A113) -> 0 | X113: =SUMIFS('B0.8.Online'!K:K,'B0.8.Online'!A:A,'B0.SUM (tuần 0)'!$A113) -> 0 | Y113: =SUM(Z113:AF113) -> 0 | AA113: =SUMIFS('B0.3.XK'!L:L,'B0.3.XK'!A:A,'B0.SUM (tuần 0)'!$A113) -> 0 | AC113: =SUMIFS('B0.5.GT2'!L:L,'B0.5.GT2'!A:A,'B0.SUM (tuần 0)'!$A113) -> 0 | AD113: =SUMIFS('B0.4.OEM'!L:L,'B0.4.OEM'!A:A,'B0.SUM (tuần 0)'!$A113) -> 0 | AF113: =SUMIFS('B0.8.Online'!L:L,'B0.8.Online'!A:A,'B0.SUM (tuần 0)'!$A113) -> 0 | AG113: =SUM(AH113:AN113) -> 0 | AI113: =SUMIFS('B0.3.XK'!M:M,'B0.3.XK'!A:A,'B0.SUM (tuần 0)'!$A113) -> 0 | AK113: =SUMIFS('B0.5.GT2'!M:M,'B0.5.GT2'!A:A,'B0.SUM (tuần 0)'!$A113) -> 0 | AL113: =SUMIFS('B0.4.OEM'!M:M,'B0.4.OEM'!A:A,'B0.SUM (tuần 0)'!$A113) -> 0 | AN113: =SUMIFS('B0.8.Online'!M:M,'B0.8.Online'!A:A,'B0.SUM (tuần 0)'!$A113) -> 0 | AP113: =SUMIFS('B1.SUM (tuần 4)'!$I:$I,'B1.SUM (tuần 4)'!$A:$A,'B0.SUM (tuần 0)'!$A113) -> 0 | AQ113: =I113-AP113 -> 0
A114: 1001110566 | B114: Máy lọc nước KAROFI KWP - D10LS1 (Anh) | C114: KAQ-U98 | D114: Máy TCM Sx | E114: 10L | F114: XK | H114: 2560473 | I114: =SUM(J114:P114) -> 0 | K114: =SUMIFS('B0.3.XK'!J:J,'B0.3.XK'!A:A,'B0.SUM (tuần 0)'!$A114) -> 0 | M114: =SUMIFS('B0.5.GT2'!K:K,'B0.5.GT2'!A:A,'B0.SUM (tuần 0)'!$A114) -> 0 | N114: =SUMIFS('B0.4.OEM'!J:J,'B0.4.OEM'!A:A,'B0.SUM (tuần 0)'!$A114) -> 0 | P114: =SUMIFS('B0.8.Online'!J:J,'B0.8.Online'!A:A,'B0.SUM (tuần 0)'!$A114) -> 0 | Q114: =SUM(R114:X114) -> 0 | S114: =SUMIFS('B0.3.XK'!K:K,'B0.3.XK'!A:A,'B0.SUM (tuần 0)'!$A114) -> 0 | U114: =SUMIFS('B0.5.GT2'!K:K,'B0.5.GT2'!A:A,'B0.SUM (tuần 0)'!$A114) -> 0 | V114: =SUMIFS('B0.4.OEM'!K:K,'B0.4.OEM'!A:A,'B0.SUM (tuần 0)'!$A114) -> 0 | X114: =SUMIFS('B0.8.Online'!K:K,'B0.8.Online'!A:A,'B0.SUM (tuần 0)'!$A114) -> 0 | Y114: =SUM(Z114:AF114) -> 0 | AA114: =SUMIFS('B0.3.XK'!L:L,'B0.3.XK'!A:A,'B0.SUM (tuần 0)'!$A114) -> 0 | AC114: =SUMIFS('B0.5.GT2'!L:L,'B0.5.GT2'!A:A,'B0.SUM (tuần 0)'!$A114) -> 0 | AD114: =SUMIFS('B0.4.OEM'!L:L,'B0.4.OEM'!A:A,'B0.SUM (tuần 0)'!$A114) -> 0 | AF114: =SUMIFS('B0.8.Online'!L:L,'B0.8.Online'!A:A,'B0.SUM (tuần 0)'!$A114) -> 0 | AG114: =SUM(AH114:AN114) -> 0 | AI114: =SUMIFS('B0.3.XK'!M:M,'B0.3.XK'!A:A,'B0.SUM (tuần 0)'!$A114) -> 0 | AK114: =SUMIFS('B0.5.GT2'!M:M,'B0.5.GT2'!A:A,'B0.SUM (tuần 0)'!$A114) -> 0 | AL114: =SUMIFS('B0.4.OEM'!M:M,'B0.4.OEM'!A:A,'B0.SUM (tuần 0)'!$A114) -> 0 | AN114: =SUMIFS('B0.8.Online'!M:M,'B0.8.Online'!A:A,'B0.SUM (tuần 0)'!$A114) -> 0 | AP114: =SUMIFS('B1.SUM (tuần 4)'!$I:$I,'B1.SUM (tuần 4)'!$A:$A,'B0.SUM (tuần 0)'!$A114) -> 0 | AQ114: =I114-AP114 -> 0
A115: 1001110569 | B115: Máy lọc nước NL KRF KWP - X11CS2 (Anh) | C115: KAD-X68 | D115: Máy TCM Sx | E115: Block | F115: XK | H115: 4671995 | I115: =SUM(J115:P115) -> 0 | K115: =SUMIFS('B0.3.XK'!J:J,'B0.3.XK'!A:A,'B0.SUM (tuần 0)'!$A115) -> 0 | M115: =SUMIFS('B0.5.GT2'!K:K,'B0.5.GT2'!A:A,'B0.SUM (tuần 0)'!$A115) -> 0 | N115: =SUMIFS('B0.4.OEM'!J:J,'B0.4.OEM'!A:A,'B0.SUM (tuần 0)'!$A115) -> 0 | P115: =SUMIFS('B0.8.Online'!J:J,'B0.8.Online'!A:A,'B0.SUM (tuần 0)'!$A115) -> 0 | Q115: =SUM(R115:X115) -> 0 | S115: =SUMIFS('B0.3.XK'!K:K,'B0.3.XK'!A:A,'B0.SUM (tuần 0)'!$A115) -> 0 | U115: =SUMIFS('B0.5.GT2'!K:K,'B0.5.GT2'!A:A,'B0.SUM (tuần 0)'!$A115) -> 0 | V115: =SUMIFS('B0.4.OEM'!K:K,'B0.4.OEM'!A:A,'B0.SUM (tuần 0)'!$A115) -> 0 | X115: =SUMIFS('B0.8.Online'!K:K,'B0.8.Online'!A:A,'B0.SUM (tuần 0)'!$A115) -> 0 | Y115: =SUM(Z115:AF115) -> 0 | AA115: =SUMIFS('B0.3.XK'!L:L,'B0.3.XK'!A:A,'B0.SUM (tuần 0)'!$A115) -> 0 | AC115: =SUMIFS('B0.5.GT2'!L:L,'B0.5.GT2'!A:A,'B0.SUM (tuần 0)'!$A115) -> 0 | AD115: =SUMIFS('B0.4.OEM'!L:L,'B0.4.OEM'!A:A,'B0.SUM (tuần 0)'!$A115) -> 0 | AF115: =SUMIFS('B0.8.Online'!L:L,'B0.8.Online'!A:A,'B0.SUM (tuần 0)'!$A115) -> 0 | AG115: =SUM(AH115:AN115) -> 0 | AI115: =SUMIFS('B0.3.XK'!M:M,'B0.3.XK'!A:A,'B0.SUM (tuần 0)'!$A115) -> 0 | AK115: =SUMIFS('B0.5.GT2'!M:M,'B0.5.GT2'!A:A,'B0.SUM (tuần 0)'!$A115) -> 0 | AL115: =SUMIFS('B0.4.OEM'!M:M,'B0.4.OEM'!A:A,'B0.SUM (tuần 0)'!$A115) -> 0 | AN115: =SUMIFS('B0.8.Online'!M:M,'B0.8.Online'!A:A,'B0.SUM (tuần 0)'!$A115) -> 0 | AP115: =SUMIFS('B1.SUM (tuần 4)'!$I:$I,'B1.SUM (tuần 4)'!$A:$A,'B0.SUM (tuần 0)'!$A115) -> 0 | AQ115: =I115-AP115 -> 0
A116: 1001110570 | B116: Máy lọc nước NL KRF KWP - X11LN2 (Anh) | C116: KAD-X58 | D116: Máy TCM Sx | E116: Block | F116: XK | H116: 4000831 | I116: =SUM(J116:P116) -> 0 | K116: =SUMIFS('B0.3.XK'!J:J,'B0.3.XK'!A:A,'B0.SUM (tuần 0)'!$A116) -> 0 | M116: =SUMIFS('B0.5.GT2'!K:K,'B0.5.GT2'!A:A,'B0.SUM (tuần 0)'!$A116) -> 0 | N116: =SUMIFS('B0.4.OEM'!J:J,'B0.4.OEM'!A:A,'B0.SUM (tuần 0)'!$A116) -> 0 | P116: =SUMIFS('B0.8.Online'!J:J,'B0.8.Online'!A:A,'B0.SUM (tuần 0)'!$A116) -> 0 | Q116: =SUM(R116:X116) -> 0 | S116: =SUMIFS('B0.3.XK'!K:K,'B0.3.XK'!A:A,'B0.SUM (tuần 0)'!$A116) -> 0 | U116: =SUMIFS('B0.5.GT2'!K:K,'B0.5.GT2'!A:A,'B0.SUM (tuần 0)'!$A116) -> 0 | V116: =SUMIFS('B0.4.OEM'!K:K,'B0.4.OEM'!A:A,'B0.SUM (tuần 0)'!$A116) -> 0 | X116: =SUMIFS('B0.8.Online'!K:K,'B0.8.Online'!A:A,'B0.SUM (tuần 0)'!$A116) -> 0 | Y116: =SUM(Z116:AF116) -> 59 | AA116: =SUMIFS('B0.3.XK'!L:L,'B0.3.XK'!A:A,'B0.SUM (tuần 0)'!$A116) -> 59 | AC116: =SUMIFS('B0.5.GT2'!L:L,'B0.5.GT2'!A:A,'B0.SUM (tuần 0)'!$A116) -> 0 | AD116: =SUMIFS('B0.4.OEM'!L:L,'B0.4.OEM'!A:A,'B0.SUM (tuần 0)'!$A116) -> 0 | AF116: =SUMIFS('B0.8.Online'!L:L,'B0.8.Online'!A:A,'B0.SUM (tuần 0)'!$A116) -> 0 | AG116: =SUM(AH116:AN116) -> 0 | AI116: =SUMIFS('B0.3.XK'!M:M,'B0.3.XK'!A:A,'B0.SUM (tuần 0)'!$A116) -> 0 | AK116: =SUMIFS('B0.5.GT2'!M:M,'B0.5.GT2'!A:A,'B0.SUM (tuần 0)'!$A116) -> 0 | AL116: =SUMIFS('B0.4.OEM'!M:M,'B0.4.OEM'!A:A,'B0.SUM (tuần 0)'!$A116) -> 0 | AN116: =SUMIFS('B0.8.Online'!M:M,'B0.8.Online'!A:A,'B0.SUM (tuần 0)'!$A116) -> 0 | AP116: =SUMIFS('B1.SUM (tuần 4)'!$I:$I,'B1.SUM (tuần 4)'!$A:$A,'B0.SUM (tuần 0)'!$A116) -> 0 | AQ116: =I116-AP116 -> 0
A117: 1001110571 | B117: Máy lọc nước KAROFI KWP - X11LN1 (Anh) | C117: KAQ-X18 | D117: Máy TCM Sx | E117: 10L Tủ | F117: XK | H117: 2729224 | I117: =SUM(J117:P117) -> 0 | K117: =SUMIFS('B0.3.XK'!J:J,'B0.3.XK'!A:A,'B0.SUM (tuần 0)'!$A117) -> 0 | M117: =SUMIFS('B0.5.GT2'!K:K,'B0.5.GT2'!A:A,'B0.SUM (tuần 0)'!$A117) -> 0 | N117: =SUMIFS('B0.4.OEM'!J:J,'B0.4.OEM'!A:A,'B0.SUM (tuần 0)'!$A117) -> 0 | P117: =SUMIFS('B0.8.Online'!J:J,'B0.8.Online'!A:A,'B0.SUM (tuần 0)'!$A117) -> 0 | Q117: =SUM(R117:X117) -> 0 | S117: =SUMIFS('B0.3.XK'!K:K,'B0.3.XK'!A:A,'B0.SUM (tuần 0)'!$A117) -> 0 | U117: =SUMIFS('B0.5.GT2'!K:K,'B0.5.GT2'!A:A,'B0.SUM (tuần 0)'!$A117) -> 0 | V117: =SUMIFS('B0.4.OEM'!K:K,'B0.4.OEM'!A:A,'B0.SUM (tuần 0)'!$A117) -> 0 | X117: =SUMIFS('B0.8.Online'!K:K,'B0.8.Online'!A:A,'B0.SUM (tuần 0)'!$A117) -> 0 | Y117: =SUM(Z117:AF117) -> 60 | AA117: =SUMIFS('B0.3.XK'!L:L,'B0.3.XK'!A:A,'B0.SUM (tuần 0)'!$A117) -> 60 | AC117: =SUMIFS('B0.5.GT2'!L:L,'B0.5.GT2'!A:A,'B0.SUM (tuần 0)'!$A117) -> 0 | AD117: =SUMIFS('B0.4.OEM'!L:L,'B0.4.OEM'!A:A,'B0.SUM (tuần 0)'!$A117) -> 0 | AF117: =SUMIFS('B0.8.Online'!L:L,'B0.8.Online'!A:A,'B0.SUM (tuần 0)'!$A117) -> 0 | AG117: =SUM(AH117:AN117) -> 0 | AI117: =SUMIFS('B0.3.XK'!M:M,'B0.3.XK'!A:A,'B0.SUM (tuần 0)'!$A117) -> 0 | AK117: =SUMIFS('B0.5.GT2'!M:M,'B0.5.GT2'!A:A,'B0.SUM (tuần 0)'!$A117) -> 0 | AL117: =SUMIFS('B0.4.OEM'!M:M,'B0.4.OEM'!A:A,'B0.SUM (tuần 0)'!$A117) -> 0 | AN117: =SUMIFS('B0.8.Online'!M:M,'B0.8.Online'!A:A,'B0.SUM (tuần 0)'!$A117) -> 0 | AP117: =SUMIFS('B1.SUM (tuần 4)'!$I:$I,'B1.SUM (tuần 4)'!$A:$A,'B0.SUM (tuần 0)'!$A117) -> 0 | AQ117: =I117-AP117 -> 0
A118: 1001110572 | B118: Máy lọc nước KRF KWP - U10CN1 (Anh) | C118: KAQ-U05 Pro | D118: Máy TCM Sx | E118: 10L | F118: XK | H118: 1901149 | I118: =SUM(J118:P118) -> 0 | K118: =SUMIFS('B0.3.XK'!J:J,'B0.3.XK'!A:A,'B0.SUM (tuần 0)'!$A118) -> 0 | M118: =SUMIFS('B0.5.GT2'!K:K,'B0.5.GT2'!A:A,'B0.SUM (tuần 0)'!$A118) -> 0 | N118: =SUMIFS('B0.4.OEM'!J:J,'B0.4.OEM'!A:A,'B0.SUM (tuần 0)'!$A118) -> 0 | P118: =SUMIFS('B0.8.Online'!J:J,'B0.8.Online'!A:A,'B0.SUM (tuần 0)'!$A118) -> 0 | Q118: =SUM(R118:X118) -> 0 | S118: =SUMIFS('B0.3.XK'!K:K,'B0.3.XK'!A:A,'B0.SUM (tuần 0)'!$A118) -> 0 | U118: =SUMIFS('B0.5.GT2'!K:K,'B0.5.GT2'!A:A,'B0.SUM (tuần 0)'!$A118) -> 0 | V118: =SUMIFS('B0.4.OEM'!K:K,'B0.4.OEM'!A:A,'B0.SUM (tuần 0)'!$A118) -> 0 | X118: =SUMIFS('B0.8.Online'!K:K,'B0.8.Online'!A:A,'B0.SUM (tuần 0)'!$A118) -> 0 | Y118: =SUM(Z118:AF118) -> 50 | AA118: =SUMIFS('B0.3.XK'!L:L,'B0.3.XK'!A:A,'B0.SUM (tuần 0)'!$A118) -> 50 | AC118: =SUMIFS('B0.5.GT2'!L:L,'B0.5.GT2'!A:A,'B0.SUM (tuần 0)'!$A118) -> 0 | AD118: =SUMIFS('B0.4.OEM'!L:L,'B0.4.OEM'!A:A,'B0.SUM (tuần 0)'!$A118) -> 0 | AF118: =SUMIFS('B0.8.Online'!L:L,'B0.8.Online'!A:A,'B0.SUM (tuần 0)'!$A118) -> 0 | AG118: =SUM(AH118:AN118) -> 0 | AI118: =SUMIFS('B0.3.XK'!M:M,'B0.3.XK'!A:A,'B0.SUM (tuần 0)'!$A118) -> 0 | AK118: =SUMIFS('B0.5.GT2'!M:M,'B0.5.GT2'!A:A,'B0.SUM (tuần 0)'!$A118) -> 0 | AL118: =SUMIFS('B0.4.OEM'!M:M,'B0.4.OEM'!A:A,'B0.SUM (tuần 0)'!$A118) -> 0 | AN118: =SUMIFS('B0.8.Online'!M:M,'B0.8.Online'!A:A,'B0.SUM (tuần 0)'!$A118) -> 0 | AP118: =SUMIFS('B1.SUM (tuần 4)'!$I:$I,'B1.SUM (tuần 4)'!$A:$A,'B0.SUM (tuần 0)'!$A118) -> 0 | AQ118: =I118-AP118 -> 0
A119: 1001110575 | B119: Water purifier U05 Pro WATERNESS | C119: KAQ-U05 Pro | D119: Máy TCM Sx | E119: 10L | F119: XK | H119: 2025857 | I119: =SUM(J119:P119) -> 0 | K119: =SUMIFS('B0.3.XK'!J:J,'B0.3.XK'!A:A,'B0.SUM (tuần 0)'!$A119) -> 0 | M119: =SUMIFS('B0.5.GT2'!K:K,'B0.5.GT2'!A:A,'B0.SUM (tuần 0)'!$A119) -> 0 | N119: =SUMIFS('B0.4.OEM'!J:J,'B0.4.OEM'!A:A,'B0.SUM (tuần 0)'!$A119) -> 0 | P119: =SUMIFS('B0.8.Online'!J:J,'B0.8.Online'!A:A,'B0.SUM (tuần 0)'!$A119) -> 0 | Q119: =SUM(R119:X119) -> 0 | S119: =SUMIFS('B0.3.XK'!K:K,'B0.3.XK'!A:A,'B0.SUM (tuần 0)'!$A119) -> 0 | U119: =SUMIFS('B0.5.GT2'!K:K,'B0.5.GT2'!A:A,'B0.SUM (tuần 0)'!$A119) -> 0 | V119: =SUMIFS('B0.4.OEM'!K:K,'B0.4.OEM'!A:A,'B0.SUM (tuần 0)'!$A119) -> 0 | X119: =SUMIFS('B0.8.Online'!K:K,'B0.8.Online'!A:A,'B0.SUM (tuần 0)'!$A119) -> 0 | Y119: =SUM(Z119:AF119) -> 0 | AA119: =SUMIFS('B0.3.XK'!L:L,'B0.3.XK'!A:A,'B0.SUM (tuần 0)'!$A119) -> 0 | AC119: =SUMIFS('B0.5.GT2'!L:L,'B0.5.GT2'!A:A,'B0.SUM (tuần 0)'!$A119) -> 0 | AD119: =SUMIFS('B0.4.OEM'!L:L,'B0.4.OEM'!A:A,'B0.SUM (tuần 0)'!$A119) -> 0 | AF119: =SUMIFS('B0.8.Online'!L:L,'B0.8.Online'!A:A,'B0.SUM (tuần 0)'!$A119) -> 0 | AG119: =SUM(AH119:AN119) -> 0 | AI119: =SUMIFS('B0.3.XK'!M:M,'B0.3.XK'!A:A,'B0.SUM (tuần 0)'!$A119) -> 0 | AK119: =SUMIFS('B0.5.GT2'!M:M,'B0.5.GT2'!A:A,'B0.SUM (tuần 0)'!$A119) -> 0 | AL119: =SUMIFS('B0.4.OEM'!M:M,'B0.4.OEM'!A:A,'B0.SUM (tuần 0)'!$A119) -> 0 | AN119: =SUMIFS('B0.8.Online'!M:M,'B0.8.Online'!A:A,'B0.SUM (tuần 0)'!$A119) -> 0 | AP119: =SUMIFS('B1.SUM (tuần 4)'!$I:$I,'B1.SUM (tuần 4)'!$A:$A,'B0.SUM (tuần 0)'!$A119) -> 0 | AQ119: =I119-AP119 -> 0
A120: 1001110576 | B120: Máy lọc nước U05 Pro KAROFI (Anh) v5 | C120: KAQ-U05 Pro | D120: Máy TCM Sx | E120: 10L | F120: XK | H120: 1886415 | I120: =SUM(J120:P120) -> 300 | K120: =SUMIFS('B0.3.XK'!J:J,'B0.3.XK'!A:A,'B0.SUM (tuần 0)'!$A120) -> 300 | M120: =SUMIFS('B0.5.GT2'!K:K,'B0.5.GT2'!A:A,'B0.SUM (tuần 0)'!$A120) -> 0 | N120: =SUMIFS('B0.4.OEM'!J:J,'B0.4.OEM'!A:A,'B0.SUM (tuần 0)'!$A120) -> 0 | P120: =SUMIFS('B0.8.Online'!J:J,'B0.8.Online'!A:A,'B0.SUM (tuần 0)'!$A120) -> 0 | Q120: =SUM(R120:X120) -> 0 | S120: =SUMIFS('B0.3.XK'!K:K,'B0.3.XK'!A:A,'B0.SUM (tuần 0)'!$A120) -> 0 | U120: =SUMIFS('B0.5.GT2'!K:K,'B0.5.GT2'!A:A,'B0.SUM (tuần 0)'!$A120) -> 0 | V120: =SUMIFS('B0.4.OEM'!K:K,'B0.4.OEM'!A:A,'B0.SUM (tuần 0)'!$A120) -> 0 | X120: =SUMIFS('B0.8.Online'!K:K,'B0.8.Online'!A:A,'B0.SUM (tuần 0)'!$A120) -> 0 | Y120: =SUM(Z120:AF120) -> 50 | AA120: =SUMIFS('B0.3.XK'!L:L,'B0.3.XK'!A:A,'B0.SUM (tuần 0)'!$A120) -> 50 | AC120: =SUMIFS('B0.5.GT2'!L:L,'B0.5.GT2'!A:A,'B0.SUM (tuần 0)'!$A120) -> 0 | AD120: =SUMIFS('B0.4.OEM'!L:L,'B0.4.OEM'!A:A,'B0.SUM (tuần 0)'!$A120) -> 0 | AF120: =SUMIFS('B0.8.Online'!L:L,'B0.8.Online'!A:A,'B0.SUM (tuần 0)'!$A120) -> 0 | AG120: =SUM(AH120:AN120) -> 0 | AI120: =SUMIFS('B0.3.XK'!M:M,'B0.3.XK'!A:A,'B0.SUM (tuần 0)'!$A120) -> 0 | AK120: =SUMIFS('B0.5.GT2'!M:M,'B0.5.GT2'!A:A,'B0.SUM (tuần 0)'!$A120) -> 0 | AL120: =SUMIFS('B0.4.OEM'!M:M,'B0.4.OEM'!A:A,'B0.SUM (tuần 0)'!$A120) -> 0 | AN120: =SUMIFS('B0.8.Online'!M:M,'B0.8.Online'!A:A,'B0.SUM (tuần 0)'!$A120) -> 0 | AP120: =SUMIFS('B1.SUM (tuần 4)'!$I:$I,'B1.SUM (tuần 4)'!$A:$A,'B0.SUM (tuần 0)'!$A120) -> 0 | AQ120: =I120-AP120 -> 300
A121: 1001110578 | B121: Máy lọc nước UNDERSINK đen Polar | C121: S-S027 | D121: Máy TCM Sx | E121: 10L | F121: XK | H121: 2282378 | I121: =SUM(J121:P121) -> 0 | K121: =SUMIFS('B0.3.XK'!J:J,'B0.3.XK'!A:A,'B0.SUM (tuần 0)'!$A121) -> 0 | M121: =SUMIFS('B0.5.GT2'!K:K,'B0.5.GT2'!A:A,'B0.SUM (tuần 0)'!$A121) -> 0 | N121: =SUMIFS('B0.4.OEM'!J:J,'B0.4.OEM'!A:A,'B0.SUM (tuần 0)'!$A121) -> 0 | P121: =SUMIFS('B0.8.Online'!J:J,'B0.8.Online'!A:A,'B0.SUM (tuần 0)'!$A121) -> 0 | Q121: =SUM(R121:X121) -> 200 | S121: =SUMIFS('B0.3.XK'!K:K,'B0.3.XK'!A:A,'B0.SUM (tuần 0)'!$A121) -> 200 | U121: =SUMIFS('B0.5.GT2'!K:K,'B0.5.GT2'!A:A,'B0.SUM (tuần 0)'!$A121) -> 0 | V121: =SUMIFS('B0.4.OEM'!K:K,'B0.4.OEM'!A:A,'B0.SUM (tuần 0)'!$A121) -> 0 | X121: =SUMIFS('B0.8.Online'!K:K,'B0.8.Online'!A:A,'B0.SUM (tuần 0)'!$A121) -> 0 | Y121: =SUM(Z121:AF121) -> 0 | AA121: =SUMIFS('B0.3.XK'!L:L,'B0.3.XK'!A:A,'B0.SUM (tuần 0)'!$A121) -> 0 | AC121: =SUMIFS('B0.5.GT2'!L:L,'B0.5.GT2'!A:A,'B0.SUM (tuần 0)'!$A121) -> 0 | AD121: =SUMIFS('B0.4.OEM'!L:L,'B0.4.OEM'!A:A,'B0.SUM (tuần 0)'!$A121) -> 0 | AF121: =SUMIFS('B0.8.Online'!L:L,'B0.8.Online'!A:A,'B0.SUM (tuần 0)'!$A121) -> 0 | AG121: =SUM(AH121:AN121) -> 0 | AI121: =SUMIFS('B0.3.XK'!M:M,'B0.3.XK'!A:A,'B0.SUM (tuần 0)'!$A121) -> 0 | AK121: =SUMIFS('B0.5.GT2'!M:M,'B0.5.GT2'!A:A,'B0.SUM (tuần 0)'!$A121) -> 0 | AL121: =SUMIFS('B0.4.OEM'!M:M,'B0.4.OEM'!A:A,'B0.SUM (tuần 0)'!$A121) -> 0 | AN121: =SUMIFS('B0.8.Online'!M:M,'B0.8.Online'!A:A,'B0.SUM (tuần 0)'!$A121) -> 0 | AP121: =SUMIFS('B1.SUM (tuần 4)'!$I:$I,'B1.SUM (tuần 4)'!$A:$A,'B0.SUM (tuần 0)'!$A121) -> 0 | AQ121: =I121-AP121 -> 0
... A129: 1001110588 | B129: Máy NL KRF PHC11DNA100 Brills (X68) | C129: KAD-X68 | D129: Máy TCM Sx | E129: Block | F129: XK | H129: 3781688 | I129: =SUM(J129:P129) -> 0 | K129: =SUMIFS('B0.3.XK'!J:J,'B0.3.XK'!A:A,'B0.SUM (tuần 0)'!$A129) -> 0 | M129: =SUMIFS('B0.5.GT2'!K:K,'B0.5.GT2'!A:A,'B0.SUM (tuần 0)'!$A129) -> 0 | N129: =SUMIFS('B0.4.OEM'!J:J,'B0.4.OEM'!A:A,'B0.SUM (tuần 0)'!$A129) -> 0 | P129: =SUMIFS('B0.8.Online'!J:J,'B0.8.Online'!A:A,'B0.SUM (tuần 0)'!$A129) -> 0 | Q129: =SUM(R129:X129) -> 200 | S129: =SUMIFS('B0.3.XK'!K:K,'B0.3.XK'!A:A,'B0.SUM (tuần 0)'!$A129) -> 200 | U129: =SUMIFS('B0.5.GT2'!K:K,'B0.5.GT2'!A:A,'B0.SUM (tuần 0)'!$A129) -> 0 | V129: =SUMIFS('B0.4.OEM'!K:K,'B0.4.OEM'!A:A,'B0.SUM (tuần 0)'!$A129) -> 0 | X129: =SUMIFS('B0.8.Online'!K:K,'B0.8.Online'!A:A,'B0.SUM (tuần 0)'!$A129) -> 0 | Y129: =SUM(Z129:AF129) -> 0 | AA129: =SUMIFS('B0.3.XK'!L:L,'B0.3.XK'!A:A,'B0.SUM (tuần 0)'!$A129) -> 0 | AC129: =SUMIFS('B0.5.GT2'!L:L,'B0.5.GT2'!A:A,'B0.SUM (tuần 0)'!$A129) -> 0 | AD129: =SUMIFS('B0.4.OEM'!L:L,'B0.4.OEM'!A:A,'B0.SUM (tuần 0)'!$A129) -> 0 | AF129: =SUMIFS('B0.8.Online'!L:L,'B0.8.Online'!A:A,'B0.SUM (tuần 0)'!$A129) -> 0 | AG129: =SUM(AH129:AN129) -> 0 | AI129: =SUMIFS('B0.3.XK'!M:M,'B0.3.XK'!A:A,'B0.SUM (tuần 0)'!$A129) -> 0 | AK129: =SUMIFS('B0.5.GT2'!M:M,'B0.5.GT2'!A:A,'B0.SUM (tuần 0)'!$A129) -> 0 | AL129: =SUMIFS('B0.4.OEM'!M:M,'B0.4.OEM'!A:A,'B0.SUM (tuần 0)'!$A129) -> 0 | AN129: =SUMIFS('B0.8.Online'!M:M,'B0.8.Online'!A:A,'B0.SUM (tuần 0)'!$A129) -> 0 | AP129: =SUMIFS('B1.SUM (tuần 4)'!$I:$I,'B1.SUM (tuần 4)'!$A:$A,'B0.SUM (tuần 0)'!$A129) -> 0 | AQ129: =I129-AP129 -> 0
A130: 1001110589 | B130: Máy LN KAROFI PHC11-100 Brills (X18) | C130: KAQ-X18 | D130: Máy TCM Sx | E130: 10L Tủ | F130: XK | H130: 2241861 | I130: =SUM(J130:P130) -> 0 | K130: =SUMIFS('B0.3.XK'!J:J,'B0.3.XK'!A:A,'B0.SUM (tuần 0)'!$A130) -> 0 | M130: =SUMIFS('B0.5.GT2'!K:K,'B0.5.GT2'!A:A,'B0.SUM (tuần 0)'!$A130) -> 0 | N130: =SUMIFS('B0.4.OEM'!J:J,'B0.4.OEM'!A:A,'B0.SUM (tuần 0)'!$A130) -> 0 | P130: =SUMIFS('B0.8.Online'!J:J,'B0.8.Online'!A:A,'B0.SUM (tuần 0)'!$A130) -> 0 | Q130: =SUM(R130:X130) -> 101 | S130: =SUMIFS('B0.3.XK'!K:K,'B0.3.XK'!A:A,'B0.SUM (tuần 0)'!$A130) -> 101 | U130: =SUMIFS('B0.5.GT2'!K:K,'B0.5.GT2'!A:A,'B0.SUM (tuần 0)'!$A130) -> 0 | V130: =SUMIFS('B0.4.OEM'!K:K,'B0.4.OEM'!A:A,'B0.SUM (tuần 0)'!$A130) -> 0 | X130: =SUMIFS('B0.8.Online'!K:K,'B0.8.Online'!A:A,'B0.SUM (tuần 0)'!$A130) -> 0 | Y130: =SUM(Z130:AF130) -> 120 | AA130: =SUMIFS('B0.3.XK'!L:L,'B0.3.XK'!A:A,'B0.SUM (tuần 0)'!$A130) -> 120 | AC130: =SUMIFS('B0.5.GT2'!L:L,'B0.5.GT2'!A:A,'B0.SUM (tuần 0)'!$A130) -> 0 | AD130: =SUMIFS('B0.4.OEM'!L:L,'B0.4.OEM'!A:A,'B0.SUM (tuần 0)'!$A130) -> 0 | AF130: =SUMIFS('B0.8.Online'!L:L,'B0.8.Online'!A:A,'B0.SUM (tuần 0)'!$A130) -> 0 | AG130: =SUM(AH130:AN130) -> 0 | AI130: =SUMIFS('B0.3.XK'!M:M,'B0.3.XK'!A:A,'B0.SUM (tuần 0)'!$A130) -> 0 | AK130: =SUMIFS('B0.5.GT2'!M:M,'B0.5.GT2'!A:A,'B0.SUM (tuần 0)'!$A130) -> 0 | AL130: =SUMIFS('B0.4.OEM'!M:M,'B0.4.OEM'!A:A,'B0.SUM (tuần 0)'!$A130) -> 0 | AN130: =SUMIFS('B0.8.Online'!M:M,'B0.8.Online'!A:A,'B0.SUM (tuần 0)'!$A130) -> 0 | AO130: Model clear, bán hết tồn NVL | AP130: =SUMIFS('B1.SUM (tuần 4)'!$I:$I,'B1.SUM (tuần 4)'!$A:$A,'B0.SUM (tuần 0)'!$A130) -> 0 | AQ130: =I130-AP130 -> 0
A131: 1001110591 | B131: Máy lọc nước RO-401 WATER MASTER(8S) | C131: RO-401 | D131: Máy TCM Sx | E131: 10L | F131: XK | H131: 1486506 | I131: =SUM(J131:P131) -> 0 | K131: =SUMIFS('B0.3.XK'!J:J,'B0.3.XK'!A:A,'B0.SUM (tuần 0)'!$A131) -> 0 | M131: =SUMIFS('B0.5.GT2'!K:K,'B0.5.GT2'!A:A,'B0.SUM (tuần 0)'!$A131) -> 0 | N131: =SUMIFS('B0.4.OEM'!J:J,'B0.4.OEM'!A:A,'B0.SUM (tuần 0)'!$A131) -> 0 | P131: =SUMIFS('B0.8.Online'!J:J,'B0.8.Online'!A:A,'B0.SUM (tuần 0)'!$A131) -> 0 | Q131: =SUM(R131:X131) -> 300 | S131: =SUMIFS('B0.3.XK'!K:K,'B0.3.XK'!A:A,'B0.SUM (tuần 0)'!$A131) -> 300 | U131: =SUMIFS('B0.5.GT2'!K:K,'B0.5.GT2'!A:A,'B0.SUM (tuần 0)'!$A131) -> 0 | V131: =SUMIFS('B0.4.OEM'!K:K,'B0.4.OEM'!A:A,'B0.SUM (tuần 0)'!$A131) -> 0 | X131: =SUMIFS('B0.8.Online'!K:K,'B0.8.Online'!A:A,'B0.SUM (tuần 0)'!$A131) -> 0 | Y131: =SUM(Z131:AF131) -> 0 | AA131: =SUMIFS('B0.3.XK'!L:L,'B0.3.XK'!A:A,'B0.SUM (tuần 0)'!$A131) -> 0 | AC131: =SUMIFS('B0.5.GT2'!L:L,'B0.5.GT2'!A:A,'B0.SUM (tuần 0)'!$A131) -> 0 | AD131: =SUMIFS('B0.4.OEM'!L:L,'B0.4.OEM'!A:A,'B0.SUM (tuần 0)'!$A131) -> 0 | AF131: =SUMIFS('B0.8.Online'!L:L,'B0.8.Online'!A:A,'B0.SUM (tuần 0)'!$A131) -> 0 | AG131: =SUM(AH131:AN131) -> 0 | AI131: =SUMIFS('B0.3.XK'!M:M,'B0.3.XK'!A:A,'B0.SUM (tuần 0)'!$A131) -> 0 | AK131: =SUMIFS('B0.5.GT2'!M:M,'B0.5.GT2'!A:A,'B0.SUM (tuần 0)'!$A131) -> 0 | AL131: =SUMIFS('B0.4.OEM'!M:M,'B0.4.OEM'!A:A,'B0.SUM (tuần 0)'!$A131) -> 0 | AN131: =SUMIFS('B0.8.Online'!M:M,'B0.8.Online'!A:A,'B0.SUM (tuần 0)'!$A131) -> 0 | AP131: =SUMIFS('B1.SUM (tuần 4)'!$I:$I,'B1.SUM (tuần 4)'!$A:$A,'B0.SUM (tuần 0)'!$A131) -> 0 | AQ131: =I131-AP131 -> 0
A132: 1001110592 | B132: Máy lọc nước RO-107 NQAA ALMAA v3 | C132: RO-107 | D132: Máy TCM Sx | E132: 10L | F132: XK | H132: 2057805 | I132: =SUM(J132:P132) -> 0 | K132: =SUMIFS('B0.3.XK'!J:J,'B0.3.XK'!A:A,'B0.SUM (tuần 0)'!$A132) -> 0 | M132: =SUMIFS('B0.5.GT2'!K:K,'B0.5.GT2'!A:A,'B0.SUM (tuần 0)'!$A132) -> 0 | N132: =SUMIFS('B0.4.OEM'!J:J,'B0.4.OEM'!A:A,'B0.SUM (tuần 0)'!$A132) -> 0 | P132: =SUMIFS('B0.8.Online'!J:J,'B0.8.Online'!A:A,'B0.SUM (tuần 0)'!$A132) -> 0 | Q132: =SUM(R132:X132) -> 0 | S132: =SUMIFS('B0.3.XK'!K:K,'B0.3.XK'!A:A,'B0.SUM (tuần 0)'!$A132) -> 0 | U132: =SUMIFS('B0.5.GT2'!K:K,'B0.5.GT2'!A:A,'B0.SUM (tuần 0)'!$A132) -> 0 | V132: =SUMIFS('B0.4.OEM'!K:K,'B0.4.OEM'!A:A,'B0.SUM (tuần 0)'!$A132) -> 0 | X132: =SUMIFS('B0.8.Online'!K:K,'B0.8.Online'!A:A,'B0.SUM (tuần 0)'!$A132) -> 0 | Y132: =SUM(Z132:AF132) -> 0 | AA132: =SUMIFS('B0.3.XK'!L:L,'B0.3.XK'!A:A,'B0.SUM (tuần 0)'!$A132) -> 0 | AC132: =SUMIFS('B0.5.GT2'!L:L,'B0.5.GT2'!A:A,'B0.SUM (tuần 0)'!$A132) -> 0 | AD132: =SUMIFS('B0.4.OEM'!L:L,'B0.4.OEM'!A:A,'B0.SUM (tuần 0)'!$A132) -> 0 | AF132: =SUMIFS('B0.8.Online'!L:L,'B0.8.Online'!A:A,'B0.SUM (tuần 0)'!$A132) -> 0 | AG132: =SUM(AH132:AN132) -> 0 | AI132: =SUMIFS('B0.3.XK'!M:M,'B0.3.XK'!A:A,'B0.SUM (tuần 0)'!$A132) -> 0 | AK132: =SUMIFS('B0.5.GT2'!M:M,'B0.5.GT2'!A:A,'B0.SUM (tuần 0)'!$A132) -> 0 | AL132: =SUMIFS('B0.4.OEM'!M:M,'B0.4.OEM'!A:A,'B0.SUM (tuần 0)'!$A132) -> 0 | AN132: =SUMIFS('B0.8.Online'!M:M,'B0.8.Online'!A:A,'B0.SUM (tuần 0)'!$A132) -> 0 | AP132: =SUMIFS('B1.SUM (tuần 4)'!$I:$I,'B1.SUM (tuần 4)'!$A:$A,'B0.SUM (tuần 0)'!$A132) -> 0 | AQ132: =I132-AP132 -> 0
A133: 1001110593 | B133: Máy lọc nước RO-04 NQAA ALMAA v3 | C133: RO-04 | D133: Máy TCM Sx | E133: 10L | F133: XK | H133: 1928803 | I133: =SUM(J133:P133) -> 0 | K133: =SUMIFS('B0.3.XK'!J:J,'B0.3.XK'!A:A,'B0.SUM (tuần 0)'!$A133) -> 0 | M133: =SUMIFS('B0.5.GT2'!K:K,'B0.5.GT2'!A:A,'B0.SUM (tuần 0)'!$A133) -> 0 | N133: =SUMIFS('B0.4.OEM'!J:J,'B0.4.OEM'!A:A,'B0.SUM (tuần 0)'!$A133) -> 0 | P133: =SUMIFS('B0.8.Online'!J:J,'B0.8.Online'!A:A,'B0.SUM (tuần 0)'!$A133) -> 0 | Q133: =SUM(R133:X133) -> 0 | S133: =SUMIFS('B0.3.XK'!K:K,'B0.3.XK'!A:A,'B0.SUM (tuần 0)'!$A133) -> 0 | U133: =SUMIFS('B0.5.GT2'!K:K,'B0.5.GT2'!A:A,'B0.SUM (tuần 0)'!$A133) -> 0 | V133: =SUMIFS('B0.4.OEM'!K:K,'B0.4.OEM'!A:A,'B0.SUM (tuần 0)'!$A133) -> 0 | X133: =SUMIFS('B0.8.Online'!K:K,'B0.8.Online'!A:A,'B0.SUM (tuần 0)'!$A133) -> 0 | Y133: =SUM(Z133:AF133) -> 0 | AA133: =SUMIFS('B0.3.XK'!L:L,'B0.3.XK'!A:A,'B0.SUM (tuần 0)'!$A133) -> 0 | AC133: =SUMIFS('B0.5.GT2'!L:L,'B0.5.GT2'!A:A,'B0.SUM (tuần 0)'!$A133) -> 0 | AD133: =SUMIFS('B0.4.OEM'!L:L,'B0.4.OEM'!A:A,'B0.SUM (tuần 0)'!$A133) -> 0 | AF133: =SUMIFS('B0.8.Online'!L:L,'B0.8.Online'!A:A,'B0.SUM (tuần 0)'!$A133) -> 0 | AG133: =SUM(AH133:AN133) -> 0 | AI133: =SUMIFS('B0.3.XK'!M:M,'B0.3.XK'!A:A,'B0.SUM (tuần 0)'!$A133) -> 0 | AK133: =SUMIFS('B0.5.GT2'!M:M,'B0.5.GT2'!A:A,'B0.SUM (tuần 0)'!$A133) -> 0 | AL133: =SUMIFS('B0.4.OEM'!M:M,'B0.4.OEM'!A:A,'B0.SUM (tuần 0)'!$A133) -> 0 | AN133: =SUMIFS('B0.8.Online'!M:M,'B0.8.Online'!A:A,'B0.SUM (tuần 0)'!$A133) -> 0 | AP133: =SUMIFS('B1.SUM (tuần 4)'!$I:$I,'B1.SUM (tuần 4)'!$A:$A,'B0.SUM (tuần 0)'!$A133) -> 0 | AQ133: =I133-AP133 -> 0
A134: 1001110597 | B134: Máy lọc nước RO-100 LIVOTEC (7S) | C134: RO-100 | D134: Máy TCM Sx | E134: 10L | F134: XK | H134: 1565435 | I134: =SUM(J134:P134) -> 0 | K134: =SUMIFS('B0.3.XK'!J:J,'B0.3.XK'!A:A,'B0.SUM (tuần 0)'!$A134) -> 0 | M134: =SUMIFS('B0.5.GT2'!K:K,'B0.5.GT2'!A:A,'B0.SUM (tuần 0)'!$A134) -> 0 | N134: =SUMIFS('B0.4.OEM'!J:J,'B0.4.OEM'!A:A,'B0.SUM (tuần 0)'!$A134) -> 0 | P134: =SUMIFS('B0.8.Online'!J:J,'B0.8.Online'!A:A,'B0.SUM (tuần 0)'!$A134) -> 0 | Q134: =SUM(R134:X134) -> 120 | S134: =SUMIFS('B0.3.XK'!K:K,'B0.3.XK'!A:A,'B0.SUM (tuần 0)'!$A134) -> 120 | U134: =SUMIFS('B0.5.GT2'!K:K,'B0.5.GT2'!A:A,'B0.SUM (tuần 0)'!$A134) -> 0 | V134: =SUMIFS('B0.4.OEM'!K:K,'B0.4.OEM'!A:A,'B0.SUM (tuần 0)'!$A134) -> 0 | X134: =SUMIFS('B0.8.Online'!K:K,'B0.8.Online'!A:A,'B0.SUM (tuần 0)'!$A134) -> 0 | Y134: =SUM(Z134:AF134) -> 0 | AA134: =SUMIFS('B0.3.XK'!L:L,'B0.3.XK'!A:A,'B0.SUM (tuần 0)'!$A134) -> 0 | AC134: =SUMIFS('B0.5.GT2'!L:L,'B0.5.GT2'!A:A,'B0.SUM (tuần 0)'!$A134) -> 0 | AD134: =SUMIFS('B0.4.OEM'!L:L,'B0.4.OEM'!A:A,'B0.SUM (tuần 0)'!$A134) -> 0 | AF134: =SUMIFS('B0.8.Online'!L:L,'B0.8.Online'!A:A,'B0.SUM (tuần 0)'!$A134) -> 0 | AG134: =SUM(AH134:AN134) -> 0 | AI134: =SUMIFS('B0.3.XK'!M:M,'B0.3.XK'!A:A,'B0.SUM (tuần 0)'!$A134) -> 0 | AK134: =SUMIFS('B0.5.GT2'!M:M,'B0.5.GT2'!A:A,'B0.SUM (tuần 0)'!$A134) -> 0 | AL134: =SUMIFS('B0.4.OEM'!M:M,'B0.4.OEM'!A:A,'B0.SUM (tuần 0)'!$A134) -> 0 | AN134: =SUMIFS('B0.8.Online'!M:M,'B0.8.Online'!A:A,'B0.SUM (tuần 0)'!$A134) -> 0 | AP134: =SUMIFS('B1.SUM (tuần 4)'!$I:$I,'B1.SUM (tuần 4)'!$A:$A,'B0.SUM (tuần 0)'!$A134) -> 0 | AQ134: =I134-AP134 -> 0
A135: 1001110598 | B135: Máy lọc nước RO-01 LIVOTEC (7S) | C135: RO-01 | D135: Máy TCM Sx | E135: 10L | F135: XK | H135: 1439148 | I135: =SUM(J135:P135) -> 0 | K135: =SUMIFS('B0.3.XK'!J:J,'B0.3.XK'!A:A,'B0.SUM (tuần 0)'!$A135) -> 0 | M135: =SUMIFS('B0.5.GT2'!K:K,'B0.5.GT2'!A:A,'B0.SUM (tuần 0)'!$A135) -> 0 | N135: =SUMIFS('B0.4.OEM'!J:J,'B0.4.OEM'!A:A,'B0.SUM (tuần 0)'!$A135) -> 0 | P135: =SUMIFS('B0.8.Online'!J:J,'B0.8.Online'!A:A,'B0.SUM (tuần 0)'!$A135) -> 0 | Q135: =SUM(R135:X135) -> 450 | S135: =SUMIFS('B0.3.XK'!K:K,'B0.3.XK'!A:A,'B0.SUM (tuần 0)'!$A135) -> 450 | U135: =SUMIFS('B0.5.GT2'!K:K,'B0.5.GT2'!A:A,'B0.SUM (tuần 0)'!$A135) -> 0 | V135: =SUMIFS('B0.4.OEM'!K:K,'B0.4.OEM'!A:A,'B0.SUM (tuần 0)'!$A135) -> 0 | X135: =SUMIFS('B0.8.Online'!K:K,'B0.8.Online'!A:A,'B0.SUM (tuần 0)'!$A135) -> 0 | Y135: =SUM(Z135:AF135) -> 0 | AA135: =SUMIFS('B0.3.XK'!L:L,'B0.3.XK'!A:A,'B0.SUM (tuần 0)'!$A135) -> 0 | AC135: =SUMIFS('B0.5.GT2'!L:L,'B0.5.GT2'!A:A,'B0.SUM (tuần 0)'!$A135) -> 0 | AD135: =SUMIFS('B0.4.OEM'!L:L,'B0.4.OEM'!A:A,'B0.SUM (tuần 0)'!$A135) -> 0 | AF135: =SUMIFS('B0.8.Online'!L:L,'B0.8.Online'!A:A,'B0.SUM (tuần 0)'!$A135) -> 0 | AG135: =SUM(AH135:AN135) -> 0 | AI135: =SUMIFS('B0.3.XK'!M:M,'B0.3.XK'!A:A,'B0.SUM (tuần 0)'!$A135) -> 0 | AK135: =SUMIFS('B0.5.GT2'!M:M,'B0.5.GT2'!A:A,'B0.SUM (tuần 0)'!$A135) -> 0 | AL135: =SUMIFS('B0.4.OEM'!M:M,'B0.4.OEM'!A:A,'B0.SUM (tuần 0)'!$A135) -> 0 | AN135: =SUMIFS('B0.8.Online'!M:M,'B0.8.Online'!A:A,'B0.SUM (tuần 0)'!$A135) -> 0 | AP135: =SUMIFS('B1.SUM (tuần 4)'!$I:$I,'B1.SUM (tuần 4)'!$A:$A,'B0.SUM (tuần 0)'!$A135) -> 0 | AQ135: =I135-AP135 -> 0
A136: 1001110600 | B136: Máy lọc nước ERO70 LIVOTEC | C136: ERO70 | D136: Máy TCM Sx | E136: 10L Tủ | F136: XK | H136: 2273170 | I136: =SUM(J136:P136) -> 0 | K136: =SUMIFS('B0.3.XK'!J:J,'B0.3.XK'!A:A,'B0.SUM (tuần 0)'!$A136) -> 0 | M136: =SUMIFS('B0.5.GT2'!K:K,'B0.5.GT2'!A:A,'B0.SUM (tuần 0)'!$A136) -> 0 | N136: =SUMIFS('B0.4.OEM'!J:J,'B0.4.OEM'!A:A,'B0.SUM (tuần 0)'!$A136) -> 0 | P136: =SUMIFS('B0.8.Online'!J:J,'B0.8.Online'!A:A,'B0.SUM (tuần 0)'!$A136) -> 0 | Q136: =SUM(R136:X136) -> 50 | S136: =SUMIFS('B0.3.XK'!K:K,'B0.3.XK'!A:A,'B0.SUM (tuần 0)'!$A136) -> 50 | U136: =SUMIFS('B0.5.GT2'!K:K,'B0.5.GT2'!A:A,'B0.SUM (tuần 0)'!$A136) -> 0 | V136: =SUMIFS('B0.4.OEM'!K:K,'B0.4.OEM'!A:A,'B0.SUM (tuần 0)'!$A136) -> 0 | X136: =SUMIFS('B0.8.Online'!K:K,'B0.8.Online'!A:A,'B0.SUM (tuần 0)'!$A136) -> 0 | Y136: =SUM(Z136:AF136) -> 0 | AA136: =SUMIFS('B0.3.XK'!L:L,'B0.3.XK'!A:A,'B0.SUM (tuần 0)'!$A136) -> 0 | AC136: =SUMIFS('B0.5.GT2'!L:L,'B0.5.GT2'!A:A,'B0.SUM (tuần 0)'!$A136) -> 0 | AD136: =SUMIFS('B0.4.OEM'!L:L,'B0.4.OEM'!A:A,'B0.SUM (tuần 0)'!$A136) -> 0 | AF136: =SUMIFS('B0.8.Online'!L:L,'B0.8.Online'!A:A,'B0.SUM (tuần 0)'!$A136) -> 0 | AG136: =SUM(AH136:AN136) -> 0 | AI136: =SUMIFS('B0.3.XK'!M:M,'B0.3.XK'!A:A,'B0.SUM (tuần 0)'!$A136) -> 0 | AK136: =SUMIFS('B0.5.GT2'!M:M,'B0.5.GT2'!A:A,'B0.SUM (tuần 0)'!$A136) -> 0 | AL136: =SUMIFS('B0.4.OEM'!M:M,'B0.4.OEM'!A:A,'B0.SUM (tuần 0)'!$A136) -> 0 | AN136: =SUMIFS('B0.8.Online'!M:M,'B0.8.Online'!A:A,'B0.SUM (tuần 0)'!$A136) -> 0 | AP136: =SUMIFS('B1.SUM (tuần 4)'!$I:$I,'B1.SUM (tuần 4)'!$A:$A,'B0.SUM (tuần 0)'!$A136) -> 0 | AQ136: =I136-AP136 -> 0
A137: 1001110604 | B137: Máy lọc nước nóng lạnh Livotec 630 (Anh) | C137: LVT-600 | D137: Máy TCM Sx | E137: Block | F137: XK | H137: 4267455 | I137: =SUM(J137:P137) -> 0 | K137: =SUMIFS('B0.3.XK'!J:J,'B0.3.XK'!A:A,'B0.SUM (tuần 0)'!$A137) -> 0 | M137: =SUMIFS('B0.5.GT2'!K:K,'B0.5.GT2'!A:A,'B0.SUM (tuần 0)'!$A137) -> 0 | N137: =SUMIFS('B0.4.OEM'!J:J,'B0.4.OEM'!A:A,'B0.SUM (tuần 0)'!$A137) -> 0 | P137: =SUMIFS('B0.8.Online'!J:J,'B0.8.Online'!A:A,'B0.SUM (tuần 0)'!$A137) -> 0 | Q137: =SUM(R137:X137) -> 0 | S137: =SUMIFS('B0.3.XK'!K:K,'B0.3.XK'!A:A,'B0.SUM (tuần 0)'!$A137) -> 0 | U137: =SUMIFS('B0.5.GT2'!K:K,'B0.5.GT2'!A:A,'B0.SUM (tuần 0)'!$A137) -> 0 | V137: =SUMIFS('B0.4.OEM'!K:K,'B0.4.OEM'!A:A,'B0.SUM (tuần 0)'!$A137) -> 0 | X137: =SUMIFS('B0.8.Online'!K:K,'B0.8.Online'!A:A,'B0.SUM (tuần 0)'!$A137) -> 0 | Y137: =SUM(Z137:AF137) -> 0 | AA137: =SUMIFS('B0.3.XK'!L:L,'B0.3.XK'!A:A,'B0.SUM (tuần 0)'!$A137) -> 0 | AC137: =SUMIFS('B0.5.GT2'!L:L,'B0.5.GT2'!A:A,'B0.SUM (tuần 0)'!$A137) -> 0 | AD137: =SUMIFS('B0.4.OEM'!L:L,'B0.4.OEM'!A:A,'B0.SUM (tuần 0)'!$A137) -> 0 | AF137: =SUMIFS('B0.8.Online'!L:L,'B0.8.Online'!A:A,'B0.SUM (tuần 0)'!$A137) -> 0 | AG137: =SUM(AH137:AN137) -> 0 | AI137: =SUMIFS('B0.3.XK'!M:M,'B0.3.XK'!A:A,'B0.SUM (tuần 0)'!$A137) -> 0 | AK137: =SUMIFS('B0.5.GT2'!M:M,'B0.5.GT2'!A:A,'B0.SUM (tuần 0)'!$A137) -> 0 | AL137: =SUMIFS('B0.4.OEM'!M:M,'B0.4.OEM'!A:A,'B0.SUM (tuần 0)'!$A137) -> 0 | AN137: =SUMIFS('B0.8.Online'!M:M,'B0.8.Online'!A:A,'B0.SUM (tuần 0)'!$A137) -> 0 | AP137: =SUMIFS('B1.SUM (tuần 4)'!$I:$I,'B1.SUM (tuần 4)'!$A:$A,'B0.SUM (tuần 0)'!$A137) -> 0 | AQ137: =I137-AP137 -> 0
A138: 1001110605 | B138: Máy lọc nước AQUALAND 522 (Anh) | C138: LVT-522 | D138: Máy TCM Sx | E138: 10L Tủ | F138: XK | H138: 2367885 | I138: =SUM(J138:P138) -> 0 | K138: =SUMIFS('B0.3.XK'!J:J,'B0.3.XK'!A:A,'B0.SUM (tuần 0)'!$A138) -> 0 | M138: =SUMIFS('B0.5.GT2'!K:K,'B0.5.GT2'!A:A,'B0.SUM (tuần 0)'!$A138) -> 0 | N138: =SUMIFS('B0.4.OEM'!J:J,'B0.4.OEM'!A:A,'B0.SUM (tuần 0)'!$A138) -> 0 | P138: =SUMIFS('B0.8.Online'!J:J,'B0.8.Online'!A:A,'B0.SUM (tuần 0)'!$A138) -> 0 | Q138: =SUM(R138:X138) -> 0 | S138: =SUMIFS('B0.3.XK'!K:K,'B0.3.XK'!A:A,'B0.SUM (tuần 0)'!$A138) -> 0 | U138: =SUMIFS('B0.5.GT2'!K:K,'B0.5.GT2'!A:A,'B0.SUM (tuần 0)'!$A138) -> 0 | V138: =SUMIFS('B0.4.OEM'!K:K,'B0.4.OEM'!A:A,'B0.SUM (tuần 0)'!$A138) -> 0 | X138: =SUMIFS('B0.8.Online'!K:K,'B0.8.Online'!A:A,'B0.SUM (tuần 0)'!$A138) -> 0 | Y138: =SUM(Z138:AF138) -> 0 | AA138: =SUMIFS('B0.3.XK'!L:L,'B0.3.XK'!A:A,'B0.SUM (tuần 0)'!$A138) -> 0 | AC138: =SUMIFS('B0.5.GT2'!L:L,'B0.5.GT2'!A:A,'B0.SUM (tuần 0)'!$A138) -> 0 | AD138: =SUMIFS('B0.4.OEM'!L:L,'B0.4.OEM'!A:A,'B0.SUM (tuần 0)'!$A138) -> 0 | AF138: =SUMIFS('B0.8.Online'!L:L,'B0.8.Online'!A:A,'B0.SUM (tuần 0)'!$A138) -> 0 | AG138: =SUM(AH138:AN138) -> 0 | AI138: =SUMIFS('B0.3.XK'!M:M,'B0.3.XK'!A:A,'B0.SUM (tuần 0)'!$A138) -> 0 | AK138: =SUMIFS('B0.5.GT2'!M:M,'B0.5.GT2'!A:A,'B0.SUM (tuần 0)'!$A138) -> 0 | AL138: =SUMIFS('B0.4.OEM'!M:M,'B0.4.OEM'!A:A,'B0.SUM (tuần 0)'!$A138) -> 0 | AN138: =SUMIFS('B0.8.Online'!M:M,'B0.8.Online'!A:A,'B0.SUM (tuần 0)'!$A138) -> 0 | AP138: =SUMIFS('B1.SUM (tuần 4)'!$I:$I,'B1.SUM (tuần 4)'!$A:$A,'B0.SUM (tuần 0)'!$A138) -> 0 | AQ138: =I138-AP138 -> 0
A139: 1001110607 | B139: Máy lọc nước KAROFI KAQ-U65 v2 | C139: KAQ-U65 | D139: Máy TCM Sx | E139: 10L | F139: XK | H139: 1986787 | I139: =SUM(J139:P139) -> 300 | K139: =SUMIFS('B0.3.XK'!J:J,'B0.3.XK'!A:A,'B0.SUM (tuần 0)'!$A139) -> 300 | M139: =SUMIFS('B0.5.GT2'!K:K,'B0.5.GT2'!A:A,'B0.SUM (tuần 0)'!$A139) -> 0 | N139: =SUMIFS('B0.4.OEM'!J:J,'B0.4.OEM'!A:A,'B0.SUM (tuần 0)'!$A139) -> 0 | P139: =SUMIFS('B0.8.Online'!J:J,'B0.8.Online'!A:A,'B0.SUM (tuần 0)'!$A139) -> 0 | Q139: =SUM(R139:X139) -> 0 | S139: =SUMIFS('B0.3.XK'!K:K,'B0.3.XK'!A:A,'B0.SUM (tuần 0)'!$A139) -> 0 | U139: =SUMIFS('B0.5.GT2'!K:K,'B0.5.GT2'!A:A,'B0.SUM (tuần 0)'!$A139) -> 0 | V139: =SUMIFS('B0.4.OEM'!K:K,'B0.4.OEM'!A:A,'B0.SUM (tuần 0)'!$A139) -> 0 | X139: =SUMIFS('B0.8.Online'!K:K,'B0.8.Online'!A:A,'B0.SUM (tuần 0)'!$A139) -> 0 | Y139: =SUM(Z139:AF139) -> 0 | AA139: =SUMIFS('B0.3.XK'!L:L,'B0.3.XK'!A:A,'B0.SUM (tuần 0)'!$A139) -> 0 | AC139: =SUMIFS('B0.5.GT2'!L:L,'B0.5.GT2'!A:A,'B0.SUM (tuần 0)'!$A139) -> 0 | AD139: =SUMIFS('B0.4.OEM'!L:L,'B0.4.OEM'!A:A,'B0.SUM (tuần 0)'!$A139) -> 0 | AF139: =SUMIFS('B0.8.Online'!L:L,'B0.8.Online'!A:A,'B0.SUM (tuần 0)'!$A139) -> 0 | AG139: =SUM(AH139:AN139) -> 0 | AI139: =SUMIFS('B0.3.XK'!M:M,'B0.3.XK'!A:A,'B0.SUM (tuần 0)'!$A139) -> 0 | AK139: =SUMIFS('B0.5.GT2'!M:M,'B0.5.GT2'!A:A,'B0.SUM (tuần 0)'!$A139) -> 0 | AL139: =SUMIFS('B0.4.OEM'!M:M,'B0.4.OEM'!A:A,'B0.SUM (tuần 0)'!$A139) -> 0 | AN139: =SUMIFS('B0.8.Online'!M:M,'B0.8.Online'!A:A,'B0.SUM (tuần 0)'!$A139) -> 0 | AP139: =SUMIFS('B1.SUM (tuần 4)'!$I:$I,'B1.SUM (tuần 4)'!$A:$A,'B0.SUM (tuần 0)'!$A139) -> 0 | AQ139: =I139-AP139 -> 300
A140: 1001110609 | B140: Máy lọc nước nóng lạnh KAROFI KAD-X58 v2 | C140: KAD-X58 | D140: Máy TCM Sx | E140: Block | F140: XK | H140: 4788390 | I140: =SUM(J140:P140) -> 30 | K140: =SUMIFS('B0.3.XK'!J:J,'B0.3.XK'!A:A,'B0.SUM (tuần 0)'!$A140) -> 30 | M140: =SUMIFS('B0.5.GT2'!K:K,'B0.5.GT2'!A:A,'B0.SUM (tuần 0)'!$A140) -> 0 | N140: =SUMIFS('B0.4.OEM'!J:J,'B0.4.OEM'!A:A,'B0.SUM (tuần 0)'!$A140) -> 0 | P140: =SUMIFS('B0.8.Online'!J:J,'B0.8.Online'!A:A,'B0.SUM (tuần 0)'!$A140) -> 0 | Q140: =SUM(R140:X140) -> 0 | S140: =SUMIFS('B0.3.XK'!K:K,'B0.3.XK'!A:A,'B0.SUM (tuần 0)'!$A140) -> 0 | U140: =SUMIFS('B0.5.GT2'!K:K,'B0.5.GT2'!A:A,'B0.SUM (tuần 0)'!$A140) -> 0 | V140: =SUMIFS('B0.4.OEM'!K:K,'B0.4.OEM'!A:A,'B0.SUM (tuần 0)'!$A140) -> 0 | X140: =SUMIFS('B0.8.Online'!K:K,'B0.8.Online'!A:A,'B0.SUM (tuần 0)'!$A140) -> 0 | Y140: =SUM(Z140:AF140) -> 0 | AA140: =SUMIFS('B0.3.XK'!L:L,'B0.3.XK'!A:A,'B0.SUM (tuần 0)'!$A140) -> 0 | AC140: =SUMIFS('B0.5.GT2'!L:L,'B0.5.GT2'!A:A,'B0.SUM (tuần 0)'!$A140) -> 0 | AD140: =SUMIFS('B0.4.OEM'!L:L,'B0.4.OEM'!A:A,'B0.SUM (tuần 0)'!$A140) -> 0 | AF140: =SUMIFS('B0.8.Online'!L:L,'B0.8.Online'!A:A,'B0.SUM (tuần 0)'!$A140) -> 0 | AG140: =SUM(AH140:AN140) -> 0 | AI140: =SUMIFS('B0.3.XK'!M:M,'B0.3.XK'!A:A,'B0.SUM (tuần 0)'!$A140) -> 0 | AK140: =SUMIFS('B0.5.GT2'!M:M,'B0.5.GT2'!A:A,'B0.SUM (tuần 0)'!$A140) -> 0 | AL140: =SUMIFS('B0.4.OEM'!M:M,'B0.4.OEM'!A:A,'B0.SUM (tuần 0)'!$A140) -> 0 | AN140: =SUMIFS('B0.8.Online'!M:M,'B0.8.Online'!A:A,'B0.SUM (tuần 0)'!$A140) -> 0 | AP140: =SUMIFS('B1.SUM (tuần 4)'!$I:$I,'B1.SUM (tuần 4)'!$A:$A,'B0.SUM (tuần 0)'!$A140) -> 0 | AQ140: =I140-AP140 -> 30
A141: 1001110610 | B141: Máy lọc nước Undersink đen World Filter | C141: S-S027 | D141: Máy TCM Sx | E141: 10L | F141: XK | H141: 2759902 | I141: =SUM(J141:P141) -> 0 | K141: =SUMIFS('B0.3.XK'!J:J,'B0.3.XK'!A:A,'B0.SUM (tuần 0)'!$A141) -> 0 | M141: =SUMIFS('B0.5.GT2'!K:K,'B0.5.GT2'!A:A,'B0.SUM (tuần 0)'!$A141) -> 0 | N141: =SUMIFS('B0.4.OEM'!J:J,'B0.4.OEM'!A:A,'B0.SUM (tuần 0)'!$A141) -> 0 | P141: =SUMIFS('B0.8.Online'!J:J,'B0.8.Online'!A:A,'B0.SUM (tuần 0)'!$A141) -> 0 | Q141: =SUM(R141:X141) -> 0 | S141: =SUMIFS('B0.3.XK'!K:K,'B0.3.XK'!A:A,'B0.SUM (tuần 0)'!$A141) -> 0 | U141: =SUMIFS('B0.5.GT2'!K:K,'B0.5.GT2'!A:A,'B0.SUM (tuần 0)'!$A141) -> 0 | V141: =SUMIFS('B0.4.OEM'!K:K,'B0.4.OEM'!A:A,'B0.SUM (tuần 0)'!$A141) -> 0 | X141: =SUMIFS('B0.8.Online'!K:K,'B0.8.Online'!A:A,'B0.SUM (tuần 0)'!$A141) -> 0 | Y141: =SUM(Z141:AF141) -> 200 | AA141: =SUMIFS('B0.3.XK'!L:L,'B0.3.XK'!A:A,'B0.SUM (tuần 0)'!$A141) -> 200 | AC141: =SUMIFS('B0.5.GT2'!L:L,'B0.5.GT2'!A:A,'B0.SUM (tuần 0)'!$A141) -> 0 | AD141: =SUMIFS('B0.4.OEM'!L:L,'B0.4.OEM'!A:A,'B0.SUM (tuần 0)'!$A141) -> 0 | AF141: =SUMIFS('B0.8.Online'!L:L,'B0.8.Online'!A:A,'B0.SUM (tuần 0)'!$A141) -> 0 | AG141: =SUM(AH141:AN141) -> 0 | AI141: =SUMIFS('B0.3.XK'!M:M,'B0.3.XK'!A:A,'B0.SUM (tuần 0)'!$A141) -> 0 | AK141: =SUMIFS('B0.5.GT2'!M:M,'B0.5.GT2'!A:A,'B0.SUM (tuần 0)'!$A141) -> 0 | AL141: =SUMIFS('B0.4.OEM'!M:M,'B0.4.OEM'!A:A,'B0.SUM (tuần 0)'!$A141) -> 0 | AN141: =SUMIFS('B0.8.Online'!M:M,'B0.8.Online'!A:A,'B0.SUM (tuần 0)'!$A141) -> 0 | AP141: =SUMIFS('B1.SUM (tuần 4)'!$I:$I,'B1.SUM (tuần 4)'!$A:$A,'B0.SUM (tuần 0)'!$A141) -> 0 | AQ141: =I141-AP141 -> 0
A142: 1001110611 | B142: Máy lọc nước Undersink xanh World Filter | C142: S-S027 | D142: Máy TCM Sx | E142: 10L | F142: XK | H142: 2509958 | I142: =SUM(J142:P142) -> 0 | K142: =SUMIFS('B0.3.XK'!J:J,'B0.3.XK'!A:A,'B0.SUM (tuần 0)'!$A142) -> 0 | M142: =SUMIFS('B0.5.GT2'!K:K,'B0.5.GT2'!A:A,'B0.SUM (tuần 0)'!$A142) -> 0 | N142: =SUMIFS('B0.4.OEM'!J:J,'B0.4.OEM'!A:A,'B0.SUM (tuần 0)'!$A142) -> 0 | P142: =SUMIFS('B0.8.Online'!J:J,'B0.8.Online'!A:A,'B0.SUM (tuần 0)'!$A142) -> 0 | Q142: =SUM(R142:X142) -> 0 | S142: =SUMIFS('B0.3.XK'!K:K,'B0.3.XK'!A:A,'B0.SUM (tuần 0)'!$A142) -> 0 | U142: =SUMIFS('B0.5.GT2'!K:K,'B0.5.GT2'!A:A,'B0.SUM (tuần 0)'!$A142) -> 0 | V142: =SUMIFS('B0.4.OEM'!K:K,'B0.4.OEM'!A:A,'B0.SUM (tuần 0)'!$A142) -> 0 | X142: =SUMIFS('B0.8.Online'!K:K,'B0.8.Online'!A:A,'B0.SUM (tuần 0)'!$A142) -> 0 | Y142: =SUM(Z142:AF142) -> 200 | AA142: =SUMIFS('B0.3.XK'!L:L,'B0.3.XK'!A:A,'B0.SUM (tuần 0)'!$A142) -> 200 | AC142: =SUMIFS('B0.5.GT2'!L:L,'B0.5.GT2'!A:A,'B0.SUM (tuần 0)'!$A142) -> 0 | AD142: =SUMIFS('B0.4.OEM'!L:L,'B0.4.OEM'!A:A,'B0.SUM (tuần 0)'!$A142) -> 0 | AF142: =SUMIFS('B0.8.Online'!L:L,'B0.8.Online'!A:A,'B0.SUM (tuần 0)'!$A142) -> 0 | AG142: =SUM(AH142:AN142) -> 0 | AI142: =SUMIFS('B0.3.XK'!M:M,'B0.3.XK'!A:A,'B0.SUM (tuần 0)'!$A142) -> 0 | AK142: =SUMIFS('B0.5.GT2'!M:M,'B0.5.GT2'!A:A,'B0.SUM (tuần 0)'!$A142) -> 0 | AL142: =SUMIFS('B0.4.OEM'!M:M,'B0.4.OEM'!A:A,'B0.SUM (tuần 0)'!$A142) -> 0 | AN142: =SUMIFS('B0.8.Online'!M:M,'B0.8.Online'!A:A,'B0.SUM (tuần 0)'!$A142) -> 0 | AP142: =SUMIFS('B1.SUM (tuần 4)'!$I:$I,'B1.SUM (tuần 4)'!$A:$A,'B0.SUM (tuần 0)'!$A142) -> 0 | AQ142: =I142-AP142 -> 0
... A161: 1001110679 | B161: Máy lọc nước WAZF600 (U99) | C161: KAQ-U99 | D161: Máy TCM Sx | E161: BCN | F161: XK | H161: 5632936 | I161: =SUM(J161:P161) -> 0 | K161: =SUMIFS('B0.3.XK'!J:J,'B0.3.XK'!A:A,'B0.SUM (tuần 0)'!$A161) -> 0 | M161: =SUMIFS('B0.5.GT2'!K:K,'B0.5.GT2'!A:A,'B0.SUM (tuần 0)'!$A161) -> 0 | N161: =SUMIFS('B0.4.OEM'!J:J,'B0.4.OEM'!A:A,'B0.SUM (tuần 0)'!$A161) -> 0 | P161: =SUMIFS('B0.8.Online'!J:J,'B0.8.Online'!A:A,'B0.SUM (tuần 0)'!$A161) -> 0 | Q161: =SUM(R161:X161) -> 0 | S161: =SUMIFS('B0.3.XK'!K:K,'B0.3.XK'!A:A,'B0.SUM (tuần 0)'!$A161) -> 0 | U161: =SUMIFS('B0.5.GT2'!K:K,'B0.5.GT2'!A:A,'B0.SUM (tuần 0)'!$A161) -> 0 | V161: =SUMIFS('B0.4.OEM'!K:K,'B0.4.OEM'!A:A,'B0.SUM (tuần 0)'!$A161) -> 0 | X161: =SUMIFS('B0.8.Online'!K:K,'B0.8.Online'!A:A,'B0.SUM (tuần 0)'!$A161) -> 0 | Y161: =SUM(Z161:AF161) -> 0 | AA161: =SUMIFS('B0.3.XK'!L:L,'B0.3.XK'!A:A,'B0.SUM (tuần 0)'!$A161) -> 0 | AC161: =SUMIFS('B0.5.GT2'!L:L,'B0.5.GT2'!A:A,'B0.SUM (tuần 0)'!$A161) -> 0 | AD161: =SUMIFS('B0.4.OEM'!L:L,'B0.4.OEM'!A:A,'B0.SUM (tuần 0)'!$A161) -> 0 | AF161: =SUMIFS('B0.8.Online'!L:L,'B0.8.Online'!A:A,'B0.SUM (tuần 0)'!$A161) -> 0 | AG161: =SUM(AH161:AN161) -> 0 | AI161: =SUMIFS('B0.3.XK'!M:M,'B0.3.XK'!A:A,'B0.SUM (tuần 0)'!$A161) -> 0 | AK161: =SUMIFS('B0.5.GT2'!M:M,'B0.5.GT2'!A:A,'B0.SUM (tuần 0)'!$A161) -> 0 | AL161: =SUMIFS('B0.4.OEM'!M:M,'B0.4.OEM'!A:A,'B0.SUM (tuần 0)'!$A161) -> 0 | AN161: =SUMIFS('B0.8.Online'!M:M,'B0.8.Online'!A:A,'B0.SUM (tuần 0)'!$A161) -> 0 | AP161: =SUMIFS('B1.SUM (tuần 4)'!$I:$I,'B1.SUM (tuần 4)'!$A:$A,'B0.SUM (tuần 0)'!$A161) -> 0 | AQ161: =I161-AP161 -> 0
A162: 1001110680 | B162: Máy lọc nước nóng lạnh WAZC11 (D66S) | D162: Máy TCM Sx | F162: XK | H162: 4759186 | I162: =SUM(J162:P162) -> 0 | K162: =SUMIFS('B0.3.XK'!J:J,'B0.3.XK'!A:A,'B0.SUM (tuần 0)'!$A162) -> 0 | M162: =SUMIFS('B0.5.GT2'!K:K,'B0.5.GT2'!A:A,'B0.SUM (tuần 0)'!$A162) -> 0 | N162: =SUMIFS('B0.4.OEM'!J:J,'B0.4.OEM'!A:A,'B0.SUM (tuần 0)'!$A162) -> 0 | P162: =SUMIFS('B0.8.Online'!J:J,'B0.8.Online'!A:A,'B0.SUM (tuần 0)'!$A162) -> 0 | Q162: =SUM(R162:X162) -> 0 | S162: =SUMIFS('B0.3.XK'!K:K,'B0.3.XK'!A:A,'B0.SUM (tuần 0)'!$A162) -> 0 | U162: =SUMIFS('B0.5.GT2'!K:K,'B0.5.GT2'!A:A,'B0.SUM (tuần 0)'!$A162) -> 0 | V162: =SUMIFS('B0.4.OEM'!K:K,'B0.4.OEM'!A:A,'B0.SUM (tuần 0)'!$A162) -> 0 | X162: =SUMIFS('B0.8.Online'!K:K,'B0.8.Online'!A:A,'B0.SUM (tuần 0)'!$A162) -> 0 | Y162: =SUM(Z162:AF162) -> 0 | AA162: =SUMIFS('B0.3.XK'!L:L,'B0.3.XK'!A:A,'B0.SUM (tuần 0)'!$A162) -> 0 | AC162: =SUMIFS('B0.5.GT2'!L:L,'B0.5.GT2'!A:A,'B0.SUM (tuần 0)'!$A162) -> 0 | AD162: =SUMIFS('B0.4.OEM'!L:L,'B0.4.OEM'!A:A,'B0.SUM (tuần 0)'!$A162) -> 0 | AF162: =SUMIFS('B0.8.Online'!L:L,'B0.8.Online'!A:A,'B0.SUM (tuần 0)'!$A162) -> 0 | AG162: =SUM(AH162:AN162) -> 0 | AI162: =SUMIFS('B0.3.XK'!M:M,'B0.3.XK'!A:A,'B0.SUM (tuần 0)'!$A162) -> 0 | AK162: =SUMIFS('B0.5.GT2'!M:M,'B0.5.GT2'!A:A,'B0.SUM (tuần 0)'!$A162) -> 0 | AL162: =SUMIFS('B0.4.OEM'!M:M,'B0.4.OEM'!A:A,'B0.SUM (tuần 0)'!$A162) -> 0 | AN162: =SUMIFS('B0.8.Online'!M:M,'B0.8.Online'!A:A,'B0.SUM (tuần 0)'!$A162) -> 0 | AP162: =SUMIFS('B1.SUM (tuần 4)'!$I:$I,'B1.SUM (tuần 4)'!$A:$A,'B0.SUM (tuần 0)'!$A162) -> 0 | AQ162: =I162-AP162 -> 0
A163: 1001110681 | B163: Máy lọc nước RO-106 HITEK CQ ngược(7S) | C163: RO-106 | D163: Máy TCM Sx | E163: 10L | F163: XK | H163: 1315492 | I163: =SUM(J163:P163) -> 0 | K163: =SUMIFS('B0.3.XK'!J:J,'B0.3.XK'!A:A,'B0.SUM (tuần 0)'!$A163) -> 0 | M163: =SUMIFS('B0.5.GT2'!K:K,'B0.5.GT2'!A:A,'B0.SUM (tuần 0)'!$A163) -> 0 | N163: =SUMIFS('B0.4.OEM'!J:J,'B0.4.OEM'!A:A,'B0.SUM (tuần 0)'!$A163) -> 0 | P163: =SUMIFS('B0.8.Online'!J:J,'B0.8.Online'!A:A,'B0.SUM (tuần 0)'!$A163) -> 0 | Q163: =SUM(R163:X163) -> 20 | S163: =SUMIFS('B0.3.XK'!K:K,'B0.3.XK'!A:A,'B0.SUM (tuần 0)'!$A163) -> 20 | U163: =SUMIFS('B0.5.GT2'!K:K,'B0.5.GT2'!A:A,'B0.SUM (tuần 0)'!$A163) -> 0 | V163: =SUMIFS('B0.4.OEM'!K:K,'B0.4.OEM'!A:A,'B0.SUM (tuần 0)'!$A163) -> 0 | X163: =SUMIFS('B0.8.Online'!K:K,'B0.8.Online'!A:A,'B0.SUM (tuần 0)'!$A163) -> 0 | Y163: =SUM(Z163:AF163) -> 0 | AA163: =SUMIFS('B0.3.XK'!L:L,'B0.3.XK'!A:A,'B0.SUM (tuần 0)'!$A163) -> 0 | AC163: =SUMIFS('B0.5.GT2'!L:L,'B0.5.GT2'!A:A,'B0.SUM (tuần 0)'!$A163) -> 0 | AD163: =SUMIFS('B0.4.OEM'!L:L,'B0.4.OEM'!A:A,'B0.SUM (tuần 0)'!$A163) -> 0 | AF163: =SUMIFS('B0.8.Online'!L:L,'B0.8.Online'!A:A,'B0.SUM (tuần 0)'!$A163) -> 0 | AG163: =SUM(AH163:AN163) -> 0 | AI163: =SUMIFS('B0.3.XK'!M:M,'B0.3.XK'!A:A,'B0.SUM (tuần 0)'!$A163) -> 0 | AK163: =SUMIFS('B0.5.GT2'!M:M,'B0.5.GT2'!A:A,'B0.SUM (tuần 0)'!$A163) -> 0 | AL163: =SUMIFS('B0.4.OEM'!M:M,'B0.4.OEM'!A:A,'B0.SUM (tuần 0)'!$A163) -> 0 | AN163: =SUMIFS('B0.8.Online'!M:M,'B0.8.Online'!A:A,'B0.SUM (tuần 0)'!$A163) -> 0 | AP163: =SUMIFS('B1.SUM (tuần 4)'!$I:$I,'B1.SUM (tuần 4)'!$A:$A,'B0.SUM (tuần 0)'!$A163) -> 0 | AQ163: =I163-AP163 -> 0
A164: 1001110682 | B164: Máy LN RO-106 HI TECH-Xanh CQ ngược(7S) | C164: RO-106 | D164: Máy TCM Sx | E164: 10L | F164: XK | H164: 1315492 | I164: =SUM(J164:P164) -> 0 | K164: =SUMIFS('B0.3.XK'!J:J,'B0.3.XK'!A:A,'B0.SUM (tuần 0)'!$A164) -> 0 | M164: =SUMIFS('B0.5.GT2'!K:K,'B0.5.GT2'!A:A,'B0.SUM (tuần 0)'!$A164) -> 0 | N164: =SUMIFS('B0.4.OEM'!J:J,'B0.4.OEM'!A:A,'B0.SUM (tuần 0)'!$A164) -> 0 | P164: =SUMIFS('B0.8.Online'!J:J,'B0.8.Online'!A:A,'B0.SUM (tuần 0)'!$A164) -> 0 | Q164: =SUM(R164:X164) -> 20 | S164: =SUMIFS('B0.3.XK'!K:K,'B0.3.XK'!A:A,'B0.SUM (tuần 0)'!$A164) -> 20 | U164: =SUMIFS('B0.5.GT2'!K:K,'B0.5.GT2'!A:A,'B0.SUM (tuần 0)'!$A164) -> 0 | V164: =SUMIFS('B0.4.OEM'!K:K,'B0.4.OEM'!A:A,'B0.SUM (tuần 0)'!$A164) -> 0 | X164: =SUMIFS('B0.8.Online'!K:K,'B0.8.Online'!A:A,'B0.SUM (tuần 0)'!$A164) -> 0 | Y164: =SUM(Z164:AF164) -> 0 | AA164: =SUMIFS('B0.3.XK'!L:L,'B0.3.XK'!A:A,'B0.SUM (tuần 0)'!$A164) -> 0 | AC164: =SUMIFS('B0.5.GT2'!L:L,'B0.5.GT2'!A:A,'B0.SUM (tuần 0)'!$A164) -> 0 | AD164: =SUMIFS('B0.4.OEM'!L:L,'B0.4.OEM'!A:A,'B0.SUM (tuần 0)'!$A164) -> 0 | AF164: =SUMIFS('B0.8.Online'!L:L,'B0.8.Online'!A:A,'B0.SUM (tuần 0)'!$A164) -> 0 | AG164: =SUM(AH164:AN164) -> 0 | AI164: =SUMIFS('B0.3.XK'!M:M,'B0.3.XK'!A:A,'B0.SUM (tuần 0)'!$A164) -> 0 | AK164: =SUMIFS('B0.5.GT2'!M:M,'B0.5.GT2'!A:A,'B0.SUM (tuần 0)'!$A164) -> 0 | AL164: =SUMIFS('B0.4.OEM'!M:M,'B0.4.OEM'!A:A,'B0.SUM (tuần 0)'!$A164) -> 0 | AN164: =SUMIFS('B0.8.Online'!M:M,'B0.8.Online'!A:A,'B0.SUM (tuần 0)'!$A164) -> 0 | AP164: =SUMIFS('B1.SUM (tuần 4)'!$I:$I,'B1.SUM (tuần 4)'!$A:$A,'B0.SUM (tuần 0)'!$A164) -> 0 | AQ164: =I164-AP164 -> 0
A165: 1001110683 | B165: Máy LN RO-106 HI TECH- ĐỎ CQ ngược (7S) | C165: RO-106 | D165: Máy TCM Sx | E165: 10L | F165: XK | H165: 1315492 | I165: =SUM(J165:P165) -> 0 | K165: =SUMIFS('B0.3.XK'!J:J,'B0.3.XK'!A:A,'B0.SUM (tuần 0)'!$A165) -> 0 | M165: =SUMIFS('B0.5.GT2'!K:K,'B0.5.GT2'!A:A,'B0.SUM (tuần 0)'!$A165) -> 0 | N165: =SUMIFS('B0.4.OEM'!J:J,'B0.4.OEM'!A:A,'B0.SUM (tuần 0)'!$A165) -> 0 | P165: =SUMIFS('B0.8.Online'!J:J,'B0.8.Online'!A:A,'B0.SUM (tuần 0)'!$A165) -> 0 | Q165: =SUM(R165:X165) -> 20 | S165: =SUMIFS('B0.3.XK'!K:K,'B0.3.XK'!A:A,'B0.SUM (tuần 0)'!$A165) -> 20 | U165: =SUMIFS('B0.5.GT2'!K:K,'B0.5.GT2'!A:A,'B0.SUM (tuần 0)'!$A165) -> 0 | V165: =SUMIFS('B0.4.OEM'!K:K,'B0.4.OEM'!A:A,'B0.SUM (tuần 0)'!$A165) -> 0 | X165: =SUMIFS('B0.8.Online'!K:K,'B0.8.Online'!A:A,'B0.SUM (tuần 0)'!$A165) -> 0 | Y165: =SUM(Z165:AF165) -> 0 | AA165: =SUMIFS('B0.3.XK'!L:L,'B0.3.XK'!A:A,'B0.SUM (tuần 0)'!$A165) -> 0 | AC165: =SUMIFS('B0.5.GT2'!L:L,'B0.5.GT2'!A:A,'B0.SUM (tuần 0)'!$A165) -> 0 | AD165: =SUMIFS('B0.4.OEM'!L:L,'B0.4.OEM'!A:A,'B0.SUM (tuần 0)'!$A165) -> 0 | AF165: =SUMIFS('B0.8.Online'!L:L,'B0.8.Online'!A:A,'B0.SUM (tuần 0)'!$A165) -> 0 | AG165: =SUM(AH165:AN165) -> 0 | AI165: =SUMIFS('B0.3.XK'!M:M,'B0.3.XK'!A:A,'B0.SUM (tuần 0)'!$A165) -> 0 | AK165: =SUMIFS('B0.5.GT2'!M:M,'B0.5.GT2'!A:A,'B0.SUM (tuần 0)'!$A165) -> 0 | AL165: =SUMIFS('B0.4.OEM'!M:M,'B0.4.OEM'!A:A,'B0.SUM (tuần 0)'!$A165) -> 0 | AN165: =SUMIFS('B0.8.Online'!M:M,'B0.8.Online'!A:A,'B0.SUM (tuần 0)'!$A165) -> 0 | AO165: Model clear, bán hết tồn NVL | AP165: =SUMIFS('B1.SUM (tuần 4)'!$I:$I,'B1.SUM (tuần 4)'!$A:$A,'B0.SUM (tuần 0)'!$A165) -> 0 | AQ165: =I165-AP165 -> 0
A166: 1001110684 | B166: Máy lọc nước RO-104 Saqi (7S) | C166: RO-104 | D166: Máy TCM Sx | E166: 10L | F166: XK | H166: 1256295 | I166: =SUM(J166:P166) -> 0 | K166: =SUMIFS('B0.3.XK'!J:J,'B0.3.XK'!A:A,'B0.SUM (tuần 0)'!$A166) -> 0 | M166: =SUMIFS('B0.5.GT2'!K:K,'B0.5.GT2'!A:A,'B0.SUM (tuần 0)'!$A166) -> 0 | N166: =SUMIFS('B0.4.OEM'!J:J,'B0.4.OEM'!A:A,'B0.SUM (tuần 0)'!$A166) -> 0 | P166: =SUMIFS('B0.8.Online'!J:J,'B0.8.Online'!A:A,'B0.SUM (tuần 0)'!$A166) -> 0 | Q166: =SUM(R166:X166) -> 0 | S166: =SUMIFS('B0.3.XK'!K:K,'B0.3.XK'!A:A,'B0.SUM (tuần 0)'!$A166) -> 0 | U166: =SUMIFS('B0.5.GT2'!K:K,'B0.5.GT2'!A:A,'B0.SUM (tuần 0)'!$A166) -> 0 | V166: =SUMIFS('B0.4.OEM'!K:K,'B0.4.OEM'!A:A,'B0.SUM (tuần 0)'!$A166) -> 0 | X166: =SUMIFS('B0.8.Online'!K:K,'B0.8.Online'!A:A,'B0.SUM (tuần 0)'!$A166) -> 0 | Y166: =SUM(Z166:AF166) -> 0 | AA166: =SUMIFS('B0.3.XK'!L:L,'B0.3.XK'!A:A,'B0.SUM (tuần 0)'!$A166) -> 0 | AC166: =SUMIFS('B0.5.GT2'!L:L,'B0.5.GT2'!A:A,'B0.SUM (tuần 0)'!$A166) -> 0 | AD166: =SUMIFS('B0.4.OEM'!L:L,'B0.4.OEM'!A:A,'B0.SUM (tuần 0)'!$A166) -> 0 | AF166: =SUMIFS('B0.8.Online'!L:L,'B0.8.Online'!A:A,'B0.SUM (tuần 0)'!$A166) -> 0 | AG166: =SUM(AH166:AN166) -> 2400 | AI166: =SUMIFS('B0.3.XK'!M:M,'B0.3.XK'!A:A,'B0.SUM (tuần 0)'!$A166) -> 2400 | AK166: =SUMIFS('B0.5.GT2'!M:M,'B0.5.GT2'!A:A,'B0.SUM (tuần 0)'!$A166) -> 0 | AL166: =SUMIFS('B0.4.OEM'!M:M,'B0.4.OEM'!A:A,'B0.SUM (tuần 0)'!$A166) -> 0 | AN166: =SUMIFS('B0.8.Online'!M:M,'B0.8.Online'!A:A,'B0.SUM (tuần 0)'!$A166) -> 0 | AP166: =SUMIFS('B1.SUM (tuần 4)'!$I:$I,'B1.SUM (tuần 4)'!$A:$A,'B0.SUM (tuần 0)'!$A166) -> 0 | AQ166: =I166-AP166 -> 0
A167: 1001110685 | B167: Máy Hydro-ion Kiềm KRF AQUA NOBLE (S86) | C167: KAE-S86 | D167: Máy TCM Sx | E167: Block | F167: XK | H167: 9629400 | I167: =SUM(J167:P167) -> 0 | K167: =SUMIFS('B0.3.XK'!J:J,'B0.3.XK'!A:A,'B0.SUM (tuần 0)'!$A167) -> 0 | M167: =SUMIFS('B0.5.GT2'!K:K,'B0.5.GT2'!A:A,'B0.SUM (tuần 0)'!$A167) -> 0 | N167: =SUMIFS('B0.4.OEM'!J:J,'B0.4.OEM'!A:A,'B0.SUM (tuần 0)'!$A167) -> 0 | P167: =SUMIFS('B0.8.Online'!J:J,'B0.8.Online'!A:A,'B0.SUM (tuần 0)'!$A167) -> 0 | Q167: =SUM(R167:X167) -> 0 | S167: =SUMIFS('B0.3.XK'!K:K,'B0.3.XK'!A:A,'B0.SUM (tuần 0)'!$A167) -> 0 | U167: =SUMIFS('B0.5.GT2'!K:K,'B0.5.GT2'!A:A,'B0.SUM (tuần 0)'!$A167) -> 0 | V167: =SUMIFS('B0.4.OEM'!K:K,'B0.4.OEM'!A:A,'B0.SUM (tuần 0)'!$A167) -> 0 | X167: =SUMIFS('B0.8.Online'!K:K,'B0.8.Online'!A:A,'B0.SUM (tuần 0)'!$A167) -> 0 | Y167: =SUM(Z167:AF167) -> 0 | AA167: =SUMIFS('B0.3.XK'!L:L,'B0.3.XK'!A:A,'B0.SUM (tuần 0)'!$A167) -> 0 | AC167: =SUMIFS('B0.5.GT2'!L:L,'B0.5.GT2'!A:A,'B0.SUM (tuần 0)'!$A167) -> 0 | AD167: =SUMIFS('B0.4.OEM'!L:L,'B0.4.OEM'!A:A,'B0.SUM (tuần 0)'!$A167) -> 0 | AF167: =SUMIFS('B0.8.Online'!L:L,'B0.8.Online'!A:A,'B0.SUM (tuần 0)'!$A167) -> 0 | AG167: =SUM(AH167:AN167) -> 0 | AI167: =SUMIFS('B0.3.XK'!M:M,'B0.3.XK'!A:A,'B0.SUM (tuần 0)'!$A167) -> 0 | AK167: =SUMIFS('B0.5.GT2'!M:M,'B0.5.GT2'!A:A,'B0.SUM (tuần 0)'!$A167) -> 0 | AL167: =SUMIFS('B0.4.OEM'!M:M,'B0.4.OEM'!A:A,'B0.SUM (tuần 0)'!$A167) -> 0 | AN167: =SUMIFS('B0.8.Online'!M:M,'B0.8.Online'!A:A,'B0.SUM (tuần 0)'!$A167) -> 0 | AP167: =SUMIFS('B1.SUM (tuần 4)'!$I:$I,'B1.SUM (tuần 4)'!$A:$A,'B0.SUM (tuần 0)'!$A167) -> 0 | AQ167: =I167-AP167 -> 0
A168: 1001110686 | B168: Lọc tổng AMAN PALACE (KTF-P02 AIO/KSA) | C168: KTF-P02 | D168: Máy TCM Sx | E168: LK khác | F168: XK | H168: 14207311 | I168: =SUM(J168:P168) -> 0 | K168: =SUMIFS('B0.3.XK'!J:J,'B0.3.XK'!A:A,'B0.SUM (tuần 0)'!$A168) -> 0 | M168: =SUMIFS('B0.5.GT2'!K:K,'B0.5.GT2'!A:A,'B0.SUM (tuần 0)'!$A168) -> 0 | N168: =SUMIFS('B0.4.OEM'!J:J,'B0.4.OEM'!A:A,'B0.SUM (tuần 0)'!$A168) -> 0 | P168: =SUMIFS('B0.8.Online'!J:J,'B0.8.Online'!A:A,'B0.SUM (tuần 0)'!$A168) -> 0 | Q168: =SUM(R168:X168) -> 0 | S168: =SUMIFS('B0.3.XK'!K:K,'B0.3.XK'!A:A,'B0.SUM (tuần 0)'!$A168) -> 0 | U168: =SUMIFS('B0.5.GT2'!K:K,'B0.5.GT2'!A:A,'B0.SUM (tuần 0)'!$A168) -> 0 | V168: =SUMIFS('B0.4.OEM'!K:K,'B0.4.OEM'!A:A,'B0.SUM (tuần 0)'!$A168) -> 0 | X168: =SUMIFS('B0.8.Online'!K:K,'B0.8.Online'!A:A,'B0.SUM (tuần 0)'!$A168) -> 0 | Y168: =SUM(Z168:AF168) -> 0 | AA168: =SUMIFS('B0.3.XK'!L:L,'B0.3.XK'!A:A,'B0.SUM (tuần 0)'!$A168) -> 0 | AC168: =SUMIFS('B0.5.GT2'!L:L,'B0.5.GT2'!A:A,'B0.SUM (tuần 0)'!$A168) -> 0 | AD168: =SUMIFS('B0.4.OEM'!L:L,'B0.4.OEM'!A:A,'B0.SUM (tuần 0)'!$A168) -> 0 | AF168: =SUMIFS('B0.8.Online'!L:L,'B0.8.Online'!A:A,'B0.SUM (tuần 0)'!$A168) -> 0 | AG168: =SUM(AH168:AN168) -> 0 | AI168: =SUMIFS('B0.3.XK'!M:M,'B0.3.XK'!A:A,'B0.SUM (tuần 0)'!$A168) -> 0 | AK168: =SUMIFS('B0.5.GT2'!M:M,'B0.5.GT2'!A:A,'B0.SUM (tuần 0)'!$A168) -> 0 | AL168: =SUMIFS('B0.4.OEM'!M:M,'B0.4.OEM'!A:A,'B0.SUM (tuần 0)'!$A168) -> 0 | AN168: =SUMIFS('B0.8.Online'!M:M,'B0.8.Online'!A:A,'B0.SUM (tuần 0)'!$A168) -> 0 | AP168: =SUMIFS('B1.SUM (tuần 4)'!$I:$I,'B1.SUM (tuần 4)'!$A:$A,'B0.SUM (tuần 0)'!$A168) -> 0 | AQ168: =I168-AP168 -> 0
A169: 1001110687 | B169: Máy RO-104 TECOMEN CQ ngược(Anh) | C169: RO-104 | D169: Máy TCM Sx | E169: 10L | F169: XK | H169: 1315492 | I169: =SUM(J169:P169) -> 0 | K169: =SUMIFS('B0.3.XK'!J:J,'B0.3.XK'!A:A,'B0.SUM (tuần 0)'!$A169) -> 0 | M169: =SUMIFS('B0.5.GT2'!K:K,'B0.5.GT2'!A:A,'B0.SUM (tuần 0)'!$A169) -> 0 | N169: =SUMIFS('B0.4.OEM'!J:J,'B0.4.OEM'!A:A,'B0.SUM (tuần 0)'!$A169) -> 0 | P169: =SUMIFS('B0.8.Online'!J:J,'B0.8.Online'!A:A,'B0.SUM (tuần 0)'!$A169) -> 0 | Q169: =SUM(R169:X169) -> 20 | S169: =SUMIFS('B0.3.XK'!K:K,'B0.3.XK'!A:A,'B0.SUM (tuần 0)'!$A169) -> 20 | U169: =SUMIFS('B0.5.GT2'!K:K,'B0.5.GT2'!A:A,'B0.SUM (tuần 0)'!$A169) -> 0 | V169: =SUMIFS('B0.4.OEM'!K:K,'B0.4.OEM'!A:A,'B0.SUM (tuần 0)'!$A169) -> 0 | X169: =SUMIFS('B0.8.Online'!K:K,'B0.8.Online'!A:A,'B0.SUM (tuần 0)'!$A169) -> 0 | Y169: =SUM(Z169:AF169) -> 0 | AA169: =SUMIFS('B0.3.XK'!L:L,'B0.3.XK'!A:A,'B0.SUM (tuần 0)'!$A169) -> 0 | AC169: =SUMIFS('B0.5.GT2'!L:L,'B0.5.GT2'!A:A,'B0.SUM (tuần 0)'!$A169) -> 0 | AD169: =SUMIFS('B0.4.OEM'!L:L,'B0.4.OEM'!A:A,'B0.SUM (tuần 0)'!$A169) -> 0 | AF169: =SUMIFS('B0.8.Online'!L:L,'B0.8.Online'!A:A,'B0.SUM (tuần 0)'!$A169) -> 0 | AG169: =SUM(AH169:AN169) -> 0 | AI169: =SUMIFS('B0.3.XK'!M:M,'B0.3.XK'!A:A,'B0.SUM (tuần 0)'!$A169) -> 0 | AK169: =SUMIFS('B0.5.GT2'!M:M,'B0.5.GT2'!A:A,'B0.SUM (tuần 0)'!$A169) -> 0 | AL169: =SUMIFS('B0.4.OEM'!M:M,'B0.4.OEM'!A:A,'B0.SUM (tuần 0)'!$A169) -> 0 | AN169: =SUMIFS('B0.8.Online'!M:M,'B0.8.Online'!A:A,'B0.SUM (tuần 0)'!$A169) -> 0 | AP169: =SUMIFS('B1.SUM (tuần 4)'!$I:$I,'B1.SUM (tuần 4)'!$A:$A,'B0.SUM (tuần 0)'!$A169) -> 0 | AQ169: =I169-AP169 -> 0
A170: 1001110694 | B170: Máy lọc nước RO-30 Pure Water (7S) | C170: RO-30 | D170: Máy TCM Sx | E170: 10L | F170: XK | H170: 1394421 | I170: =SUM(J170:P170) -> 0 | K170: =SUMIFS('B0.3.XK'!J:J,'B0.3.XK'!A:A,'B0.SUM (tuần 0)'!$A170) -> 0 | M170: =SUMIFS('B0.5.GT2'!K:K,'B0.5.GT2'!A:A,'B0.SUM (tuần 0)'!$A170) -> 0 | N170: =SUMIFS('B0.4.OEM'!J:J,'B0.4.OEM'!A:A,'B0.SUM (tuần 0)'!$A170) -> 0 | P170: =SUMIFS('B0.8.Online'!J:J,'B0.8.Online'!A:A,'B0.SUM (tuần 0)'!$A170) -> 0 | Q170: =SUM(R170:X170) -> 0 | S170: =SUMIFS('B0.3.XK'!K:K,'B0.3.XK'!A:A,'B0.SUM (tuần 0)'!$A170) -> 0 | U170: =SUMIFS('B0.5.GT2'!K:K,'B0.5.GT2'!A:A,'B0.SUM (tuần 0)'!$A170) -> 0 | V170: =SUMIFS('B0.4.OEM'!K:K,'B0.4.OEM'!A:A,'B0.SUM (tuần 0)'!$A170) -> 0 | X170: =SUMIFS('B0.8.Online'!K:K,'B0.8.Online'!A:A,'B0.SUM (tuần 0)'!$A170) -> 0 | Y170: =SUM(Z170:AF170) -> 0 | AA170: =SUMIFS('B0.3.XK'!L:L,'B0.3.XK'!A:A,'B0.SUM (tuần 0)'!$A170) -> 0 | AC170: =SUMIFS('B0.5.GT2'!L:L,'B0.5.GT2'!A:A,'B0.SUM (tuần 0)'!$A170) -> 0 | AD170: =SUMIFS('B0.4.OEM'!L:L,'B0.4.OEM'!A:A,'B0.SUM (tuần 0)'!$A170) -> 0 | AF170: =SUMIFS('B0.8.Online'!L:L,'B0.8.Online'!A:A,'B0.SUM (tuần 0)'!$A170) -> 0 | AG170: =SUM(AH170:AN170) -> 0 | AI170: =SUMIFS('B0.3.XK'!M:M,'B0.3.XK'!A:A,'B0.SUM (tuần 0)'!$A170) -> 0 | AK170: =SUMIFS('B0.5.GT2'!M:M,'B0.5.GT2'!A:A,'B0.SUM (tuần 0)'!$A170) -> 0 | AL170: =SUMIFS('B0.4.OEM'!M:M,'B0.4.OEM'!A:A,'B0.SUM (tuần 0)'!$A170) -> 0 | AN170: =SUMIFS('B0.8.Online'!M:M,'B0.8.Online'!A:A,'B0.SUM (tuần 0)'!$A170) -> 0 | AP170: =SUMIFS('B1.SUM (tuần 4)'!$I:$I,'B1.SUM (tuần 4)'!$A:$A,'B0.SUM (tuần 0)'!$A170) -> 0 | AQ170: =I170-AP170 -> 0
A171: 1001110695 | B171: Máy lọc nước UNDERSINK đen NEWLAND (6S) | C171: S-S027 | D171: Máy TCM Sx | E171: 10L | F171: XK | H171: 2063480 | I171: =SUM(J171:P171) -> 0 | K171: =SUMIFS('B0.3.XK'!J:J,'B0.3.XK'!A:A,'B0.SUM (tuần 0)'!$A171) -> 0 | M171: =SUMIFS('B0.5.GT2'!K:K,'B0.5.GT2'!A:A,'B0.SUM (tuần 0)'!$A171) -> 0 | N171: =SUMIFS('B0.4.OEM'!J:J,'B0.4.OEM'!A:A,'B0.SUM (tuần 0)'!$A171) -> 0 | P171: =SUMIFS('B0.8.Online'!J:J,'B0.8.Online'!A:A,'B0.SUM (tuần 0)'!$A171) -> 0 | Q171: =SUM(R171:X171) -> 0 | S171: =SUMIFS('B0.3.XK'!K:K,'B0.3.XK'!A:A,'B0.SUM (tuần 0)'!$A171) -> 0 | U171: =SUMIFS('B0.5.GT2'!K:K,'B0.5.GT2'!A:A,'B0.SUM (tuần 0)'!$A171) -> 0 | V171: =SUMIFS('B0.4.OEM'!K:K,'B0.4.OEM'!A:A,'B0.SUM (tuần 0)'!$A171) -> 0 | X171: =SUMIFS('B0.8.Online'!K:K,'B0.8.Online'!A:A,'B0.SUM (tuần 0)'!$A171) -> 0 | Y171: =SUM(Z171:AF171) -> 0 | AA171: =SUMIFS('B0.3.XK'!L:L,'B0.3.XK'!A:A,'B0.SUM (tuần 0)'!$A171) -> 0 | AC171: =SUMIFS('B0.5.GT2'!L:L,'B0.5.GT2'!A:A,'B0.SUM (tuần 0)'!$A171) -> 0 | AD171: =SUMIFS('B0.4.OEM'!L:L,'B0.4.OEM'!A:A,'B0.SUM (tuần 0)'!$A171) -> 0 | AF171: =SUMIFS('B0.8.Online'!L:L,'B0.8.Online'!A:A,'B0.SUM (tuần 0)'!$A171) -> 0 | AG171: =SUM(AH171:AN171) -> 0 | AI171: =SUMIFS('B0.3.XK'!M:M,'B0.3.XK'!A:A,'B0.SUM (tuần 0)'!$A171) -> 0 | AK171: =SUMIFS('B0.5.GT2'!M:M,'B0.5.GT2'!A:A,'B0.SUM (tuần 0)'!$A171) -> 0 | AL171: =SUMIFS('B0.4.OEM'!M:M,'B0.4.OEM'!A:A,'B0.SUM (tuần 0)'!$A171) -> 0 | AN171: =SUMIFS('B0.8.Online'!M:M,'B0.8.Online'!A:A,'B0.SUM (tuần 0)'!$A171) -> 0 | AP171: =SUMIFS('B1.SUM (tuần 4)'!$I:$I,'B1.SUM (tuần 4)'!$A:$A,'B0.SUM (tuần 0)'!$A171) -> 0 | AQ171: =I171-AP171 -> 0
A172: 1001110696 | B172: Máy BCN-400 GPD NEWLAND | C172: BCN-400 | D172: Máy TCM Sx | E172: BCN | F172: XK | H172: 5656615 | I172: =SUM(J172:P172) -> 0 | K172: =SUMIFS('B0.3.XK'!J:J,'B0.3.XK'!A:A,'B0.SUM (tuần 0)'!$A172) -> 0 | M172: =SUMIFS('B0.5.GT2'!K:K,'B0.5.GT2'!A:A,'B0.SUM (tuần 0)'!$A172) -> 0 | N172: =SUMIFS('B0.4.OEM'!J:J,'B0.4.OEM'!A:A,'B0.SUM (tuần 0)'!$A172) -> 0 | P172: =SUMIFS('B0.8.Online'!J:J,'B0.8.Online'!A:A,'B0.SUM (tuần 0)'!$A172) -> 0 | Q172: =SUM(R172:X172) -> 0 | S172: =SUMIFS('B0.3.XK'!K:K,'B0.3.XK'!A:A,'B0.SUM (tuần 0)'!$A172) -> 0 | U172: =SUMIFS('B0.5.GT2'!K:K,'B0.5.GT2'!A:A,'B0.SUM (tuần 0)'!$A172) -> 0 | V172: =SUMIFS('B0.4.OEM'!K:K,'B0.4.OEM'!A:A,'B0.SUM (tuần 0)'!$A172) -> 0 | X172: =SUMIFS('B0.8.Online'!K:K,'B0.8.Online'!A:A,'B0.SUM (tuần 0)'!$A172) -> 0 | Y172: =SUM(Z172:AF172) -> 0 | AA172: =SUMIFS('B0.3.XK'!L:L,'B0.3.XK'!A:A,'B0.SUM (tuần 0)'!$A172) -> 0 | AC172: =SUMIFS('B0.5.GT2'!L:L,'B0.5.GT2'!A:A,'B0.SUM (tuần 0)'!$A172) -> 0 | AD172: =SUMIFS('B0.4.OEM'!L:L,'B0.4.OEM'!A:A,'B0.SUM (tuần 0)'!$A172) -> 0 | AF172: =SUMIFS('B0.8.Online'!L:L,'B0.8.Online'!A:A,'B0.SUM (tuần 0)'!$A172) -> 0 | AG172: =SUM(AH172:AN172) -> 0 | AI172: =SUMIFS('B0.3.XK'!M:M,'B0.3.XK'!A:A,'B0.SUM (tuần 0)'!$A172) -> 0 | AK172: =SUMIFS('B0.5.GT2'!M:M,'B0.5.GT2'!A:A,'B0.SUM (tuần 0)'!$A172) -> 0 | AL172: =SUMIFS('B0.4.OEM'!M:M,'B0.4.OEM'!A:A,'B0.SUM (tuần 0)'!$A172) -> 0 | AN172: =SUMIFS('B0.8.Online'!M:M,'B0.8.Online'!A:A,'B0.SUM (tuần 0)'!$A172) -> 0 | AP172: =SUMIFS('B1.SUM (tuần 4)'!$I:$I,'B1.SUM (tuần 4)'!$A:$A,'B0.SUM (tuần 0)'!$A172) -> 0 | AQ172: =I172-AP172 -> 0
A173: 1001110697 | B173: Máy lọc nước RO-30 Lalanka (5S) | C173: RO-30 | D173: Máy TCM Sx | E173: 10L | F173: XK | H173: 1499661 | I173: =SUM(J173:P173) -> 0 | K173: =SUMIFS('B0.3.XK'!J:J,'B0.3.XK'!A:A,'B0.SUM (tuần 0)'!$A173) -> 0 | M173: =SUMIFS('B0.5.GT2'!K:K,'B0.5.GT2'!A:A,'B0.SUM (tuần 0)'!$A173) -> 0 | N173: =SUMIFS('B0.4.OEM'!J:J,'B0.4.OEM'!A:A,'B0.SUM (tuần 0)'!$A173) -> 0 | P173: =SUMIFS('B0.8.Online'!J:J,'B0.8.Online'!A:A,'B0.SUM (tuần 0)'!$A173) -> 0 | Q173: =SUM(R173:X173) -> 0 | S173: =SUMIFS('B0.3.XK'!K:K,'B0.3.XK'!A:A,'B0.SUM (tuần 0)'!$A173) -> 0 | U173: =SUMIFS('B0.5.GT2'!K:K,'B0.5.GT2'!A:A,'B0.SUM (tuần 0)'!$A173) -> 0 | V173: =SUMIFS('B0.4.OEM'!K:K,'B0.4.OEM'!A:A,'B0.SUM (tuần 0)'!$A173) -> 0 | X173: =SUMIFS('B0.8.Online'!K:K,'B0.8.Online'!A:A,'B0.SUM (tuần 0)'!$A173) -> 0 | Y173: =SUM(Z173:AF173) -> 0 | AA173: =SUMIFS('B0.3.XK'!L:L,'B0.3.XK'!A:A,'B0.SUM (tuần 0)'!$A173) -> 0 | AC173: =SUMIFS('B0.5.GT2'!L:L,'B0.5.GT2'!A:A,'B0.SUM (tuần 0)'!$A173) -> 0 | AD173: =SUMIFS('B0.4.OEM'!L:L,'B0.4.OEM'!A:A,'B0.SUM (tuần 0)'!$A173) -> 0 | AF173: =SUMIFS('B0.8.Online'!L:L,'B0.8.Online'!A:A,'B0.SUM (tuần 0)'!$A173) -> 0 | AG173: =SUM(AH173:AN173) -> 0 | AI173: =SUMIFS('B0.3.XK'!M:M,'B0.3.XK'!A:A,'B0.SUM (tuần 0)'!$A173) -> 0 | AK173: =SUMIFS('B0.5.GT2'!M:M,'B0.5.GT2'!A:A,'B0.SUM (tuần 0)'!$A173) -> 0 | AL173: =SUMIFS('B0.4.OEM'!M:M,'B0.4.OEM'!A:A,'B0.SUM (tuần 0)'!$A173) -> 0 | AN173: =SUMIFS('B0.8.Online'!M:M,'B0.8.Online'!A:A,'B0.SUM (tuần 0)'!$A173) -> 0 | AP173: =SUMIFS('B1.SUM (tuần 4)'!$I:$I,'B1.SUM (tuần 4)'!$A:$A,'B0.SUM (tuần 0)'!$A173) -> 0 | AQ173: =I173-AP173 -> 0
A174: 1001110698 | B174: Máy LN U05 Pro LIYAV | C174: KAQ-U05 Pro | D174: Máy TCM Sx | E174: 10L | F174: XK | H174: 2104787 | I174: =SUM(J174:P174) -> 0 | K174: =SUMIFS('B0.3.XK'!J:J,'B0.3.XK'!A:A,'B0.SUM (tuần 0)'!$A174) -> 0 | M174: =SUMIFS('B0.5.GT2'!K:K,'B0.5.GT2'!A:A,'B0.SUM (tuần 0)'!$A174) -> 0 | N174: =SUMIFS('B0.4.OEM'!J:J,'B0.4.OEM'!A:A,'B0.SUM (tuần 0)'!$A174) -> 0 | P174: =SUMIFS('B0.8.Online'!J:J,'B0.8.Online'!A:A,'B0.SUM (tuần 0)'!$A174) -> 0 | Q174: =SUM(R174:X174) -> 0 | S174: =SUMIFS('B0.3.XK'!K:K,'B0.3.XK'!A:A,'B0.SUM (tuần 0)'!$A174) -> 0 | U174: =SUMIFS('B0.5.GT2'!K:K,'B0.5.GT2'!A:A,'B0.SUM (tuần 0)'!$A174) -> 0 | V174: =SUMIFS('B0.4.OEM'!K:K,'B0.4.OEM'!A:A,'B0.SUM (tuần 0)'!$A174) -> 0 | X174: =SUMIFS('B0.8.Online'!K:K,'B0.8.Online'!A:A,'B0.SUM (tuần 0)'!$A174) -> 0 | Y174: =SUM(Z174:AF174) -> 0 | AA174: =SUMIFS('B0.3.XK'!L:L,'B0.3.XK'!A:A,'B0.SUM (tuần 0)'!$A174) -> 0 | AC174: =SUMIFS('B0.5.GT2'!L:L,'B0.5.GT2'!A:A,'B0.SUM (tuần 0)'!$A174) -> 0 | AD174: =SUMIFS('B0.4.OEM'!L:L,'B0.4.OEM'!A:A,'B0.SUM (tuần 0)'!$A174) -> 0 | AF174: =SUMIFS('B0.8.Online'!L:L,'B0.8.Online'!A:A,'B0.SUM (tuần 0)'!$A174) -> 0 | AG174: =SUM(AH174:AN174) -> 0 | AI174: =SUMIFS('B0.3.XK'!M:M,'B0.3.XK'!A:A,'B0.SUM (tuần 0)'!$A174) -> 0 | AK174: =SUMIFS('B0.5.GT2'!M:M,'B0.5.GT2'!A:A,'B0.SUM (tuần 0)'!$A174) -> 0 | AL174: =SUMIFS('B0.4.OEM'!M:M,'B0.4.OEM'!A:A,'B0.SUM (tuần 0)'!$A174) -> 0 | AN174: =SUMIFS('B0.8.Online'!M:M,'B0.8.Online'!A:A,'B0.SUM (tuần 0)'!$A174) -> 0 | AP174: =SUMIFS('B1.SUM (tuần 4)'!$I:$I,'B1.SUM (tuần 4)'!$A:$A,'B0.SUM (tuần 0)'!$A174) -> 0 | AQ174: =I174-AP174 -> 0
A175: 1001110699 | B175: Lọc tổng AQUASHIELD P20 (P02 AIO PHI) | C175: KTF-P02 | D175: Máy TCM Sx | E175: LK khác | F175: XK | H175: 13407492 | I175: =SUM(J175:P175) -> 0 | K175: =SUMIFS('B0.3.XK'!J:J,'B0.3.XK'!A:A,'B0.SUM (tuần 0)'!$A175) -> 0 | M175: =SUMIFS('B0.5.GT2'!K:K,'B0.5.GT2'!A:A,'B0.SUM (tuần 0)'!$A175) -> 0 | N175: =SUMIFS('B0.4.OEM'!J:J,'B0.4.OEM'!A:A,'B0.SUM (tuần 0)'!$A175) -> 0 | P175: =SUMIFS('B0.8.Online'!J:J,'B0.8.Online'!A:A,'B0.SUM (tuần 0)'!$A175) -> 0 | Q175: =SUM(R175:X175) -> 10 | S175: =SUMIFS('B0.3.XK'!K:K,'B0.3.XK'!A:A,'B0.SUM (tuần 0)'!$A175) -> 10 | U175: =SUMIFS('B0.5.GT2'!K:K,'B0.5.GT2'!A:A,'B0.SUM (tuần 0)'!$A175) -> 0 | V175: =SUMIFS('B0.4.OEM'!K:K,'B0.4.OEM'!A:A,'B0.SUM (tuần 0)'!$A175) -> 0 | X175: =SUMIFS('B0.8.Online'!K:K,'B0.8.Online'!A:A,'B0.SUM (tuần 0)'!$A175) -> 0 | Y175: =SUM(Z175:AF175) -> 0 | AA175: =SUMIFS('B0.3.XK'!L:L,'B0.3.XK'!A:A,'B0.SUM (tuần 0)'!$A175) -> 0 | AC175: =SUMIFS('B0.5.GT2'!L:L,'B0.5.GT2'!A:A,'B0.SUM (tuần 0)'!$A175) -> 0 | AD175: =SUMIFS('B0.4.OEM'!L:L,'B0.4.OEM'!A:A,'B0.SUM (tuần 0)'!$A175) -> 0 | AF175: =SUMIFS('B0.8.Online'!L:L,'B0.8.Online'!A:A,'B0.SUM (tuần 0)'!$A175) -> 0 | AG175: =SUM(AH175:AN175) -> 0 | AI175: =SUMIFS('B0.3.XK'!M:M,'B0.3.XK'!A:A,'B0.SUM (tuần 0)'!$A175) -> 0 | AK175: =SUMIFS('B0.5.GT2'!M:M,'B0.5.GT2'!A:A,'B0.SUM (tuần 0)'!$A175) -> 0 | AL175: =SUMIFS('B0.4.OEM'!M:M,'B0.4.OEM'!A:A,'B0.SUM (tuần 0)'!$A175) -> 0 | AN175: =SUMIFS('B0.8.Online'!M:M,'B0.8.Online'!A:A,'B0.SUM (tuần 0)'!$A175) -> 0 | AP175: =SUMIFS('B1.SUM (tuần 4)'!$I:$I,'B1.SUM (tuần 4)'!$A:$A,'B0.SUM (tuần 0)'!$A175) -> 0 | AQ175: =I175-AP175 -> 0
A176: 1001110700 | B176: Máy PLATINUM LUMIFLOW S6 (S66 Trắng) | C176: Platinum S6 | D176: Máy TCM Sx | E176: Block | F176: XK | H176: 6123351 | I176: =SUM(J176:P176) -> 0 | K176: =SUMIFS('B0.3.XK'!J:J,'B0.3.XK'!A:A,'B0.SUM (tuần 0)'!$A176) -> 0 | M176: =SUMIFS('B0.5.GT2'!K:K,'B0.5.GT2'!A:A,'B0.SUM (tuần 0)'!$A176) -> 0 | N176: =SUMIFS('B0.4.OEM'!J:J,'B0.4.OEM'!A:A,'B0.SUM (tuần 0)'!$A176) -> 0 | P176: =SUMIFS('B0.8.Online'!J:J,'B0.8.Online'!A:A,'B0.SUM (tuần 0)'!$A176) -> 0 | Q176: =SUM(R176:X176) -> 0 | S176: =SUMIFS('B0.3.XK'!K:K,'B0.3.XK'!A:A,'B0.SUM (tuần 0)'!$A176) -> 0 | U176: =SUMIFS('B0.5.GT2'!K:K,'B0.5.GT2'!A:A,'B0.SUM (tuần 0)'!$A176) -> 0 | V176: =SUMIFS('B0.4.OEM'!K:K,'B0.4.OEM'!A:A,'B0.SUM (tuần 0)'!$A176) -> 0 | X176: =SUMIFS('B0.8.Online'!K:K,'B0.8.Online'!A:A,'B0.SUM (tuần 0)'!$A176) -> 0 | Y176: =SUM(Z176:AF176) -> 0 | AA176: =SUMIFS('B0.3.XK'!L:L,'B0.3.XK'!A:A,'B0.SUM (tuần 0)'!$A176) -> 0 | AC176: =SUMIFS('B0.5.GT2'!L:L,'B0.5.GT2'!A:A,'B0.SUM (tuần 0)'!$A176) -> 0 | AD176: =SUMIFS('B0.4.OEM'!L:L,'B0.4.OEM'!A:A,'B0.SUM (tuần 0)'!$A176) -> 0 | AF176: =SUMIFS('B0.8.Online'!L:L,'B0.8.Online'!A:A,'B0.SUM (tuần 0)'!$A176) -> 0 | AG176: =SUM(AH176:AN176) -> 0 | AI176: =SUMIFS('B0.3.XK'!M:M,'B0.3.XK'!A:A,'B0.SUM (tuần 0)'!$A176) -> 0 | AK176: =SUMIFS('B0.5.GT2'!M:M,'B0.5.GT2'!A:A,'B0.SUM (tuần 0)'!$A176) -> 0 | AL176: =SUMIFS('B0.4.OEM'!M:M,'B0.4.OEM'!A:A,'B0.SUM (tuần 0)'!$A176) -> 0 | AN176: =SUMIFS('B0.8.Online'!M:M,'B0.8.Online'!A:A,'B0.SUM (tuần 0)'!$A176) -> 0 | AP176: =SUMIFS('B1.SUM (tuần 4)'!$I:$I,'B1.SUM (tuần 4)'!$A:$A,'B0.SUM (tuần 0)'!$A176) -> 0 | AQ176: =I176-AP176 -> 0
A177: 1001110701 | B177: Máy LN RO-104 TNT USA (7S) | C177: RO-104 | D177: Máy TCM Sx | E177: 10L | F177: XK | H177: 1960083 | I177: =SUM(J177:P177) -> 0 | K177: =SUMIFS('B0.3.XK'!J:J,'B0.3.XK'!A:A,'B0.SUM (tuần 0)'!$A177) -> 0 | M177: =SUMIFS('B0.5.GT2'!K:K,'B0.5.GT2'!A:A,'B0.SUM (tuần 0)'!$A177) -> 0 | N177: =SUMIFS('B0.4.OEM'!J:J,'B0.4.OEM'!A:A,'B0.SUM (tuần 0)'!$A177) -> 0 | P177: =SUMIFS('B0.8.Online'!J:J,'B0.8.Online'!A:A,'B0.SUM (tuần 0)'!$A177) -> 0 | Q177: =SUM(R177:X177) -> 0 | S177: =SUMIFS('B0.3.XK'!K:K,'B0.3.XK'!A:A,'B0.SUM (tuần 0)'!$A177) -> 0 | U177: =SUMIFS('B0.5.GT2'!K:K,'B0.5.GT2'!A:A,'B0.SUM (tuần 0)'!$A177) -> 0 | V177: =SUMIFS('B0.4.OEM'!K:K,'B0.4.OEM'!A:A,'B0.SUM (tuần 0)'!$A177) -> 0 | X177: =SUMIFS('B0.8.Online'!K:K,'B0.8.Online'!A:A,'B0.SUM (tuần 0)'!$A177) -> 0 | Y177: =SUM(Z177:AF177) -> 0 | AA177: =SUMIFS('B0.3.XK'!L:L,'B0.3.XK'!A:A,'B0.SUM (tuần 0)'!$A177) -> 0 | AC177: =SUMIFS('B0.5.GT2'!L:L,'B0.5.GT2'!A:A,'B0.SUM (tuần 0)'!$A177) -> 0 | AD177: =SUMIFS('B0.4.OEM'!L:L,'B0.4.OEM'!A:A,'B0.SUM (tuần 0)'!$A177) -> 0 | AF177: =SUMIFS('B0.8.Online'!L:L,'B0.8.Online'!A:A,'B0.SUM (tuần 0)'!$A177) -> 0 | AG177: =SUM(AH177:AN177) -> 0 | AI177: =SUMIFS('B0.3.XK'!M:M,'B0.3.XK'!A:A,'B0.SUM (tuần 0)'!$A177) -> 0 | AK177: =SUMIFS('B0.5.GT2'!M:M,'B0.5.GT2'!A:A,'B0.SUM (tuần 0)'!$A177) -> 0 | AL177: =SUMIFS('B0.4.OEM'!M:M,'B0.4.OEM'!A:A,'B0.SUM (tuần 0)'!$A177) -> 0 | AN177: =SUMIFS('B0.8.Online'!M:M,'B0.8.Online'!A:A,'B0.SUM (tuần 0)'!$A177) -> 0 | AP177: =SUMIFS('B1.SUM (tuần 4)'!$I:$I,'B1.SUM (tuần 4)'!$A:$A,'B0.SUM (tuần 0)'!$A177) -> 0 | AQ177: =I177-AP177 -> 0
A178: 1001110702 | B178: Máy LN KAQ-U95 Pro KRF (TNT USA) | C178: KAQ-U95 Pro | D178: Máy TCM Sx | E178: 10L | F178: XK | H178: 2078477 | I178: =SUM(J178:P178) -> 0 | K178: =SUMIFS('B0.3.XK'!J:J,'B0.3.XK'!A:A,'B0.SUM (tuần 0)'!$A178) -> 0 | M178: =SUMIFS('B0.5.GT2'!K:K,'B0.5.GT2'!A:A,'B0.SUM (tuần 0)'!$A178) -> 0 | N178: =SUMIFS('B0.4.OEM'!J:J,'B0.4.OEM'!A:A,'B0.SUM (tuần 0)'!$A178) -> 0 | P178: =SUMIFS('B0.8.Online'!J:J,'B0.8.Online'!A:A,'B0.SUM (tuần 0)'!$A178) -> 0 | Q178: =SUM(R178:X178) -> 0 | S178: =SUMIFS('B0.3.XK'!K:K,'B0.3.XK'!A:A,'B0.SUM (tuần 0)'!$A178) -> 0 | U178: =SUMIFS('B0.5.GT2'!K:K,'B0.5.GT2'!A:A,'B0.SUM (tuần 0)'!$A178) -> 0 | V178: =SUMIFS('B0.4.OEM'!K:K,'B0.4.OEM'!A:A,'B0.SUM (tuần 0)'!$A178) -> 0 | X178: =SUMIFS('B0.8.Online'!K:K,'B0.8.Online'!A:A,'B0.SUM (tuần 0)'!$A178) -> 0 | Y178: =SUM(Z178:AF178) -> 0 | AA178: =SUMIFS('B0.3.XK'!L:L,'B0.3.XK'!A:A,'B0.SUM (tuần 0)'!$A178) -> 0 | AC178: =SUMIFS('B0.5.GT2'!L:L,'B0.5.GT2'!A:A,'B0.SUM (tuần 0)'!$A178) -> 0 | AD178: =SUMIFS('B0.4.OEM'!L:L,'B0.4.OEM'!A:A,'B0.SUM (tuần 0)'!$A178) -> 0 | AF178: =SUMIFS('B0.8.Online'!L:L,'B0.8.Online'!A:A,'B0.SUM (tuần 0)'!$A178) -> 0 | AG178: =SUM(AH178:AN178) -> 0 | AI178: =SUMIFS('B0.3.XK'!M:M,'B0.3.XK'!A:A,'B0.SUM (tuần 0)'!$A178) -> 0 | AK178: =SUMIFS('B0.5.GT2'!M:M,'B0.5.GT2'!A:A,'B0.SUM (tuần 0)'!$A178) -> 0 | AL178: =SUMIFS('B0.4.OEM'!M:M,'B0.4.OEM'!A:A,'B0.SUM (tuần 0)'!$A178) -> 0 | AN178: =SUMIFS('B0.8.Online'!M:M,'B0.8.Online'!A:A,'B0.SUM (tuần 0)'!$A178) -> 0 | AP178: =SUMIFS('B1.SUM (tuần 4)'!$I:$I,'B1.SUM (tuần 4)'!$A:$A,'B0.SUM (tuần 0)'!$A178) -> 0 | AQ178: =I178-AP178 -> 0
A179: 1001110703 | B179: Máy LN KAQ-U98 Pro KRF (TNT USA) | C179: KAQ-U98 Pro | D179: Máy TCM Sx | E179: 10L | F179: XK | H179: 2420505 | I179: =SUM(J179:P179) -> 0 | K179: =SUMIFS('B0.3.XK'!J:J,'B0.3.XK'!A:A,'B0.SUM (tuần 0)'!$A179) -> 0 | M179: =SUMIFS('B0.5.GT2'!K:K,'B0.5.GT2'!A:A,'B0.SUM (tuần 0)'!$A179) -> 0 | N179: =SUMIFS('B0.4.OEM'!J:J,'B0.4.OEM'!A:A,'B0.SUM (tuần 0)'!$A179) -> 0 | P179: =SUMIFS('B0.8.Online'!J:J,'B0.8.Online'!A:A,'B0.SUM (tuần 0)'!$A179) -> 0 | Q179: =SUM(R179:X179) -> 0 | S179: =SUMIFS('B0.3.XK'!K:K,'B0.3.XK'!A:A,'B0.SUM (tuần 0)'!$A179) -> 0 | U179: =SUMIFS('B0.5.GT2'!K:K,'B0.5.GT2'!A:A,'B0.SUM (tuần 0)'!$A179) -> 0 | V179: =SUMIFS('B0.4.OEM'!K:K,'B0.4.OEM'!A:A,'B0.SUM (tuần 0)'!$A179) -> 0 | X179: =SUMIFS('B0.8.Online'!K:K,'B0.8.Online'!A:A,'B0.SUM (tuần 0)'!$A179) -> 0 | Y179: =SUM(Z179:AF179) -> 0 | AA179: =SUMIFS('B0.3.XK'!L:L,'B0.3.XK'!A:A,'B0.SUM (tuần 0)'!$A179) -> 0 | AC179: =SUMIFS('B0.5.GT2'!L:L,'B0.5.GT2'!A:A,'B0.SUM (tuần 0)'!$A179) -> 0 | AD179: =SUMIFS('B0.4.OEM'!L:L,'B0.4.OEM'!A:A,'B0.SUM (tuần 0)'!$A179) -> 0 | AF179: =SUMIFS('B0.8.Online'!L:L,'B0.8.Online'!A:A,'B0.SUM (tuần 0)'!$A179) -> 0 | AG179: =SUM(AH179:AN179) -> 0 | AI179: =SUMIFS('B0.3.XK'!M:M,'B0.3.XK'!A:A,'B0.SUM (tuần 0)'!$A179) -> 0 | AK179: =SUMIFS('B0.5.GT2'!M:M,'B0.5.GT2'!A:A,'B0.SUM (tuần 0)'!$A179) -> 0 | AL179: =SUMIFS('B0.4.OEM'!M:M,'B0.4.OEM'!A:A,'B0.SUM (tuần 0)'!$A179) -> 0 | AN179: =SUMIFS('B0.8.Online'!M:M,'B0.8.Online'!A:A,'B0.SUM (tuần 0)'!$A179) -> 0 | AP179: =SUMIFS('B1.SUM (tuần 4)'!$I:$I,'B1.SUM (tuần 4)'!$A:$A,'B0.SUM (tuần 0)'!$A179) -> 0 | AQ179: =I179-AP179 -> 0
A180: 1001110704 | B180: Máy LN NL DIAMOND SENSIA S7 | C180: SensiaS7 | D180: Máy TCM Sx | E180: Block | F180: XK | H180: 7043143 | I180: =SUM(J180:P180) -> 0 | K180: =SUMIFS('B0.3.XK'!J:J,'B0.3.XK'!A:A,'B0.SUM (tuần 0)'!$A180) -> 0 | M180: =SUMIFS('B0.5.GT2'!K:K,'B0.5.GT2'!A:A,'B0.SUM (tuần 0)'!$A180) -> 0 | N180: =SUMIFS('B0.4.OEM'!J:J,'B0.4.OEM'!A:A,'B0.SUM (tuần 0)'!$A180) -> 0 | P180: =SUMIFS('B0.8.Online'!J:J,'B0.8.Online'!A:A,'B0.SUM (tuần 0)'!$A180) -> 0 | Q180: =SUM(R180:X180) -> 0 | S180: =SUMIFS('B0.3.XK'!K:K,'B0.3.XK'!A:A,'B0.SUM (tuần 0)'!$A180) -> 0 | U180: =SUMIFS('B0.5.GT2'!K:K,'B0.5.GT2'!A:A,'B0.SUM (tuần 0)'!$A180) -> 0 | V180: =SUMIFS('B0.4.OEM'!K:K,'B0.4.OEM'!A:A,'B0.SUM (tuần 0)'!$A180) -> 0 | X180: =SUMIFS('B0.8.Online'!K:K,'B0.8.Online'!A:A,'B0.SUM (tuần 0)'!$A180) -> 0 | Y180: =SUM(Z180:AF180) -> 0 | AA180: =SUMIFS('B0.3.XK'!L:L,'B0.3.XK'!A:A,'B0.SUM (tuần 0)'!$A180) -> 0 | AC180: =SUMIFS('B0.5.GT2'!L:L,'B0.5.GT2'!A:A,'B0.SUM (tuần 0)'!$A180) -> 0 | AD180: =SUMIFS('B0.4.OEM'!L:L,'B0.4.OEM'!A:A,'B0.SUM (tuần 0)'!$A180) -> 0 | AF180: =SUMIFS('B0.8.Online'!L:L,'B0.8.Online'!A:A,'B0.SUM (tuần 0)'!$A180) -> 0 | AG180: =SUM(AH180:AN180) -> 0 | AI180: =SUMIFS('B0.3.XK'!M:M,'B0.3.XK'!A:A,'B0.SUM (tuần 0)'!$A180) -> 0 | AK180: =SUMIFS('B0.5.GT2'!M:M,'B0.5.GT2'!A:A,'B0.SUM (tuần 0)'!$A180) -> 0 | AL180: =SUMIFS('B0.4.OEM'!M:M,'B0.4.OEM'!A:A,'B0.SUM (tuần 0)'!$A180) -> 0 | AN180: =SUMIFS('B0.8.Online'!M:M,'B0.8.Online'!A:A,'B0.SUM (tuần 0)'!$A180) -> 0 | AP180: =SUMIFS('B1.SUM (tuần 4)'!$I:$I,'B1.SUM (tuần 4)'!$A:$A,'B0.SUM (tuần 0)'!$A180) -> 0 | AQ180: =I180-AP180 -> 0
A181: 1001110705 | B181: Máy LN PLATINUM LUMIFLOW S2 | C181: Platinum S2 | D181: Máy TCM Sx | E181: 10L Tủ | F181: XK | H181: 4424262 | I181: =SUM(J181:P181) -> 0 | K181: =SUMIFS('B0.3.XK'!J:J,'B0.3.XK'!A:A,'B0.SUM (tuần 0)'!$A181) -> 0 | M181: =SUMIFS('B0.5.GT2'!K:K,'B0.5.GT2'!A:A,'B0.SUM (tuần 0)'!$A181) -> 0 | N181: =SUMIFS('B0.4.OEM'!J:J,'B0.4.OEM'!A:A,'B0.SUM (tuần 0)'!$A181) -> 0 | P181: =SUMIFS('B0.8.Online'!J:J,'B0.8.Online'!A:A,'B0.SUM (tuần 0)'!$A181) -> 0 | Q181: =SUM(R181:X181) -> 0 | S181: =SUMIFS('B0.3.XK'!K:K,'B0.3.XK'!A:A,'B0.SUM (tuần 0)'!$A181) -> 0 | U181: =SUMIFS('B0.5.GT2'!K:K,'B0.5.GT2'!A:A,'B0.SUM (tuần 0)'!$A181) -> 0 | V181: =SUMIFS('B0.4.OEM'!K:K,'B0.4.OEM'!A:A,'B0.SUM (tuần 0)'!$A181) -> 0 | X181: =SUMIFS('B0.8.Online'!K:K,'B0.8.Online'!A:A,'B0.SUM (tuần 0)'!$A181) -> 0 | Y181: =SUM(Z181:AF181) -> 0 | AA181: =SUMIFS('B0.3.XK'!L:L,'B0.3.XK'!A:A,'B0.SUM (tuần 0)'!$A181) -> 0 | AC181: =SUMIFS('B0.5.GT2'!L:L,'B0.5.GT2'!A:A,'B0.SUM (tuần 0)'!$A181) -> 0 | AD181: =SUMIFS('B0.4.OEM'!L:L,'B0.4.OEM'!A:A,'B0.SUM (tuần 0)'!$A181) -> 0 | AF181: =SUMIFS('B0.8.Online'!L:L,'B0.8.Online'!A:A,'B0.SUM (tuần 0)'!$A181) -> 0 | AG181: =SUM(AH181:AN181) -> 0 | AI181: =SUMIFS('B0.3.XK'!M:M,'B0.3.XK'!A:A,'B0.SUM (tuần 0)'!$A181) -> 0 | AK181: =SUMIFS('B0.5.GT2'!M:M,'B0.5.GT2'!A:A,'B0.SUM (tuần 0)'!$A181) -> 0 | AL181: =SUMIFS('B0.4.OEM'!M:M,'B0.4.OEM'!A:A,'B0.SUM (tuần 0)'!$A181) -> 0 | AN181: =SUMIFS('B0.8.Online'!M:M,'B0.8.Online'!A:A,'B0.SUM (tuần 0)'!$A181) -> 0 | AP181: =SUMIFS('B1.SUM (tuần 4)'!$I:$I,'B1.SUM (tuần 4)'!$A:$A,'B0.SUM (tuần 0)'!$A181) -> 0 | AQ181: =I181-AP181 -> 0
A182: 1001110706 | B182: Máy LN DIAMOND SENSIA INFINITY X600 | C182: INFINITYX600 | D182: Máy TCM Sx | E182: 10L Tủ | F182: XK | H182: 2679657 | I182: =SUM(J182:P182) -> 0 | K182: =SUMIFS('B0.3.XK'!J:J,'B0.3.XK'!A:A,'B0.SUM (tuần 0)'!$A182) -> 0 | M182: =SUMIFS('B0.5.GT2'!K:K,'B0.5.GT2'!A:A,'B0.SUM (tuần 0)'!$A182) -> 0 | N182: =SUMIFS('B0.4.OEM'!J:J,'B0.4.OEM'!A:A,'B0.SUM (tuần 0)'!$A182) -> 0 | P182: =SUMIFS('B0.8.Online'!J:J,'B0.8.Online'!A:A,'B0.SUM (tuần 0)'!$A182) -> 0 | Q182: =SUM(R182:X182) -> 0 | S182: =SUMIFS('B0.3.XK'!K:K,'B0.3.XK'!A:A,'B0.SUM (tuần 0)'!$A182) -> 0 | U182: =SUMIFS('B0.5.GT2'!K:K,'B0.5.GT2'!A:A,'B0.SUM (tuần 0)'!$A182) -> 0 | V182: =SUMIFS('B0.4.OEM'!K:K,'B0.4.OEM'!A:A,'B0.SUM (tuần 0)'!$A182) -> 0 | X182: =SUMIFS('B0.8.Online'!K:K,'B0.8.Online'!A:A,'B0.SUM (tuần 0)'!$A182) -> 0 | Y182: =SUM(Z182:AF182) -> 0 | AA182: =SUMIFS('B0.3.XK'!L:L,'B0.3.XK'!A:A,'B0.SUM (tuần 0)'!$A182) -> 0 | AC182: =SUMIFS('B0.5.GT2'!L:L,'B0.5.GT2'!A:A,'B0.SUM (tuần 0)'!$A182) -> 0 | AD182: =SUMIFS('B0.4.OEM'!L:L,'B0.4.OEM'!A:A,'B0.SUM (tuần 0)'!$A182) -> 0 | AF182: =SUMIFS('B0.8.Online'!L:L,'B0.8.Online'!A:A,'B0.SUM (tuần 0)'!$A182) -> 0 | AG182: =SUM(AH182:AN182) -> 0 | AI182: =SUMIFS('B0.3.XK'!M:M,'B0.3.XK'!A:A,'B0.SUM (tuần 0)'!$A182) -> 0 | AK182: =SUMIFS('B0.5.GT2'!M:M,'B0.5.GT2'!A:A,'B0.SUM (tuần 0)'!$A182) -> 0 | AL182: =SUMIFS('B0.4.OEM'!M:M,'B0.4.OEM'!A:A,'B0.SUM (tuần 0)'!$A182) -> 0 | AN182: =SUMIFS('B0.8.Online'!M:M,'B0.8.Online'!A:A,'B0.SUM (tuần 0)'!$A182) -> 0 | AP182: =SUMIFS('B1.SUM (tuần 4)'!$I:$I,'B1.SUM (tuần 4)'!$A:$A,'B0.SUM (tuần 0)'!$A182) -> 0 | AQ182: =I182-AP182 -> 0
A183: 1005010011 | B183: Máy lọc không khí KAROFI KAP-317 | C183: KAP-317 | D183: Máy TCM Sx | E183: LK khác | F183: XK | H183: 2302111 | I183: =SUM(J183:P183) -> 0 | K183: =SUMIFS('B0.3.XK'!J:J,'B0.3.XK'!A:A,'B0.SUM (tuần 0)'!$A183) -> 0 | M183: =SUMIFS('B0.5.GT2'!K:K,'B0.5.GT2'!A:A,'B0.SUM (tuần 0)'!$A183) -> 0 | N183: =SUMIFS('B0.4.OEM'!J:J,'B0.4.OEM'!A:A,'B0.SUM (tuần 0)'!$A183) -> 0 | P183: =SUMIFS('B0.8.Online'!J:J,'B0.8.Online'!A:A,'B0.SUM (tuần 0)'!$A183) -> 0 | Q183: =SUM(R183:X183) -> 0 | S183: =SUMIFS('B0.3.XK'!K:K,'B0.3.XK'!A:A,'B0.SUM (tuần 0)'!$A183) -> 0 | U183: =SUMIFS('B0.5.GT2'!K:K,'B0.5.GT2'!A:A,'B0.SUM (tuần 0)'!$A183) -> 0 | V183: =SUMIFS('B0.4.OEM'!K:K,'B0.4.OEM'!A:A,'B0.SUM (tuần 0)'!$A183) -> 0 | X183: =SUMIFS('B0.8.Online'!K:K,'B0.8.Online'!A:A,'B0.SUM (tuần 0)'!$A183) -> 0 | Y183: =SUM(Z183:AF183) -> 0 | AA183: =SUMIFS('B0.3.XK'!L:L,'B0.3.XK'!A:A,'B0.SUM (tuần 0)'!$A183) -> 0 | AC183: =SUMIFS('B0.5.GT2'!L:L,'B0.5.GT2'!A:A,'B0.SUM (tuần 0)'!$A183) -> 0 | AD183: =SUMIFS('B0.4.OEM'!L:L,'B0.4.OEM'!A:A,'B0.SUM (tuần 0)'!$A183) -> 0 | AF183: =SUMIFS('B0.8.Online'!L:L,'B0.8.Online'!A:A,'B0.SUM (tuần 0)'!$A183) -> 0 | AG183: =SUM(AH183:AN183) -> 0 | AI183: =SUMIFS('B0.3.XK'!M:M,'B0.3.XK'!A:A,'B0.SUM (tuần 0)'!$A183) -> 0 | AK183: =SUMIFS('B0.5.GT2'!M:M,'B0.5.GT2'!A:A,'B0.SUM (tuần 0)'!$A183) -> 0 | AL183: =SUMIFS('B0.4.OEM'!M:M,'B0.4.OEM'!A:A,'B0.SUM (tuần 0)'!$A183) -> 0 | AN183: =SUMIFS('B0.8.Online'!M:M,'B0.8.Online'!A:A,'B0.SUM (tuần 0)'!$A183) -> 0 | AP183: =SUMIFS('B1.SUM (tuần 4)'!$I:$I,'B1.SUM (tuần 4)'!$A:$A,'B0.SUM (tuần 0)'!$A183) -> 0 | AQ183: =I183-AP183 -> 0
A184: 2001020023 | B184: Nắp cốc 20" 3/8 đen (TCM) | C184: HS Cap 20" 3/8 | D184: Linh kiện khác | E184: LK khác | F184: XK | H184: 0 | I184: =SUM(J184:P184) -> 0 | K184: =SUMIFS('B0.3.XK'!J:J,'B0.3.XK'!A:A,'B0.SUM (tuần 0)'!$A184) -> 0 | M184: =SUMIFS('B0.5.GT2'!K:K,'B0.5.GT2'!A:A,'B0.SUM (tuần 0)'!$A184) -> 0 | N184: =SUMIFS('B0.4.OEM'!J:J,'B0.4.OEM'!A:A,'B0.SUM (tuần 0)'!$A184) -> 0 | P184: =SUMIFS('B0.8.Online'!J:J,'B0.8.Online'!A:A,'B0.SUM (tuần 0)'!$A184) -> 0 | Q184: =SUM(R184:X184) -> 120 | S184: =SUMIFS('B0.3.XK'!K:K,'B0.3.XK'!A:A,'B0.SUM (tuần 0)'!$A184) -> 120 | U184: =SUMIFS('B0.5.GT2'!K:K,'B0.5.GT2'!A:A,'B0.SUM (tuần 0)'!$A184) -> 0 | V184: =SUMIFS('B0.4.OEM'!K:K,'B0.4.OEM'!A:A,'B0.SUM (tuần 0)'!$A184) -> 0 | X184: =SUMIFS('B0.8.Online'!K:K,'B0.8.Online'!A:A,'B0.SUM (tuần 0)'!$A184) -> 0 | Y184: =SUM(Z184:AF184) -> 0 | AA184: =SUMIFS('B0.3.XK'!L:L,'B0.3.XK'!A:A,'B0.SUM (tuần 0)'!$A184) -> 0 | AC184: =SUMIFS('B0.5.GT2'!L:L,'B0.5.GT2'!A:A,'B0.SUM (tuần 0)'!$A184) -> 0 | AD184: =SUMIFS('B0.4.OEM'!L:L,'B0.4.OEM'!A:A,'B0.SUM (tuần 0)'!$A184) -> 0 | AF184: =SUMIFS('B0.8.Online'!L:L,'B0.8.Online'!A:A,'B0.SUM (tuần 0)'!$A184) -> 0 | AG184: =SUM(AH184:AN184) -> 0 | AI184: =SUMIFS('B0.3.XK'!M:M,'B0.3.XK'!A:A,'B0.SUM (tuần 0)'!$A184) -> 0 | AK184: =SUMIFS('B0.5.GT2'!M:M,'B0.5.GT2'!A:A,'B0.SUM (tuần 0)'!$A184) -> 0 | AL184: =SUMIFS('B0.4.OEM'!M:M,'B0.4.OEM'!A:A,'B0.SUM (tuần 0)'!$A184) -> 0 | AN184: =SUMIFS('B0.8.Online'!M:M,'B0.8.Online'!A:A,'B0.SUM (tuần 0)'!$A184) -> 0 | AP184: =SUMIFS('B1.SUM (tuần 4)'!$I:$I,'B1.SUM (tuần 4)'!$A:$A,'B0.SUM (tuần 0)'!$A184) -> 0 | AQ184: =I184-AP184 -> 0
A185: 2001020025 | B185: Cốc 20" vuông xanh 3/8 KAROFI | C185: Housing 20" Blue | D185: Linh kiện khác | E185: Cốc | F185: XK | H185: 352552 | I185: =SUM(J185:P185) -> 0 | K185: =SUMIFS('B0.3.XK'!J:J,'B0.3.XK'!A:A,'B0.SUM (tuần 0)'!$A185) -> 0 | M185: =SUMIFS('B0.5.GT2'!K:K,'B0.5.GT2'!A:A,'B0.SUM (tuần 0)'!$A185) -> 0 | N185: =SUMIFS('B0.4.OEM'!J:J,'B0.4.OEM'!A:A,'B0.SUM (tuần 0)'!$A185) -> 0 | P185: =SUMIFS('B0.8.Online'!J:J,'B0.8.Online'!A:A,'B0.SUM (tuần 0)'!$A185) -> 0 | Q185: =SUM(R185:X185) -> 80 | S185: =SUMIFS('B0.3.XK'!K:K,'B0.3.XK'!A:A,'B0.SUM (tuần 0)'!$A185) -> 80 | U185: =SUMIFS('B0.5.GT2'!K:K,'B0.5.GT2'!A:A,'B0.SUM (tuần 0)'!$A185) -> 0 | V185: =SUMIFS('B0.4.OEM'!K:K,'B0.4.OEM'!A:A,'B0.SUM (tuần 0)'!$A185) -> 0 | X185: =SUMIFS('B0.8.Online'!K:K,'B0.8.Online'!A:A,'B0.SUM (tuần 0)'!$A185) -> 0 | Y185: =SUM(Z185:AF185) -> 0 | AA185: =SUMIFS('B0.3.XK'!L:L,'B0.3.XK'!A:A,'B0.SUM (tuần 0)'!$A185) -> 0 | AC185: =SUMIFS('B0.5.GT2'!L:L,'B0.5.GT2'!A:A,'B0.SUM (tuần 0)'!$A185) -> 0 | AD185: =SUMIFS('B0.4.OEM'!L:L,'B0.4.OEM'!A:A,'B0.SUM (tuần 0)'!$A185) -> 0 | AF185: =SUMIFS('B0.8.Online'!L:L,'B0.8.Online'!A:A,'B0.SUM (tuần 0)'!$A185) -> 0 | AG185: =SUM(AH185:AN185) -> 0 | AI185: =SUMIFS('B0.3.XK'!M:M,'B0.3.XK'!A:A,'B0.SUM (tuần 0)'!$A185) -> 0 | AK185: =SUMIFS('B0.5.GT2'!M:M,'B0.5.GT2'!A:A,'B0.SUM (tuần 0)'!$A185) -> 0 | AL185: =SUMIFS('B0.4.OEM'!M:M,'B0.4.OEM'!A:A,'B0.SUM (tuần 0)'!$A185) -> 0 | AN185: =SUMIFS('B0.8.Online'!M:M,'B0.8.Online'!A:A,'B0.SUM (tuần 0)'!$A185) -> 0 | AP185: =SUMIFS('B1.SUM (tuần 4)'!$I:$I,'B1.SUM (tuần 4)'!$A:$A,'B0.SUM (tuần 0)'!$A185) -> 0 | AQ185: =I185-AP185 -> 0
... A190: 2001020040 | B190: Bộ cốc 10" Đài Loan trắng MOYA BARDA | C190: Housing TW Color | D190: Linh kiện khác | E190: Cốc | F190: XK | H190: 47358 | I190: =SUM(J190:P190) -> 0 | K190: =SUMIFS('B0.3.XK'!J:J,'B0.3.XK'!A:A,'B0.SUM (tuần 0)'!$A190) -> 0 | M190: =SUMIFS('B0.5.GT2'!K:K,'B0.5.GT2'!A:A,'B0.SUM (tuần 0)'!$A190) -> 0 | N190: =SUMIFS('B0.4.OEM'!J:J,'B0.4.OEM'!A:A,'B0.SUM (tuần 0)'!$A190) -> 0 | P190: =SUMIFS('B0.8.Online'!J:J,'B0.8.Online'!A:A,'B0.SUM (tuần 0)'!$A190) -> 0 | Q190: =SUM(R190:X190) -> 0 | S190: =SUMIFS('B0.3.XK'!K:K,'B0.3.XK'!A:A,'B0.SUM (tuần 0)'!$A190) -> 0 | U190: =SUMIFS('B0.5.GT2'!K:K,'B0.5.GT2'!A:A,'B0.SUM (tuần 0)'!$A190) -> 0 | V190: =SUMIFS('B0.4.OEM'!K:K,'B0.4.OEM'!A:A,'B0.SUM (tuần 0)'!$A190) -> 0 | X190: =SUMIFS('B0.8.Online'!K:K,'B0.8.Online'!A:A,'B0.SUM (tuần 0)'!$A190) -> 0 | Y190: =SUM(Z190:AF190) -> 0 | AA190: =SUMIFS('B0.3.XK'!L:L,'B0.3.XK'!A:A,'B0.SUM (tuần 0)'!$A190) -> 0 | AC190: =SUMIFS('B0.5.GT2'!L:L,'B0.5.GT2'!A:A,'B0.SUM (tuần 0)'!$A190) -> 0 | AD190: =SUMIFS('B0.4.OEM'!L:L,'B0.4.OEM'!A:A,'B0.SUM (tuần 0)'!$A190) -> 0 | AF190: =SUMIFS('B0.8.Online'!L:L,'B0.8.Online'!A:A,'B0.SUM (tuần 0)'!$A190) -> 0 | AG190: =SUM(AH190:AN190) -> 600 | AI190: =SUMIFS('B0.3.XK'!M:M,'B0.3.XK'!A:A,'B0.SUM (tuần 0)'!$A190) -> 600 | AK190: =SUMIFS('B0.5.GT2'!M:M,'B0.5.GT2'!A:A,'B0.SUM (tuần 0)'!$A190) -> 0 | AL190: =SUMIFS('B0.4.OEM'!M:M,'B0.4.OEM'!A:A,'B0.SUM (tuần 0)'!$A190) -> 0 | AN190: =SUMIFS('B0.8.Online'!M:M,'B0.8.Online'!A:A,'B0.SUM (tuần 0)'!$A190) -> 0 | AP190: =SUMIFS('B1.SUM (tuần 4)'!$I:$I,'B1.SUM (tuần 4)'!$A:$A,'B0.SUM (tuần 0)'!$A190) -> 0 | AQ190: =I190-AP190 -> 0
A191: 2001020041 | B191: Bộ cốc 10" Đài Loan trong MOYA BARDA | C191: Housing TW Clear | D191: Linh kiện khác | E191: Cốc | F191: XK | H191: 52620 | I191: =SUM(J191:P191) -> 0 | K191: =SUMIFS('B0.3.XK'!J:J,'B0.3.XK'!A:A,'B0.SUM (tuần 0)'!$A191) -> 0 | M191: =SUMIFS('B0.5.GT2'!K:K,'B0.5.GT2'!A:A,'B0.SUM (tuần 0)'!$A191) -> 0 | N191: =SUMIFS('B0.4.OEM'!J:J,'B0.4.OEM'!A:A,'B0.SUM (tuần 0)'!$A191) -> 0 | P191: =SUMIFS('B0.8.Online'!J:J,'B0.8.Online'!A:A,'B0.SUM (tuần 0)'!$A191) -> 0 | Q191: =SUM(R191:X191) -> 0 | S191: =SUMIFS('B0.3.XK'!K:K,'B0.3.XK'!A:A,'B0.SUM (tuần 0)'!$A191) -> 0 | U191: =SUMIFS('B0.5.GT2'!K:K,'B0.5.GT2'!A:A,'B0.SUM (tuần 0)'!$A191) -> 0 | V191: =SUMIFS('B0.4.OEM'!K:K,'B0.4.OEM'!A:A,'B0.SUM (tuần 0)'!$A191) -> 0 | X191: =SUMIFS('B0.8.Online'!K:K,'B0.8.Online'!A:A,'B0.SUM (tuần 0)'!$A191) -> 0 | Y191: =SUM(Z191:AF191) -> 0 | AA191: =SUMIFS('B0.3.XK'!L:L,'B0.3.XK'!A:A,'B0.SUM (tuần 0)'!$A191) -> 0 | AC191: =SUMIFS('B0.5.GT2'!L:L,'B0.5.GT2'!A:A,'B0.SUM (tuần 0)'!$A191) -> 0 | AD191: =SUMIFS('B0.4.OEM'!L:L,'B0.4.OEM'!A:A,'B0.SUM (tuần 0)'!$A191) -> 0 | AF191: =SUMIFS('B0.8.Online'!L:L,'B0.8.Online'!A:A,'B0.SUM (tuần 0)'!$A191) -> 0 | AG191: =SUM(AH191:AN191) -> 300 | AI191: =SUMIFS('B0.3.XK'!M:M,'B0.3.XK'!A:A,'B0.SUM (tuần 0)'!$A191) -> 300 | AK191: =SUMIFS('B0.5.GT2'!M:M,'B0.5.GT2'!A:A,'B0.SUM (tuần 0)'!$A191) -> 0 | AL191: =SUMIFS('B0.4.OEM'!M:M,'B0.4.OEM'!A:A,'B0.SUM (tuần 0)'!$A191) -> 0 | AN191: =SUMIFS('B0.8.Online'!M:M,'B0.8.Online'!A:A,'B0.SUM (tuần 0)'!$A191) -> 0 | AO191: Bỏ mã, clear NVL | AP191: =SUMIFS('B1.SUM (tuần 4)'!$I:$I,'B1.SUM (tuần 4)'!$A:$A,'B0.SUM (tuần 0)'!$A191) -> 0 | AQ191: =I191-AP191 -> 0
A192: 2001020045 | B192: Bộ cốc ĐL 4-4I trắng | C192: TW_White4-4I | D192: Linh kiện khác | E192: Cốc | F192: XK | H192: 49594 | I192: =SUM(J192:P192) -> 500 | K192: =SUMIFS('B0.3.XK'!J:J,'B0.3.XK'!A:A,'B0.SUM (tuần 0)'!$A192) -> 500 | M192: =SUMIFS('B0.5.GT2'!K:K,'B0.5.GT2'!A:A,'B0.SUM (tuần 0)'!$A192) -> 0 | N192: =SUMIFS('B0.4.OEM'!J:J,'B0.4.OEM'!A:A,'B0.SUM (tuần 0)'!$A192) -> 0 | P192: =SUMIFS('B0.8.Online'!J:J,'B0.8.Online'!A:A,'B0.SUM (tuần 0)'!$A192) -> 0 | Q192: =SUM(R192:X192) -> 0 | S192: =SUMIFS('B0.3.XK'!K:K,'B0.3.XK'!A:A,'B0.SUM (tuần 0)'!$A192) -> 0 | U192: =SUMIFS('B0.5.GT2'!K:K,'B0.5.GT2'!A:A,'B0.SUM (tuần 0)'!$A192) -> 0 | V192: =SUMIFS('B0.4.OEM'!K:K,'B0.4.OEM'!A:A,'B0.SUM (tuần 0)'!$A192) -> 0 | X192: =SUMIFS('B0.8.Online'!K:K,'B0.8.Online'!A:A,'B0.SUM (tuần 0)'!$A192) -> 0 | Y192: =SUM(Z192:AF192) -> 0 | AA192: =SUMIFS('B0.3.XK'!L:L,'B0.3.XK'!A:A,'B0.SUM (tuần 0)'!$A192) -> 0 | AC192: =SUMIFS('B0.5.GT2'!L:L,'B0.5.GT2'!A:A,'B0.SUM (tuần 0)'!$A192) -> 0 | AD192: =SUMIFS('B0.4.OEM'!L:L,'B0.4.OEM'!A:A,'B0.SUM (tuần 0)'!$A192) -> 0 | AF192: =SUMIFS('B0.8.Online'!L:L,'B0.8.Online'!A:A,'B0.SUM (tuần 0)'!$A192) -> 0 | AG192: =SUM(AH192:AN192) -> 0 | AI192: =SUMIFS('B0.3.XK'!M:M,'B0.3.XK'!A:A,'B0.SUM (tuần 0)'!$A192) -> 0 | AK192: =SUMIFS('B0.5.GT2'!M:M,'B0.5.GT2'!A:A,'B0.SUM (tuần 0)'!$A192) -> 0 | AL192: =SUMIFS('B0.4.OEM'!M:M,'B0.4.OEM'!A:A,'B0.SUM (tuần 0)'!$A192) -> 0 | AN192: =SUMIFS('B0.8.Online'!M:M,'B0.8.Online'!A:A,'B0.SUM (tuần 0)'!$A192) -> 0 | AP192: =SUMIFS('B1.SUM (tuần 4)'!$I:$I,'B1.SUM (tuần 4)'!$A:$A,'B0.SUM (tuần 0)'!$A192) -> 0 | AQ192: =I192-AP192 -> 500
...

Sheet B0.3.XK
A1: BẢNG 0.3: | B1: SALES FORECAST - KÊNH XUẤT KHẨU | I1: Tổng cộng | O1: Miền Bắc | U1: Miền Nam
I2: TỔNG | J2: =J10 -> Tháng 7 | K2: =K10 -> Tháng 8 | L2: =L10 -> Tháng 9 | M2: =M10 -> Tháng 10
G3: NHÓM 1 | H3: Máy TCM sx | I3: =SUM(J3:M3) -> 27066 | J3: =SUMIF($D$10:$D$1025,$H3,J$10:J$1025) -> 3795 | K3: =SUMIF($D$10:$D$1025,$H3,K$10:K$1025) -> 7150 | L3: =SUMIF($D$10:$D$1025,$H3,L$10:L$1025) -> 7791 | M3: =SUMIF($D$10:$D$1025,$H3,M$10:M$1025) -> 8330
G4: NHÓM 2 | H4: Máy nhập khẩu | I4: =SUM(J4:M4) -> 0 | J4: =SUMIF($D$10:$D$1025,$H4,J$10:J$1025) -> 0 | K4: =SUMIF($D$10:$D$1025,$H4,K$10:K$1025) -> 0 | L4: =SUMIF($D$10:$D$1025,$H4,L$10:L$1025) -> 0 | M4: =SUMIF($D$10:$D$1025,$H4,M$10:M$1025) -> 0
G5: NHÓM 3 | H5: Mockup | I5: =SUM(J5:M5) -> 0 | J5: =SUMIF($D$10:$D$1025,$H5,J$10:J$1025) -> 0 | K5: =SUMIF($D$10:$D$1025,$H5,K$10:K$1025) -> 0 | L5: =SUMIF($D$10:$D$1025,$H5,L$10:L$1025) -> 0 | M5: =SUMIF($D$10:$D$1025,$H5,M$10:M$1025) -> 0
G6: NHÓM 4 | H6: Lõi | I6: =SUM(J6:M6) -> 529105 | J6: =SUMIF($D$10:$D$1025,$H6,J$10:J$1025) -> 134477 | K6: =SUMIF($D$10:$D$1025,$H6,K$10:K$1025) -> 43355 | L6: =SUMIF($D$10:$D$1025,$H6,L$10:L$1025) -> 59130 | M6: =SUMIF($D$10:$D$1025,$H6,M$10:M$1025) -> 292143
G7: NHÓM 5 | H7: Màng | I7: =SUM(J7:M7) -> 11930 | J7: =SUMIF($D$10:$D$1025,$H7,J$10:J$1025) -> 6475 | K7: =SUMIF($D$10:$D$1025,$H7,K$10:K$1025) -> 1975 | L7: =SUMIF($D$10:$D$1025,$H7,L$10:L$1025) -> 1450 | M7: =SUMIF($D$10:$D$1025,$H7,M$10:M$1025) -> 2030
A8: Ngày update | B8: ='B0.SUM (tuần 0)'!B3 -> 46204 | H8: Doanh thu theo FC | J8: =SUMPRODUCT($H$11:$H$715,J11:J715) -> 1.1008535e+10 | K8: =SUMPRODUCT($H$11:$H$176,K11:K176) -> 1.2531411e+10 | L8: =SUMPRODUCT($H$11:$H$176,L11:L176) -> 1.391031e+10 | M8: =SUMPRODUCT($H$11:$H$176,M11:M176) -> 1.2660184e+10
I9: =SUBTOTAL(9,I11:I1013) -> 706434 | J9: =J8*0.6 -> 6.6051212e+09 | K9: =K8*0.6 -> 7.5188466e+09 | L9: =L8*0.6 -> 8.3461863e+09 | M9: =M8*0.6 -> 7.5961102e+09 | O9: =SUBTOTAL(9,O11:O1013) -> 26916 | P9: =SUBTOTAL(9,P11:P1013) -> 169974 | Q9: =SUBTOTAL(9,Q11:Q1013) -> 76475 | R9: =SUBTOTAL(9,R11:R1013) -> 77831 | S9: =SUBTOTAL(9,S11:S1013) -> 382154 | T9: =SUBTOTAL(9,T11:T1013) -> 0 | U9: =SUBTOTAL(9,U11:U1013) -> 0 | V9: =SUBTOTAL(9,V11:V1013) -> 0 | ... Y9: =SUBTOTAL(9,Y11:Y1013) -> 0
A10: Mã sản phẩm | B10: Tên sản phẩm | C10: Model (tên gọi tắt) | D10: Nhóm | E10: Công nghệ chính | F10: Channel | G10: Độc quyền | H10: Giá ghi nhận Doanh thu (-VAT) | I10: Tổng FC | J10: ="Tháng"&" "&IF(DAY($B$8)<22,MONTH($B$8),MONTH($B$8)+1) -> Tháng 7 | K10: ="Tháng"&" "&RIGHT(J10,2)+1 -> Tháng 8 | L10: ="Tháng"&" "&RIGHT(K10,2)+1 -> Tháng 9 | M10: ="Tháng"&" "&RIGHT(L10,1)+1 -> Tháng 10 | O10: Tổng FC | P10: =J10 -> Tháng 7 | Q10: =K10 -> Tháng 8 | R10: =L10 -> Tháng 9 | S10: =M10 -> Tháng 10 | U10: Tổng FC | V10: =J10 -> Tháng 7 | W10: =K10 -> Tháng 8 | X10: =L10 -> Tháng 9 | Y10: =M10 -> Tháng 10 | Z10: Tài chính comment | AA10: TNKD
A11: 1001010040 | B11: Máy lọc nước KoriHome WPK-606 | C11: WPK-606 | D11: Máy TCM Sx | E11: 10L | F11: XK | H11: 3139092.2 | I11: =SUM(J11:M11) -> 100 | J11: =P11+V11 -> 100 | K11: =Q11+W11 -> 0 | L11: =R11+X11 -> 0 | M11: =S11+Y11 -> 0 | O11: =SUM(P11:S11) -> 100 | P11: 100 | U11: =SUM(V11:Y11) -> 0
A12: 1001020018 | B12: Bộ lọc thô 2 stages GRANDSAFE | C12: Prefilter2S10" | D12: Máy TCM Sx | E12: Bộ lọc thô | F12: XK | H12: 210478.68 | I12: =SUM(J12:M12) -> 2 | J12: =P12+V12 -> 0 | K12: =Q12+W12 -> 2 | L12: =R12+X12 -> 0 | M12: =S12+Y12 -> 0 | O12: =SUM(P12:S12) -> 2 | Q12: 2 | U12: =SUM(V12:Y12) -> 0
A13: 1001020019 | B13: Bộ lọc thô 1 stage GRANDSAFE | C13: Prefilter1S10" | D13: Máy TCM Sx | E13: Bộ lọc thô | F13: XK | H13: 152860 | I13: =SUM(J13:M13) -> 0 | J13: =P13+V13 -> 0 | K13: =Q13+W13 -> 0 | L13: =R13+X13 -> 0 | M13: =S13+Y13 -> 0 | O13: =SUM(P13:S13) -> 0 | U13: =SUM(V13:Y13) -> 0
A14: 1001020027 | B14: Bộ lọc thô 1 stage AQUALAND | C14: Prefilter1S10" | D14: Máy TCM Sx | E14: Bộ lọc thô | F14: XK | H14: 132864.67 | I14: =SUM(J14:M14) -> 0 | J14: =P14+V14 -> 0 | K14: =Q14+W14 -> 0 | L14: =R14+X14 -> 0 | M14: =S14+Y14 -> 0 | O14: =SUM(P14:S14) -> 0 | U14: =SUM(V14:Y14) -> 0
A15: 1001040396 | B15: Water purifier KAROFI S-s156 MT (KBA) | C15: 0 | D15: Máy TCM Sx | F15: XK | H15: 5393516.2 | I15: =SUM(J15:M15) -> 0 | J15: =P15+V15 -> 0 | K15: =Q15+W15 -> 0 | L15: =R15+X15 -> 0 | M15: =S15+Y15 -> 0 | O15: =SUM(P15:S15) -> 0 | U15: =SUM(V15:Y15) -> 0
A16: 1001040483 | B16: Máy lọc nước KAROFI KAQ-X16 | C16: KAQ-X16 | D16: Máy TCM Sx | E16: 10L Tủ | F16: XK | H16: 2853039 | I16: =SUM(J16:M16) -> 0 | J16: =P16+V16 -> 0 | K16: =Q16+W16 -> 0 | L16: =R16+X16 -> 0 | M16: =S16+Y16 -> 0 | O16: =SUM(P16:S16) -> 0 | U16: =SUM(V16:Y16) -> 0
A17: 1001040513 | B17: Máy lọc nước nóng lạnh KAROFI HCV-208RO | C17: HCV-208RO | D17: Máy TCM Sx | E17: Block | F17: XK | H17: 2889258.4 | I17: =SUM(J17:M17) -> 30 | J17: =P17+V17 -> 30 | K17: =Q17+W17 -> 0 | L17: =R17+X17 -> 0 | M17: =S17+Y17 -> 0 | O17: =SUM(P17:S17) -> 30 | P17: 30 | U17: =SUM(V17:Y17) -> 0
A18: 1001040537 | B18: Máy lọc nước KAROFI KAQ-U05 Pro | C18: KAQ-U05 Pro | D18: Máy TCM Sx | E18: 10L | F18: XK | H18: 1310192.2 | I18: =SUM(J18:M18) -> 0 | J18: =P18+V18 -> 0 | K18: =Q18+W18 -> 0 | L18: =R18+X18 -> 0 | M18: =S18+Y18 -> 0 | O18: =SUM(P18:S18) -> 0 | U18: =SUM(V18:Y18) -> 0
A19: 1001040549 | B19: Máy lọc nước nóng lạnh KAROFI KAD-X58 | C19: KAD-X58 | D19: Máy TCM Sx | E19: Block | F19: XK | H19: 4505559.3 | I19: =SUM(J19:M19) -> 20 | J19: =P19+V19 -> 0 | K19: =Q19+W19 -> 0 | L19: =R19+X19 -> 20 | M19: =S19+Y19 -> 0 | O19: =SUM(P19:S19) -> 20 | R19: 20 | U19: =SUM(V19:Y19) -> 0
A20: 1001040625 | B20: Máy LN-NL ion kiềm KRF KAE-S88 PROMAX | C20: S88 Promax | D20: Máy TCM Sx | E20: Block | F20: XK | H20: 13949475 | I20: =SUM(J20:M20) -> 0 | J20: =P20+V20 -> 0 | K20: =Q20+W20 -> 0 | L20: =R20+X20 -> 0 | M20: =S20+Y20 -> 0 | O20: =SUM(P20:S20) -> 0 | U20: =SUM(V20:Y20) -> 0
A21: 1001040673 | B21: Máy lọc tổng Karofi KTF-P02 (SF-T2) | C21: KTF-P02 | D21: Máy TCM Sx | E21: LK khác | F21: XK | H21: 9968336.1 | I21: =SUM(J21:M21) -> 0 | J21: =P21+V21 -> 0 | K21: =Q21+W21 -> 0 | L21: =R21+X21 -> 0 | M21: =S21+Y21 -> 0 | O21: =SUM(P21:S21) -> 0 | U21: =SUM(V21:Y21) -> 0
A22: 1001110006 | B22: MÁY RO-01 Tecomen 7S | C22: RO-01 | D22: Máy TCM Sx | E22: 10L | F22: XK | H22: 1735791 | I22: =SUM(J22:M22) -> 0 | J22: =P22+V22 -> 0 | K22: =Q22+W22 -> 0 | L22: =R22+X22 -> 0 | M22: =S22+Y22 -> 0 | O22: =SUM(P22:S22) -> 0 | U22: =SUM(V22:Y22) -> 0
A23: 1001110019 | B23: Máy lọc nước UNDERSINK GRANDSAFE | C23: S-S027 | D23: Máy TCM Sx | E23: 10L | F23: XK | H23: 2514694 | I23: =SUM(J23:M23) -> 120 | J23: =P23+V23 -> 0 | K23: =Q23+W23 -> 0 | L23: =R23+X23 -> 120 | M23: =S23+Y23 -> 0 | O23: =SUM(P23:S23) -> 120 | R23: 120 | U23: =SUM(V23:Y23) -> 0
A24: 1001110020 | B24: Máy RO-100 GRANDSAFE | C24: RO-100 | D24: Máy TCM Sx | E24: 10L | F24: XK | H24: 2002967.7 | I24: =SUM(J24:M24) -> 70 | J24: =P24+V24 -> 0 | K24: =Q24+W24 -> 0 | L24: =R24+X24 -> 70 | M24: =S24+Y24 -> 0 | O24: =SUM(P24:S24) -> 70 | R24: 70 | U24: =SUM(V24:Y24) -> 0
A25: 1001110035 | B25: Máy BCN-400 GPD ANMAX | C25: BCN-400 | D25: Máy TCM Sx | E25: BCN | F25: XK | H25: 4854164.6 | I25: =SUM(J25:M25) -> 300 | J25: =P25+V25 -> 0 | K25: =Q25+W25 -> 0 | L25: =R25+X25 -> 0 | M25: =S25+Y25 -> 300 | O25: =SUM(P25:S25) -> 300 | S25: 300 | U25: =SUM(V25:Y25) -> 0
A26: 1001110036 | B26: Máy BCN-200 GPD ANMAX | C26: BCN-200 | D26: Máy TCM Sx | E26: BCN | F26: XK | H26: 3354504 | I26: =SUM(J26:M26) -> 300 | J26: =P26+V26 -> 0 | K26: =Q26+W26 -> 0 | L26: =R26+X26 -> 0 | M26: =S26+Y26 -> 300 | O26: =SUM(P26:S26) -> 300 | S26: 300 | U26: =SUM(V26:Y26) -> 0
A27: 1001110042 | B27: Máy lọc nước UNDERSINK V2 GRANDSAFE đỏ | C27: S-S027 | D27: Máy TCM Sx | E27: 10L | F27: XK | H27: 2514694 | I27: =SUM(J27:M27) -> 120 | J27: =P27+V27 -> 0 | K27: =Q27+W27 -> 0 | L27: =R27+X27 -> 120 | M27: =S27+Y27 -> 0 | O27: =SUM(P27:S27) -> 120 | R27: 120 | U27: =SUM(V27:Y27) -> 0
A28: 1001110046 | B28: Máy lọc nước UNDERSINK V2 GRANDSAFE xanh | C28: S-S027 | D28: Máy TCM Sx | E28: 10L | F28: XK | H28: 2514694 | I28: =SUM(J28:M28) -> 120 | J28: =P28+V28 -> 0 | K28: =Q28+W28 -> 0 | L28: =R28+X28 -> 120 | M28: =S28+Y28 -> 0 | O28: =SUM(P28:S28) -> 120 | R28: 120 | U28: =SUM(V28:Y28) -> 0
A29: 1001110048 | B29: Máy RO-26 Tecomen | C29: RO-26 | D29: Máy TCM Sx | E29: 10L | F29: XK | H29: 1802223.7 | I29: =SUM(J29:M29) -> 60 | J29: =P29+V29 -> 0 | K29: =Q29+W29 -> 60 | L29: =R29+X29 -> 0 | M29: =S29+Y29 -> 0 | O29: =SUM(P29:S29) -> 60 | Q29: 60 | U29: =SUM(V29:Y29) -> 0
A30: 1001110051 | B30: Máy RO-100 AQUALAND (6S) | C30: RO-100 | D30: Máy TCM Sx | E30: 10L | F30: XK | H30: 1480717.5 | I30: =SUM(J30:M30) -> 0 | J30: =P30+V30 -> 0 | K30: =Q30+W30 -> 0 | L30: =R30+X30 -> 0 | M30: =S30+Y30 -> 0 | O30: =SUM(P30:S30) -> 0 | U30: =SUM(V30:Y30) -> 0
A31: 1001110056 | B31: Máy RO-401 (8S) | C31: RO-401 | D31: Máy TCM Sx | E31: 10L | F31: XK | H31: 1920618 | I31: =SUM(J31:M31) -> 300 | J31: =P31+V31 -> 0 | K31: =Q31+W31 -> 300 | L31: =R31+X31 -> 0 | M31: =S31+Y31 -> 0 | O31: =SUM(P31:S31) -> 300 | Q31: 300 | U31: =SUM(V31:Y31) -> 0
A32: 1001110058 | B32: Máy RO-35 Tecomen (7S) | C32: RO-35 | D32: Máy TCM Sx | E32: 10L | F32: XK | H32: 1723294.2 | I32: =SUM(J32:M32) -> 100 | J32: =P32+V32 -> 0 | K32: =Q32+W32 -> 100 | L32: =R32+X32 -> 0 | M32: =S32+Y32 -> 0 | O32: =SUM(P32:S32) -> 100 | Q32: 100 | U32: =SUM(V32:Y32) -> 0
A33: 1001110083 | B33: Máy lọc nước UNDERSINK đen v3 PURE LIFE | C33: S-S027 | D33: Máy TCM Sx | E33: 10L | F33: XK | H33: 2275800.7 | I33: =SUM(J33:M33) -> 400 | J33: =P33+V33 -> 0 | K33: =Q33+W33 -> 0 | L33: =R33+X33 -> 400 | M33: =S33+Y33 -> 0 | O33: =SUM(P33:S33) -> 400 | R33: 400 | U33: =SUM(V33:Y33) -> 0
A34: 1001110086 | B34: Bộ lọc thô 1 stage PURE LIFE | C34: Prefilter1S10" | D34: Máy TCM Sx | E34: Bộ lọc thô | F34: XK | H34: 124445.52 | I34: =SUM(J34:M34) -> 100 | J34: =P34+V34 -> 0 | K34: =Q34+W34 -> 0 | L34: =R34+X34 -> 100 | M34: =S34+Y34 -> 0 | O34: =SUM(P34:S34) -> 100 | R34: 100 | U34: =SUM(V34:Y34) -> 0
A35: 1001110088 | B35: Bộ lọc thô 3 stages Pure Life | C35: Prefilter3S10" | D35: Máy TCM Sx | E35: Bộ lọc thô | F35: XK | H35: 400698.79 | I35: =SUM(J35:M35) -> 100 | J35: =P35+V35 -> 0 | K35: =Q35+W35 -> 0 | L35: =R35+X35 -> 100 | M35: =S35+Y35 -> 0 | O35: =SUM(P35:S35) -> 100 | R35: 100 | U35: =SUM(V35:Y35) -> 0
A36: 1001110090 | B36: Máy RO BCN-300 Tecomen | C36: BCN-300 | D36: Máy TCM Sx | E36: BCN | F36: XK | H36: 6081518.4 | I36: =SUM(J36:M36) -> 0 | J36: =P36+V36 -> 0 | K36: =Q36+W36 -> 0 | L36: =R36+X36 -> 0 | M36: =S36+Y36 -> 0 | O36: =SUM(P36:S36) -> 0 | U36: =SUM(V36:Y36) -> 0
A37: 1001110092 | B37: Máy RO Undersink US | C37: UDSUS | D37: Máy TCM Sx | E37: 10L | F37: XK | H37: 1595033.8 | I37: =SUM(J37:M37) -> 612 | J37: =P37+V37 -> 0 | K37: =Q37+W37 -> 0 | L37: =R37+X37 -> 612 | M37: =S37+Y37 -> 0 | O37: =SUM(P37:S37) -> 612 | R37: 612 | U37: =SUM(V37:Y37) -> 0
A38: 1001110097 | B38: MÁY BCN-400 GPD GRANDSAFE | C38: BCN-400 | D38: Máy TCM Sx | E38: BCN | F38: XK | H38: 6735317.8 | I38: =SUM(J38:M38) -> 20 | J38: =P38+V38 -> 0 | K38: =Q38+W38 -> 0 | L38: =R38+X38 -> 20 | M38: =S38+Y38 -> 0 | O38: =SUM(P38:S38) -> 20 | R38: 20 | U38: =SUM(V38:Y38) -> 0
A39: 1001110128 | B39: Bộ lọc thô 2 stages LALANKA | C39: Prefilter2S10" | D39: Máy TCM Sx | E39: Bộ lọc thô | F39: XK | H39: 230474.16 | I39: =SUM(J39:M39) -> 0 | J39: =P39+V39 -> 0 | K39: =Q39+W39 -> 0 | L39: =R39+X39 -> 0 | M39: =S39+Y39 -> 0 | O39: =SUM(P39:S39) -> 0 | U39: =SUM(V39:Y39) -> 0
A40: 1001110129 | B40: Bộ lọc thô 3 stages LALANKA | C40: Prefilter3S10" | D40: Máy TCM Sx | E40: Bộ lọc thô | F40: XK | H40: 358866.15 | I40: =SUM(J40:M40) -> 0 | J40: =P40+V40 -> 0 | K40: =Q40+W40 -> 0 | L40: =R40+X40 -> 0 | M40: =S40+Y40 -> 0 | O40: =SUM(P40:S40) -> 0 | U40: =SUM(V40:Y40) -> 0
A41: 1001110132 | B41: Máy RO-30 MAXPURE | C41: RO-30 | D41: Máy TCM Sx | E41: 10L | F41: XK | H41: 1447040.9 | I41: =SUM(J41:M41) -> 500 | J41: =P41+V41 -> 0 | K41: =Q41+W41 -> 0 | L41: =R41+X41 -> 500 | M41: =S41+Y41 -> 0 | O41: =SUM(P41:S41) -> 500 | R41: 500 | U41: =SUM(V41:Y41) -> 0
A42: 1001110139 | B42: Máy lọc nước UNDERSINK AQUA PURE (7S) | C42: S-S027 | D42: Máy TCM Sx | E42: 10L | F42: XK | H42: 2630983.5 | I42: =SUM(J42:M42) -> 0 | J42: =P42+V42 -> 0 | K42: =Q42+W42 -> 0 | L42: =R42+X42 -> 0 | M42: =S42+Y42 -> 0 | O42: =SUM(P42:S42) -> 0 | U42: =SUM(V42:Y42) -> 0
A43: 1001110151 | B43: Máy BCN-200 GPD Karofi (NATURAL) | C43: BCN-200 | D43: Máy TCM Sx | E43: BCN | F43: XK | H43: 4612991.1 | I43: =SUM(J43:M43) -> 0 | J43: =P43+V43 -> 0 | K43: =Q43+W43 -> 0 | L43: =R43+X43 -> 0 | M43: =S43+Y43 -> 0 | O43: =SUM(P43:S43) -> 0 | U43: =SUM(V43:Y43) -> 0
A44: 1001110152 | B44: Máy BCN-300 GPD Karofi (NATURAL) | C44: BCN-300 | D44: Máy TCM Sx | E44: BCN | F44: XK | H44: 5426403.5 | I44: =SUM(J44:M44) -> 150 | J44: =P44+V44 -> 0 | K44: =Q44+W44 -> 0 | L44: =R44+X44 -> 0 | M44: =S44+Y44 -> 150 | O44: =SUM(P44:S44) -> 150 | S44: 150 | U44: =SUM(V44:Y44) -> 0
A45: 1001110153 | B45: Máy BCN-400 GPD Karofi (NATURAL) | C45: BCN-400 | D45: Máy TCM Sx | E45: BCN | F45: XK | H45: 5867093.2 | I45: =SUM(J45:M45) -> 20 | J45: =P45+V45 -> 0 | K45: =Q45+W45 -> 0 | L45: =R45+X45 -> 20 | M45: =S45+Y45 -> 0 | O45: =SUM(P45:S45) -> 20 | R45: 20 | U45: =SUM(V45:Y45) -> 0
A46: 1001110156 | B46: Máy BCN-400 GPD Tecomen | C46: BCN-400 | D46: Máy TCM Sx | E46: BCN | F46: XK | H46: 6850818 | I46: =SUM(J46:M46) -> 50 | J46: =P46+V46 -> 0 | K46: =Q46+W46 -> 0 | L46: =R46+X46 -> 0 | M46: =S46+Y46 -> 50 | O46: =SUM(P46:S46) -> 50 | S46: 50 | U46: =SUM(V46:Y46) -> 0
A47: 1001110167 | B47: Máy RO-30 Karofi (6S) | C47: RO-30 | D47: Máy TCM Sx | E47: 10L | F47: XK | H47: 1513867.9 | I47: =SUM(J47:M47) -> 100 | J47: =P47+V47 -> 0 | K47: =Q47+W47 -> 0 | L47: =R47+X47 -> 100 | M47: =S47+Y47 -> 0 | O47: =SUM(P47:S47) -> 100 | R47: 100 | U47: =SUM(V47:Y47) -> 0
A48: 1001110210 | B48: Máy RO-200 GPD BLUE LEAF (5S) | C48: BCN-200 | D48: Máy TCM Sx | E48: BCN | F48: XK | H48: 3709686.7 | I48: =SUM(J48:M48) -> 20 | J48: =P48+V48 -> 0 | K48: =Q48+W48 -> 0 | L48: =R48+X48 -> 0 | M48: =S48+Y48 -> 20 | O48: =SUM(P48:S48) -> 20 | S48: 20 | U48: =SUM(V48:Y48) -> 0
A49: 1001110220 | B49: Máy RO-406 Karofi (5S) V2 | C49: RO-406 | D49: Máy TCM Sx | E49: 10L | F49: XK | H49: 1052393.4 | I49: =SUM(J49:M49) -> 0 | J49: =P49+V49 -> 0 | K49: =Q49+W49 -> 0 | L49: =R49+X49 -> 0 | M49: =S49+Y49 -> 0 | O49: =SUM(P49:S49) -> 0 | U49: =SUM(V49:Y49) -> 0
A50: 1001110223 | B50: Máy lọc nước WATERNESS Slim S-s038 | C50: S-S038 | D50: Máy TCM Sx | E50: 10L | F50: XK | H50: 1815378.6 | I50: =SUM(J50:M50) -> 0 | J50: =P50+V50 -> 0 | K50: =Q50+W50 -> 0 | L50: =R50+X50 -> 0 | M50: =S50+Y50 -> 0 | O50: =SUM(P50:S50) -> 0 | U50: =SUM(V50:Y50) -> 0
A51: 1001110229 | B51: Máy LN NL DIAMOND HYDRO-SENSIA S9 | C51: SensiaS9 | D51: Máy TCM Sx | E51: Block | F51: XK | H51: 13121504 | I51: =SUM(J51:M51) -> 0 | J51: =P51+V51 -> 0 | K51: =Q51+W51 -> 0 | L51: =R51+X51 -> 0 | M51: =S51+Y51 -> 0 | O51: =SUM(P51:S51) -> 0 | U51: =SUM(V51:Y51) -> 0
A52: 1001110245 | B52: Máy RO-30 AQUA QUALITY (7S) | C52: RO-30 | D52: Máy TCM Sx | E52: 10L | F52: XK | H52: 1052393.4 | I52: =SUM(J52:M52) -> 400 | J52: =P52+V52 -> 0 | K52: =Q52+W52 -> 0 | L52: =R52+X52 -> 0 | M52: =S52+Y52 -> 400 | O52: =SUM(P52:S52) -> 400 | S52: 400 | U52: =SUM(V52:Y52) -> 0
A53: 1001110246 | B53: Máy RO-100 Tecomen V2 (7S) | C53: RO-100 | D53: Máy TCM Sx | E53: 10L | F53: XK | H53: 1488610.5 | I53: =SUM(J53:M53) -> 500 | J53: =P53+V53 -> 500 | K53: =Q53+W53 -> 0 | L53: =R53+X53 -> 0 | M53: =S53+Y53 -> 0 | O53: =SUM(P53:S53) -> 500 | P53: 500 | U53: =SUM(V53:Y53) -> 0
A54: 1001110248 | B54: Máy RO-400 GPD BLUE LEAF (5S) | C54: BCN-400 | D54: Máy TCM Sx | E54: BCN | F54: XK | H54: 5393516.2 | I54: =SUM(J54:M54) -> 10 | J54: =P54+V54 -> 0 | K54: =Q54+W54 -> 0 | L54: =R54+X54 -> 0 | M54: =S54+Y54 -> 10 | O54: =SUM(P54:S54) -> 10 | S54: 10 | U54: =SUM(V54:Y54) -> 0
A55: 1001110249 | B55: Máy RO-35 HYDRO10 | C55: RO-35 | D55: Máy TCM Sx | E55: 10L | F55: XK | H55: 1723294.2 | I55: =SUM(J55:M55) -> 100 | J55: =P55+V55 -> 0 | K55: =Q55+W55 -> 100 | L55: =R55+X55 -> 0 | M55: =S55+Y55 -> 0 | O55: =SUM(P55:S55) -> 100 | Q55: 100 | U55: =SUM(V55:Y55) -> 0
A56: 1001110259 | B56: Máy lọc nước nóng lạnh KAD-X58 (Anh) | C56: KAD-X58 | D56: Máy TCM Sx | E56: Block | F56: XK | H56: 4343753.8 | I56: =SUM(J56:M56) -> 330 | J56: =P56+V56 -> 0 | K56: =Q56+W56 -> 330 | L56: =R56+X56 -> 0 | M56: =S56+Y56 -> 0 | O56: =SUM(P56:S56) -> 330 | Q56: 330 | U56: =SUM(V56:Y56) -> 0
A57: 1001110261 | B57: Máy RO-103 Livotec (6S) | C57: RO-103 | D57: Máy TCM Sx | E57: 10L | F57: XK | H57: 1514657.2 | I57: =SUM(J57:M57) -> 200 | J57: =P57+V57 -> 0 | K57: =Q57+W57 -> 0 | L57: =R57+X57 -> 200 | M57: =S57+Y57 -> 0 | O57: =SUM(P57:S57) -> 200 | R57: 200 | U57: =SUM(V57:Y57) -> 0
A58: 1001110282 | B58: Bộ lọc thô 1 stage Karofi (Anh) | C58: Prefilter1S10" | D58: Máy TCM Sx | E58: Bộ lọc thô | F58: XK | H58: 122077.63 | I58: =SUM(J58:M58) -> 108 | J58: =P58+V58 -> 108 | K58: =Q58+W58 -> 0 | L58: =R58+X58 -> 0 | M58: =S58+Y58 -> 0 | O58: =SUM(P58:S58) -> 108 | P58: 108 | U58: =SUM(V58:Y58) -> 0
A59: 1001110290 | B59: Máy RO-406 AMI | C59: RO-406 | D59: Máy TCM Sx | E59: 10L | F59: XK | H59: 901111.85 | I59: =SUM(J59:M59) -> 5 | J59: =P59+V59 -> 0 | K59: =Q59+W59 -> 5 | L59: =R59+X59 -> 0 | M59: =S59+Y59 -> 0 | O59: =SUM(P59:S59) -> 5 | Q59: 5 | U59: =SUM(V59:Y59) -> 0
A60: 1001110326 | B60: Máy RO-04 ANMAX (7S) v2 | C60: RO-04 | D60: Máy TCM Sx | E60: 10L | F60: XK | H60: 919528.74 | I60: =SUM(J60:M60) -> 116 | J60: =P60+V60 -> 116 | K60: =Q60+W60 -> 0 | L60: =R60+X60 -> 0 | M60: =S60+Y60 -> 0 | O60: =SUM(P60:S60) -> 116 | P60: 116 | U60: =SUM(V60:Y60) -> 0
A61: 1001110339 | B61: Máy RO Undersink US v2 | C61: UDSUS | D61: Máy TCM Sx | E61: 10L | F61: XK | H61: 1573328.1 | I61: =SUM(J61:M61) -> 755 | J61: =P61+V61 -> 0 | K61: =Q61+W61 -> 0 | L61: =R61+X61 -> 755 | M61: =S61+Y61 -> 0 | O61: =SUM(P61:S61) -> 755 | R61: 755 | U61: =SUM(V61:Y61) -> 0
A62: 1001110340 | B62: Bộ lọc thô 3 stages 20'' BLUE LEAF | C62: Prefilter3SJumbo | D62: Máy TCM Sx | E62: Bộ lọc thô | F62: XK | H62: 2236336 | I62: =SUM(J62:M62) -> 40 | J62: =P62+V62 -> 0 | K62: =Q62+W62 -> 0 | L62: =R62+X62 -> 40 | M62: =S62+Y62 -> 0 | O62: =SUM(P62:S62) -> 40 | R62: 40 | U62: =SUM(V62:Y62) -> 0
A63: 1001110349 | B63: Bộ lọc thô 3 stages Karofi (Anh) | C63: Prefilter3S10" | D63: Máy TCM Sx | E63: Bộ lọc thô | F63: XK | H63: 384123.59 | I63: =SUM(J63:M63) -> 51 | J63: =P63+V63 -> 51 | K63: =Q63+W63 -> 0 | L63: =R63+X63 -> 0 | M63: =S63+Y63 -> 0 | O63: =SUM(P63:S63) -> 51 | P63: 51 | U63: =SUM(V63:Y63) -> 0
A64: 1001110350 | B64: Máy lọc nước Karofi KAQ-U05 (Anh) v2 | C64: KAQ-U05 | D64: Máy TCM Sx | E64: 10L | F64: XK | H64: 2195630.9 | I64: =SUM(J64:M64) -> 355 | J64: =P64+V64 -> 0 | K64: =Q64+W64 -> 85 | L64: =R64+X64 -> 270 | M64: =S64+Y64 -> 0 | O64: =SUM(P64:S64) -> 355 | Q64: 85 | R64: 270 | U64: =SUM(V64:Y64) -> 0
A65: 1001110354 | B65: Máy lọc nước nóng lạnh Karofi KAD-N69 (Anh) | C65: KAD-N69 | D65: Máy TCM Sx | E65: Block | F65: XK | H65: 5763394.9 | I65: =SUM(J65:M65) -> 50 | J65: =P65+V65 -> 0 | K65: =Q65+W65 -> 0 | L65: =R65+X65 -> 50 | M65: =S65+Y65 -> 0 | O65: =SUM(P65:S65) -> 50 | R65: 50 | U65: =SUM(V65:Y65) -> 0
A66: 1001110364 | B66: Máy lọc nước RO-410 KAROFI (Anh) | C66: RO-410 | D66: Máy TCM Sx | E66: 10L | F66: XK | H66: 1857299 | I66: =SUM(J66:M66) -> 400 | J66: =P66+V66 -> 300 | K66: =Q66+W66 -> 100 | L66: =R66+X66 -> 0 | M66: =S66+Y66 -> 0 | O66: =SUM(P66:S66) -> 400 | P66: 300 | Q66: 100 | U66: =SUM(V66:Y66) -> 0
A67: 1001110365 | B67: Máy lọc nước RO-01 POWER MAX (7S) | C67: RO-01 | D67: Máy TCM Sx | E67: 10L | F67: XK | H67: 1289181.9 | I67: =SUM(J67:M67) -> 300 | J67: =P67+V67 -> 0 | K67: =Q67+W67 -> 300 | L67: =R67+X67 -> 0 | M67: =S67+Y67 -> 0 | O67: =SUM(P67:S67) -> 300 | Q67: 300 | U67: =SUM(V67:Y67) -> 0
A68: 1001110378 | B68: Máy lọc nước UNDERSINK đen AL-SAQAF (5S) | C68: S-S027 | D68: Máy TCM Sx | E68: 10L | F68: XK | H68: 2673474 | I68: =SUM(J68:M68) -> 0 | J68: =P68+V68 -> 0 | K68: =Q68+W68 -> 0 | L68: =R68+X68 -> 0 | M68: =S68+Y68 -> 0 | O68: =SUM(P68:S68) -> 0 | U68: =SUM(V68:Y68) -> 0
A69: 1001110381 | B69: Máy lọc nước RO-30 KAROFI (WCSA) | C69: RO-30 | D69: Máy TCM Sx | E69: 10L | F69: XK | H69: 1604899.9 | I69: =SUM(J69:M69) -> 0 | J69: =P69+V69 -> 0 | K69: =Q69+W69 -> 0 | L69: =R69+X69 -> 0 | M69: =S69+Y69 -> 0 | O69: =SUM(P69:S69) -> 0 | U69: =SUM(V69:Y69) -> 0
A70: 1001110383 | B70: Máy RO-401 Water Tec (7S) | C70: RO-401 | D70: Máy TCM Sx | E70: 10L | F70: XK | H70: 1593937.5 | I70: =SUM(J70:M70) -> 0 | J70: =P70+V70 -> 0 | K70: =Q70+W70 -> 0 | L70: =R70+X70 -> 0 | M70: =S70+Y70 -> 0 | O70: =SUM(P70:S70) -> 0 | U70: =SUM(V70:Y70) -> 0
A71: 1001110390 | B71: Máy lọc nước RO BCN-200 NQAA ALMAA | C71: BCN-200 | D71: Máy TCM Sx | E71: BCN | F71: XK | H71: 3441326.4 | I71: =SUM(J71:M71) -> 0 | J71: =P71+V71 -> 0 | K71: =Q71+W71 -> 0 | L71: =R71+X71 -> 0 | M71: =S71+Y71 -> 0 | O71: =SUM(P71:S71) -> 0 | U71: =SUM(V71:Y71) -> 0
A72: 1001110394 | B72: Máy nóng lạnh KAROFI HCV208-RO (Anh) | C72: HCV-208RO | D72: Máy TCM Sx | E72: Block | F72: XK | H72: 3870933.2 | I72: =SUM(J72:M72) -> 70 | J72: =P72+V72 -> 70 | K72: =Q72+W72 -> 0 | L72: =R72+X72 -> 0 | M72: =S72+Y72 -> 0 | O72: =SUM(P72:S72) -> 70 | P72: 70 | U72: =SUM(V72:Y72) -> 0
A73: 1001110397 | B73: Máy RO RO-104 TECOMEN | C73: RO-104 | D73: Máy TCM Sx | E73: 10L | F73: XK | H73: 1236562.2 | I73: =SUM(J73:M73) -> 0 | J73: =P73+V73 -> 0 | K73: =Q73+W73 -> 0 | L73: =R73+X73 -> 0 | M73: =S73+Y73 -> 0 | O73: =SUM(P73:S73) -> 0 | U73: =SUM(V73:Y73) -> 0
A74: 1001110415 | B74: Máy lọc nước RO-406 NO-BRAND | C74: RO-406 | D74: Máy TCM Sx | E74: 10L | F74: XK | H74: 1194466.5 | I74: =SUM(J74:M74) -> 0 | J74: =P74+V74 -> 0 | K74: =Q74+W74 -> 0 | L74: =R74+X74 -> 0 | M74: =S74+Y74 -> 0 | O74: =SUM(P74:S74) -> 0 | U74: =SUM(V74:Y74) -> 0
A75: 1001110416 | B75: Máy RO S-s04 LEFAY | C75: KAQ-U05 | D75: Máy TCM Sx | E75: 10L | F75: XK | H75: 1611477.4 | I75: =SUM(J75:M75) -> 0 | J75: =P75+V75 -> 0 | K75: =Q75+W75 -> 0 | L75: =R75+X75 -> 0 | M75: =S75+Y75 -> 0 | O75: =SUM(P75:S75) -> 0 | U75: =SUM(V75:Y75) -> 0
A76: 1001110419 | B76: Máy lọc nước RO-107 AQUA GOLD - PRO | C76: RO-107 | D76: Máy TCM Sx | E76: 10L | F76: XK | H76: 1217769.5 | I76: =SUM(J76:M76) -> 1700 | J76: =P76+V76 -> 500 | K76: =Q76+W76 -> 0 | L76: =R76+X76 -> 0 | M76: =S76+Y76 -> 1200 | O76: =SUM(P76:S76) -> 1700 | P76: 500 | S76: 1200 | U76: =SUM(V76:Y76) -> 0
A77: 1001110428 | B77: Máy lọc nước RO-404 KAROFI (8S) v2 | C77: RO-404 | D77: Máy TCM Sx | E77: 10L | F77: XK | H77: 1951268.9 | I77: =SUM(J77:M77) -> 0 | J77: =P77+V77 -> 0 | K77: =Q77+W77 -> 0 | L77: =R77+X77 -> 0 | M77: =S77+Y77 -> 0 | O77: =SUM(P77:S77) -> 0 | U77: =SUM(V77:Y77) -> 0
A78: 1001110429 | B78: Máy lọc nước KAROFI KAQ-X16 (Anh) | C78: KAQ-X16 | D78: Máy TCM Sx | E78: 10L Tủ | F78: XK | H78: 2569155.4 | I78: =SUM(J78:M78) -> 0 | J78: =P78+V78 -> 0 | K78: =Q78+W78 -> 0 | L78: =R78+X78 -> 0 | M78: =S78+Y78 -> 0 | O78: =SUM(P78:S78) -> 0 | U78: =SUM(V78:Y78) -> 0
A79: 1001110432 | B79: Máy lọc nước RO-100 BRAFCO (7S) | C79: RO-100 | D79: Máy TCM Sx | E79: 10L | F79: XK | H79: 1657914.3 | I79: =SUM(J79:M79) -> 950 | J79: =P79+V79 -> 0 | K79: =Q79+W79 -> 800 | L79: =R79+X79 -> 150 | M79: =S79+Y79 -> 0 | O79: =SUM(P79:S79) -> 950 | Q79: 800 | R79: 150 | U79: =SUM(V79:Y79) -> 0
A80: 1001110434 | B80: Máy lọc nước RO-01/023 BRAFCO (7S) | C80: RO-01 | D80: Máy TCM Sx | E80: 10L | F80: XK | H80: 1532986.4 | I80: =SUM(J80:M80) -> 1150 | J80: =P80+V80 -> 0 | K80: =Q80+W80 -> 850 | L80: =R80+X80 -> 300 | M80: =S80+Y80 -> 0 | O80: =SUM(P80:S80) -> 1150 | Q80: 850 | R80: 300 | U80: =SUM(V80:Y80) -> 0
A81: 1001110449 | B81: Máy RO-100 LIYAV | C81: RO-100 | D81: Máy TCM Sx | E81: 10L | F81: XK | H81: 1610161.9 | I81: =SUM(J81:M81) -> 0 | J81: =P81+V81 -> 0 | K81: =Q81+W81 -> 0 | L81: =R81+X81 -> 0 | M81: =S81+Y81 -> 0 | O81: =SUM(P81:S81) -> 0 | U81: =SUM(V81:Y81) -> 0
A82: 1001110450 | B82: Máy lọc nước RO-01 PURE TOUCH (6S) | C82: RO-01 | D82: Máy TCM Sx | E82: 10L | F82: XK | H82: 1354956.5 | I82: =SUM(J82:M82) -> 395 | J82: =P82+V82 -> 0 | K82: =Q82+W82 -> 395 | L82: =R82+X82 -> 0 | M82: =S82+Y82 -> 0 | O82: =SUM(P82:S82) -> 395 | Q82: 395 | U82: =SUM(V82:Y82) -> 0
A83: 1001110453 | B83: Máy RO-01 HYDRO (7S) | C83: RO-01 | D83: Máy TCM Sx | E83: 10L | F83: XK | H83: 1424589.9 | I83: =SUM(J83:M83) -> 120 | J83: =P83+V83 -> 120 | K83: =Q83+W83 -> 0 | L83: =R83+X83 -> 0 | M83: =S83+Y83 -> 0 | O83: =SUM(P83:S83) -> 120 | P83: 120 | U83: =SUM(V83:Y83) -> 0
A84: 1001110454 | B84: Máy lọc nước RO-401 HYDRO (7S) | C84: RO-401 | D84: Máy TCM Sx | E84: 10L | F84: XK | H84: 1516469.7 | I84: =SUM(J84:M84) -> 340 | J84: =P84+V84 -> 340 | K84: =Q84+W84 -> 0 | L84: =R84+X84 -> 0 | M84: =S84+Y84 -> 0 | O84: =SUM(P84:S84) -> 340 | P84: 340 | U84: =SUM(V84:Y84) -> 0
A85: 1001110463 | B85: Máy lọc nước KAROFI Slim S-s038 Brills | C85: S-S038 | D85: Máy TCM Sx | E85: 10L | F85: XK | H85: 2012025.8 | I85: =SUM(J85:M85) -> 93 | J85: =P85+V85 -> 0 | K85: =Q85+W85 -> 23 | L85: =R85+X85 -> 70 | M85: =S85+Y85 -> 0 | O85: =SUM(P85:S85) -> 93 | Q85: 23 | R85: 70 | U85: =SUM(V85:Y85) -> 0
A86: 1001110466 | B86: Máy lọc nước NL KAROFI KAD-D66V Brills | C86: KAD-D66S | D86: Máy TCM Sx | E86: Block | F86: XK | H86: 4663886 | I86: =SUM(J86:M86) -> 70 | J86: =P86+V86 -> 0 | K86: =Q86+W86 -> 0 | L86: =R86+X86 -> 70 | M86: =S86+Y86 -> 0 | O86: =SUM(P86:S86) -> 70 | R86: 70 | U86: =SUM(V86:Y86) -> 0
A87: 1001110467 | B87: Máy lọc nước NL KAROFI KAD-L56 Brills | C87: KAD-L56 | D87: Máy TCM Sx | E87: Block | F87: XK | H87: 4452518.6 | I87: =SUM(J87:M87) -> 0 | J87: =P87+V87 -> 0 | K87: =Q87+W87 -> 0 | L87: =R87+X87 -> 0 | M87: =S87+Y87 -> 0 | O87: =SUM(P87:S87) -> 0 | U87: =SUM(V87:Y87) -> 0
A88: 1001110472 | B88: Bộ lọc thô 3 stages 20" NQAA ALMAA | C88: Prefilter3SJumbo | D88: Máy TCM Sx | E88: Bộ lọc thô | F88: XK | H88: 2025857.3 | I88: =SUM(J88:M88) -> 0 | J88: =P88+V88 -> 0 | K88: =Q88+W88 -> 0 | L88: =R88+X88 -> 0 | M88: =S88+Y88 -> 0 | O88: =SUM(P88:S88) -> 0 | U88: =SUM(V88:Y88) -> 0
A89: 1001110478 | B89: Máy lọc nước RO-401 POWER MAX 8S | C89: RO-401 | D89: Máy TCM Sx | E89: 10L | F89: XK | H89: 1486505.7 | I89: =SUM(J89:M89) -> 600 | J89: =P89+V89 -> 0 | K89: =Q89+W89 -> 600 | L89: =R89+X89 -> 0 | M89: =S89+Y89 -> 0 | O89: =SUM(P89:S89) -> 600 | Q89: 600 | U89: =SUM(V89:Y89) -> 0
A90: 1001110484 | B90: Máy RO-30 Hitek (6S) | C90: RO-30 | D90: Máy TCM Sx | E90: 10L | F90: XK | H90: 1409417.9 | I90: =SUM(J90:M90) -> 450 | J90: =P90+V90 -> 200 | K90: =Q90+W90 -> 0 | L90: =R90+X90 -> 250 | M90: =S90+Y90 -> 0 | O90: =SUM(P90:S90) -> 450 | P90: 200 | R90: 250 | U90: =SUM(V90:Y90) -> 0
A91: 1001110485 | B91: Máy RO-104 Hitek (6S) | C91: RO-104 | D91: Máy TCM Sx | E91: 10L | F91: XK | H91: 1514657.2 | I91: =SUM(J91:M91) -> 200 | J91: =P91+V91 -> 200 | K91: =Q91+W91 -> 0 | L91: =R91+X91 -> 0 | M91: =S91+Y91 -> 0 | O91: =SUM(P91:S91) -> 200 | P91: 200 | U91: =SUM(V91:Y91) -> 0
A92: 1001110493 | B92: Máy lọc nước RO-40 HEALTHY PURE (7S | C92: RO-40 | D92: Máy TCM Sx | E92: 10L | F92: XK | H92: 1602269 | I92: =SUM(J92:M92) -> 500 | J92: =P92+V92 -> 0 | K92: =Q92+W92 -> 0 | L92: =R92+X92 -> 500 | M92: =S92+Y92 -> 0 | O92: =SUM(P92:S92) -> 500 | R92: 500 | U92: =SUM(V92:Y92) -> 0
A93: 1001110494 | B93: Máy lọc nước RO-109 HEALTHY PURE (7S) | C93: RO-109 | D93: Máy TCM Sx | E93: 10L | F93: XK | H93: 1904832.1 | I93: =SUM(J93:M93) -> 200 | J93: =P93+V93 -> 0 | K93: =Q93+W93 -> 0 | L93: =R93+X93 -> 200 | M93: =S93+Y93 -> 0 | O93: =SUM(P93:S93) -> 200 | R93: 200 | U93: =SUM(V93:Y93) -> 0
A94: 1001110495 | B94: Máy lọc nước RO-01 WATER MASTER (7S) | C94: RO-01 | D94: Máy TCM Sx | E94: 10L | F94: XK | H94: 1289181.9 | I94: =SUM(J94:M94) -> 200 | J94: =P94+V94 -> 0 | K94: =Q94+W94 -> 200 | L94: =R94+X94 -> 0 | M94: =S94+Y94 -> 0 | O94: =SUM(P94:S94) -> 200 | Q94: 200 | U94: =SUM(V94:Y94) -> 0
A95: 1001110502 | B95: Máy lọc nước RO-01 AQUA STAR (7S) | C95: RO-01 | D95: Máy TCM Sx | E95: 10L | F95: XK | H95: 1315491.8 | I95: =SUM(J95:M95) -> 7 | J95: =P95+V95 -> 7 | K95: =Q95+W95 -> 0 | L95: =R95+X95 -> 0 | M95: =S95+Y95 -> 0 | O95: =SUM(P95:S95) -> 7 | P95: 7 | U95: =SUM(V95:Y95) -> 0
A96: 1001110503 | B96: Máy lọc nước RO-01 WTR | C96: RO-01 | D96: Máy TCM Sx | E96: 10L | F96: XK | H96: 920844.23 | I96: =SUM(J96:M96) -> 700 | J96: =P96+V96 -> 0 | K96: =Q96+W96 -> 0 | L96: =R96+X96 -> 700 | M96: =S96+Y96 -> 0 | O96: =SUM(P96:S96) -> 700 | R96: 700 | U96: =SUM(V96:Y96) -> 0
A97: 1001110509 | B97: Máy lọc nước U05 Pro AQ | C97: KAQ-U05 Pro | D97: Máy TCM Sx | E97: 10L | F97: XK | H97: 1578590.1 | I97: =SUM(J97:M97) -> 3 | J97: =P97+V97 -> 0 | K97: =Q97+W97 -> 3 | L97: =R97+X97 -> 0 | M97: =S97+Y97 -> 0 | O97: =SUM(P97:S97) -> 3 | Q97: 3 | U97: =SUM(V97:Y97) -> 0
A98: 1001110520 | B98: Máy lọc nước RO-38 AQUA GOLD-PRIME (7S) | C98: RO-38 | D98: Máy TCM Sx | E98: 10L | F98: XK | H98: 1204990.4 | I98: =SUM(J98:M98) -> 700 | J98: =P98+V98 -> 0 | K98: =Q98+W98 -> 0 | L98: =R98+X98 -> 0 | M98: =S98+Y98 -> 700 | O98: =SUM(P98:S98) -> 700 | S98: 700 | U98: =SUM(V98:Y98) -> 0
A99: 1001110521 | B99: Máy RO-01 KAROFI ECO | C99: RO-01 | D99: Máy TCM Sx | E99: 10L | F99: XK | H99: 1504922.6 | I99: =SUM(J99:M99) -> 525 | J99: =P99+V99 -> 0 | K99: =Q99+W99 -> 310 | L99: =R99+X99 -> 215 | M99: =S99+Y99 -> 0 | O99: =SUM(P99:S99) -> 525 | Q99: 310 | R99: 215 | U99: =SUM(V99:Y99) -> 0
A100: 1001110523 | B100: Máy lọc nước RO-411 BRONZNET (7S) | C100: RO-411 | D100: Máy TCM Sx | E100: 10L | F100: XK | H100: 1590604.9 | I100: =SUM(J100:M100) -> 400 | J100: =P100+V100 -> 0 | K100: =Q100+W100 -> 0 | L100: =R100+X100 -> 0 | M100: =S100+Y100 -> 400 | O100: =SUM(P100:S100) -> 400 | S100: 400 | U100: =SUM(V100:Y100) -> 0
...

Sheet B0.4.OEM
A1: BẢNG 0.4: | B1: SALES FORECAST - KÊNH OEM | I1: =I10 -> Tổng FC | O1: Miền Bắc | U1: Miền Nam
I2: TỔNG | J2: =J10 -> Tháng 7 | K2: =K10 -> Tháng 8 | L2: =L10 -> Tháng 9 | M2: =M10 -> Tháng 10
G3: NHÓM 1 | H3: Máy TCM sx | I3: =SUM(J3:M3) -> 5860 | J3: =SUMIF($D$11:$D$403,$H3,J$11:J$403) -> 1430 | K3: =SUMIF($D$11:$D$403,$H3,K$11:K$403) -> 1310 | L3: =SUMIF($D$11:$D$403,$H3,L$11:L$403) -> 1460 | M3: =SUMIF($D$11:$D$403,$H3,M$11:M$403) -> 1660
G4: NHÓM 2 | H4: Máy nhập khẩu | I4: =SUM(J4:M4) -> 0 | J4: =SUMIF($D$11:$D$403,$H4,J$11:J$403) -> 0 | K4: =SUMIF($D$11:$D$403,$H4,K$11:K$403) -> 0 | L4: =SUMIF($D$11:$D$403,$H4,L$11:L$403) -> 0 | M4: =SUMIF($D$11:$D$403,$H4,M$11:M$403) -> 0
G5: NHÓM 3 | H5: Mockup | I5: =SUM(J5:M5) -> 0 | J5: =SUMIF($D$11:$D$403,$H5,J$11:J$403) -> 0 | K5: =SUMIF($D$11:$D$403,$H5,K$11:K$403) -> 0 | L5: =SUMIF($D$11:$D$403,$H5,L$11:L$403) -> 0 | M5: =SUMIF($D$11:$D$403,$H5,M$11:M$403) -> 0
G6: NHÓM 4 | H6: Lõi | I6: =SUM(J6:M6) -> 0 | J6: =SUMIF($D$11:$D$403,$H6,J$11:J$403) -> 0 | K6: =SUMIF($D$11:$D$403,$H6,K$11:K$403) -> 0 | L6: =SUMIF($D$11:$D$403,$H6,L$11:L$403) -> 0 | M6: =SUMIF($D$11:$D$403,$H6,M$11:M$403) -> 0
G7: NHÓM 5 | H7: Màng | I7: =SUM(J7:M7) -> 0 | J7: =SUMIF($D$11:$D$403,$H7,J$11:J$403) -> 0 | K7: =SUMIF($D$11:$D$403,$H7,K$11:K$403) -> 0 | L7: =SUMIF($D$11:$D$403,$H7,L$11:L$403) -> 0 | M7: =SUMIF($D$11:$D$403,$H7,M$11:M$403) -> 0
A8: Ngày update | B8: ='B0.SUM (tuần 0)'!B3 -> 46204
I9: =SUBTOTAL(9,I11:I1403) -> 2208280 | J9: =SUBTOTAL(9,J11:J1403) -> 547285 | K9: =SUBTOTAL(9,K11:K1403) -> 543665 | L9: =SUBTOTAL(9,L11:L1403) -> 558315 | M9: =SUBTOTAL(9,M11:M1403) -> 559015 | O9: =SUBTOTAL(9,O11:O473) -> 2208280 | P9: =SUBTOTAL(9,P11:P473) -> 547285 | Q9: =SUBTOTAL(9,Q11:Q473) -> 543665 | R9: =SUBTOTAL(9,R11:R473) -> 558315 | S9: =SUBTOTAL(9,S11:S473) -> 559015 | T9: =SUBTOTAL(9,T11:T473) -> 0 | U9: =SUBTOTAL(9,U11:U473) -> 0 | V9: =SUBTOTAL(9,V11:V473) -> 0 | ... Y9: =SUBTOTAL(9,Y11:Y473) -> 0
A10: Mã sản phẩm | B10: Tên sản phẩm | C10: Model (tên gọi tắt) | D10: Nhóm | E10: Công nghệ chính | F10: Channel | G10: Độc quyền | H10: Giá ghi nhận doanh thu | I10: Tổng FC | J10: ="Tháng"&" "&IF(DAY($B$8)<22,MONTH($B$8),MONTH($B$8)+1) -> Tháng 7 | K10: ="Tháng"&" "&RIGHT(J10,2)+1 -> Tháng 8 | L10: ="Tháng"&" "&RIGHT(K10,2)+1 -> Tháng 9 | M10: ="Tháng"&" "&RIGHT(L10,1)+1 -> Tháng 10 | O10: Tổng FC | P10: =J10 -> Tháng 7 | Q10: =K10 -> Tháng 8 | R10: =L10 -> Tháng 9 | S10: =M10 -> Tháng 10 | U10: Tổng FC | V10: =J10 -> Tháng 7 | W10: =K10 -> Tháng 8 | X10: =L10 -> Tháng 9 | Y10: =M10 -> Tháng 10
A11: 1001050026 | B11: Máy RO-01/001 (CTNASACO.02) | C11: PC | D11: Máy TCM sx | E11: 10L | F11: OEM | G11: Nasaco | H11: 1800000 | I11: =SUM(J11:M11) -> 0 | J11: =P11+V11 -> 0 | K11: =Q11+W11 -> 0 | L11: =R11+X11 -> 0 | M11: =S11+Y11 -> 0 | O11: =SUM(P11:S11) -> 0 | U11: =SUM(V11:Y11) -> 0
A12: 1001050029 | B12: Máy RO-01/001 (CTQUOCTE.01) | C12: PC | D12: Máy TCM sx | E12: 10L | F12: OEM | G12: Quốc Tế | H12: 1800000 | I12: =SUM(J12:M12) -> 0 | J12: =P12+V12 -> 0 | K12: =Q12+W12 -> 0 | L12: =R12+X12 -> 0 | M12: =S12+Y12 -> 0 | O12: =SUM(P12:S12) -> 0 | U12: =SUM(V12:Y12) -> 0
A13: 1001050033 | B13: Máy RO-01/001 (CTVUTRU.01) | C13: PC | D13: Máy TCM sx | E13: 10L | F13: OEM | G13: Vũ Trụ | H13: 1800000 | I13: =SUM(J13:M13) -> 500 | J13: =P13+V13 -> 100 | K13: =Q13+W13 -> 100 | L13: =R13+X13 -> 150 | M13: =S13+Y13 -> 150 | O13: =SUM(P13:S13) -> 500 | P13: 100 | Q13: 100 | R13: 150 | S13: 150 | U13: =SUM(V13:Y13) -> 0
A14: 1001050061 | B14: Máy RO-01/016 (CHHOAHM.01) | C14: PC | D14: Máy TCM sx | E14: 10L | F14: OEM | G14: Hoa HM | H14: 1800000 | I14: =SUM(J14:M14) -> 200 | J14: =P14+V14 -> 50 | K14: =Q14+W14 -> 50 | L14: =R14+X14 -> 50 | M14: =S14+Y14 -> 50 | O14: =SUM(P14:S14) -> 200 | P14: 50 | Q14: 50 | R14: 50 | S14: 50 | U14: =SUM(V14:Y14) -> 0
A15: 1001050100 | B15: Máy RO-05/028 (CHGIANGSANG.02) | C15: PC | D15: Máy TCM sx | E15: 10L | F15: OEM | G15: Giang Sáng | H15: 1470700 | I15: =SUM(J15:M15) -> 50 | J15: =P15+V15 -> 0 | K15: =Q15+W15 -> 0 | L15: =R15+X15 -> 0 | M15: =S15+Y15 -> 50 | O15: =SUM(P15:S15) -> 50 | S15: 50 | U15: =SUM(V15:Y15) -> 0
A16: 1001050109 | B16: Máy RO-05/028 (CTAROMAX) | C16: PC | D16: Máy TCM sx | E16: 10L | F16: OEM | G16: Aromax | H16: 1800000 | I16: =SUM(J16:M16) -> 0 | J16: =P16+V16 -> 0 | K16: =Q16+W16 -> 0 | L16: =R16+X16 -> 0 | M16: =S16+Y16 -> 0 | O16: =SUM(P16:S16) -> 0 | U16: =SUM(V16:Y16) -> 0
A17: 1001050152 | B17: Máy RO-01/DB03 (CTMANHNGOAN.01) | C17: PC | D17: Máy TCM sx | E17: 10L | F17: OEM | G17: Mạnh Ngoan | H17: 1249997 | I17: =SUM(J17:M17) -> 150 | J17: =P17+V17 -> 0 | K17: =Q17+W17 -> 50 | L17: =R17+X17 -> 0 | M17: =S17+Y17 -> 100 | O17: =SUM(P17:S17) -> 150 | Q17: 50 | S17: 100 | U17: =SUM(V17:Y17) -> 0
A18: 1001050153 | B18: Máy RO-01/DB03 (CTMANHNGOAN.02) | C18: PC | D18: Máy TCM sx | E18: 10L | F18: OEM | G18: Mạnh Ngoan | H18: 1349997 | I18: =SUM(J18:M18) -> 100 | J18: =P18+V18 -> 50 | K18: =Q18+W18 -> 0 | L18: =R18+X18 -> 50 | M18: =S18+Y18 -> 0 | O18: =SUM(P18:S18) -> 100 | P18: 50 | R18: 50 | U18: =SUM(V18:Y18) -> 0
A19: 1001050170 | B19: Máy RO-01/003 (CHANHTHAITN.03) | C19: PC | D19: Máy TCM sx | E19: 10L | F19: OEM | G19: Thái TN | H19: 1515001 | I19: =SUM(J19:M19) -> 200 | J19: =P19+V19 -> 50 | K19: =Q19+W19 -> 50 | L19: =R19+X19 -> 50 | M19: =S19+Y19 -> 50 | O19: =SUM(P19:S19) -> 200 | P19: 50 | Q19: 50 | R19: 50 | S19: 50 | U19: =SUM(V19:Y19) -> 0
A20: 1001050198 | B20: Máy RO-01/016 (PIKOM.01) | C20: PC | D20: Máy TCM sx | E20: 10L | F20: OEM | G20: Pikom | H20: 1800000 | I20: =SUM(J20:M20) -> 70 | J20: =P20+V20 -> 20 | K20: =Q20+W20 -> 0 | L20: =R20+X20 -> 0 | M20: =S20+Y20 -> 50 | O20: =SUM(P20:S20) -> 70 | P20: 20 | S20: 50 | U20: =SUM(V20:Y20) -> 0
A21: 1001050229 | B21: Máy RO-05/001A (CTSAWA.06B) | C21: PC | D21: Máy TCM sx | E21: 10L | F21: OEM | G21: Sawa | H21: 1800000 | I21: =SUM(J21:M21) -> 0 | J21: =P21+V21 -> 0 | K21: =Q21+W21 -> 0 | L21: =R21+X21 -> 0 | M21: =S21+Y21 -> 0 | O21: =SUM(P21:S21) -> 0 | U21: =SUM(V21:Y21) -> 0
A22: 1001050232 | B22: Máy RO-100 (CHANHTHAITN.03) | C22: PC | D22: Máy TCM sx | E22: 10L | F22: OEM | G22: Thái TN | H22: 1625001 | I22: =SUM(J22:M22) -> 50 | J22: =P22+V22 -> 0 | K22: =Q22+W22 -> 0 | L22: =R22+X22 -> 0 | M22: =S22+Y22 -> 50 | O22: =SUM(P22:S22) -> 50 | S22: 50 | U22: =SUM(V22:Y22) -> 0
A23: 1001050261 | B23: Máy RO-18/027 CHTUYENHY.03 | C23: PC | D23: Máy TCM sx | E23: 10L | F23: OEM | G23: Tuyên HY | H23: 1923981 | I23: =SUM(J23:M23) -> 0 | J23: =P23+V23 -> 0 | K23: =Q23+W23 -> 0 | L23: =R23+X23 -> 0 | M23: =S23+Y23 -> 0 | O23: =SUM(P23:S23) -> 0 | U23: =SUM(V23:Y23) -> 0
A24: 1001050266 | B24: Máy RO-202/DB25 CTMANHNGOAN.02 | C24: PC | D24: Máy TCM sx | E24: 10L | F24: OEM | G24: Mạnh Ngoan | H24: 1430000 | I24: =SUM(J24:M24) -> 100 | J24: =P24+V24 -> 50 | K24: =Q24+W24 -> 0 | L24: =R24+X24 -> 50 | M24: =S24+Y24 -> 0 | O24: =SUM(P24:S24) -> 100 | P24: 50 | R24: 50 | U24: =SUM(V24:Y24) -> 0
A25: 1001050280 | B25: Máy RO-01 CHHAIDANG.02 | C25: PC | D25: Máy TCM sx | E25: 10L | F25: OEM | G25: Hải Đăng | H25: 2356000 | I25: =SUM(J25:M25) -> 50 | J25: =P25+V25 -> 0 | K25: =Q25+W25 -> 0 | L25: =R25+X25 -> 50 | M25: =S25+Y25 -> 0 | O25: =SUM(P25:S25) -> 50 | R25: 50 | U25: =SUM(V25:Y25) -> 0
A26: 1001050314 | B26: Máy lọc nước RO-01/001 v4 | C26: PC | D26: Máy TCM sx | E26: 10L | F26: OEM | G26: Chung | H26: 1200000 | I26: =SUM(J26:M26) -> 0 | J26: =P26+V26 -> 0 | K26: =Q26+W26 -> 0 | L26: =R26+X26 -> 0 | M26: =S26+Y26 -> 0 | O26: =SUM(P26:S26) -> 0 | U26: =SUM(V26:Y26) -> 0
A27: 1001070016 | B27: Máy RO-05/001A (CTANPHAT.01) | C27: PC | D27: Máy TCM sx | E27: 10L | F27: OEM | G27: An Phát | H27: 1859994 | I27: =SUM(J27:M27) -> 0 | J27: =P27+V27 -> 0 | K27: =Q27+W27 -> 0 | L27: =R27+X27 -> 0 | M27: =S27+Y27 -> 0 | O27: =SUM(P27:S27) -> 0 | U27: =SUM(V27:Y27) -> 0
A28: 1001070058 | B28: Máy RO-01 CHHAIDANG.01 | C28: PC | D28: Máy TCM sx | E28: 10L | F28: OEM | G28: Hải Đăng | H28: 1849995 | I28: =SUM(J28:M28) -> 50 | J28: =P28+V28 -> 0 | K28: =Q28+W28 -> 0 | L28: =R28+X28 -> 50 | M28: =S28+Y28 -> 0 | O28: =SUM(P28:S28) -> 50 | R28: 50 | U28: =SUM(V28:Y28) -> 0
A29: 1001070067 | B29: Máy RO classic 7 cấp SHK-7007 | C29: PC | D29: Máy TCM sx | E29: 10L | F29: OEM | G29: Sơn Hà | H29: 2462963 | I29: =SUM(J29:M29) -> 400 | J29: =P29+V29 -> 100 | K29: =Q29+W29 -> 100 | L29: =R29+X29 -> 100 | M29: =S29+Y29 -> 100 | O29: =SUM(P29:S29) -> 400 | P29: 100 | Q29: 100 | R29: 100 | S29: 100 | U29: =SUM(V29:Y29) -> 0
A30: 1001080077 | B30: Máy RO-05/001A CTEVERSUN.01 | C30: PC | D30: Máy TCM sx | E30: 10L | F30: OEM | G30: Eversun | H30: 1929998 | I30: =SUM(J30:M30) -> 0 | J30: =P30+V30 -> 0 | K30: =Q30+W30 -> 0 | L30: =R30+X30 -> 0 | M30: =S30+Y30 -> 0 | O30: =SUM(P30:S30) -> 0 | U30: =SUM(V30:Y30) -> 0
A31: 1001080081 | B31: Máy RO-202/DB25 CTHUNGTHINH.02 | C31: PC | D31: Máy TCM sx | E31: 10L | F31: OEM | G31: Hưng Thịnh | H31: 2010001 | I31: =SUM(J31:M31) -> 0 | J31: =P31+V31 -> 0 | K31: =Q31+W31 -> 0 | L31: =R31+X31 -> 0 | M31: =S31+Y31 -> 0 | O31: =SUM(P31:S31) -> 0 | U31: =SUM(V31:Y31) -> 0
A32: 1001080087 | B32: Máy RO-01/003 CHANHVIET.03 | C32: PC | D32: Máy TCM sx | E32: 10L Tủ | F32: OEM | G32: Viết NA | H32: 2116667 | I32: =SUM(J32:M32) -> 250 | J32: =P32+V32 -> 50 | K32: =Q32+W32 -> 50 | L32: =R32+X32 -> 50 | M32: =S32+Y32 -> 100 | O32: =SUM(P32:S32) -> 250 | P32: 50 | Q32: 50 | R32: 50 | S32: 100 | U32: =SUM(V32:Y32) -> 0
A33: 1001090017 | B33: Máy RO-05/028 (CTGOLDTHINK.02) | C33: PC | D33: Máy TCM sx | E33: 10L | F33: OEM | G33: Goldthink | H33: 1600000 | I33: =SUM(J33:M33) -> 0 | J33: =P33+V33 -> 0 | K33: =Q33+W33 -> 0 | L33: =R33+X33 -> 0 | M33: =S33+Y33 -> 0 | O33: =SUM(P33:S33) -> 0 | U33: =SUM(V33:Y33) -> 0
A34: 1001090055 | B34: Máy RO-202/DB25 CTHUNGTHINH.01 | C34: PC | D34: Máy TCM sx | E34: 10L | F34: OEM | G34: Hưng Thịnh | H34: 1959995 | I34: =SUM(J34:M34) -> 0 | J34: =P34+V34 -> 0 | K34: =Q34+W34 -> 0 | L34: =R34+X34 -> 0 | M34: =S34+Y34 -> 0 | O34: =SUM(P34:S34) -> 0 | U34: =SUM(V34:Y34) -> 0
A35: 1001090057 | B35: Máy RO-01/001 CTEVERSUN.01 | C35: PC | D35: Máy TCM sx | E35: 10L | F35: OEM | G35: Eversun | H35: 1879992 | I35: =SUM(J35:M35) -> 0 | J35: =P35+V35 -> 0 | K35: =Q35+W35 -> 0 | L35: =R35+X35 -> 0 | M35: =S35+Y35 -> 0 | O35: =SUM(P35:S35) -> 0 | U35: =SUM(V35:Y35) -> 0
A36: 1001090091 | B36: Máy RO 9 cấp phố xanh SHK-7109 PX | C36: PC | D36: Máy TCM sx | E36: 10L Tủ | F36: OEM | G36: Sơn Hà | H36: 2190000 | I36: =SUM(J36:M36) -> 200 | J36: =P36+V36 -> 50 | K36: =Q36+W36 -> 50 | L36: =R36+X36 -> 50 | M36: =S36+Y36 -> 50 | O36: =SUM(P36:S36) -> 200 | P36: 50 | Q36: 50 | R36: 50 | S36: 50 | U36: =SUM(V36:Y36) -> 0
A37: 1001090092 | B37: Máy NLN 9 cấp sao lam SHK-7309 CSL | C37: PC | D37: Máy TCM sx | E37: Block | F37: OEM | G37: Sơn Hà | H37: 3567000 | I37: =SUM(J37:M37) -> 200 | J37: =P37+V37 -> 50 | K37: =Q37+W37 -> 50 | L37: =R37+X37 -> 50 | M37: =S37+Y37 -> 50 | O37: =SUM(P37:S37) -> 200 | P37: 50 | Q37: 50 | R37: 50 | S37: 50 | U37: =SUM(V37:Y37) -> 0
A38: 1001090097 | B38: Máy lọc nước RO Undersink 9 cấp IROKA | C38: PC | D38: Máy TCM sx | E38: 10L | F38: OEM | G38: Viết NA | H38: 1773148 | I38: =SUM(J38:M38) -> 200 | J38: =P38+V38 -> 50 | K38: =Q38+W38 -> 50 | L38: =R38+X38 -> 0 | M38: =S38+Y38 -> 100 | O38: =SUM(P38:S38) -> 200 | P38: 50 | Q38: 50 | S38: 100 | U38: =SUM(V38:Y38) -> 0
A39: 1001090109 | B39: Máy RO classic 9 cấp SHK-7009 | C39: PC | D39: Máy TCM sx | E39: 10L | F39: OEM | G39: Sơn Hà | H39: 2365200 | I39: =SUM(J39:M39) -> 400 | J39: =P39+V39 -> 100 | K39: =Q39+W39 -> 100 | L39: =R39+X39 -> 100 | M39: =S39+Y39 -> 100 | O39: =SUM(P39:S39) -> 400 | P39: 100 | Q39: 100 | R39: 100 | S39: 100 | U39: =SUM(V39:Y39) -> 0
A40: 1001090111 | B40: Máy lọc nước RO-01/001 | C40: PC | D40: Máy TCM sx | E40: 10L | F40: OEM | G40: Chung | H40: 1000000 | I40: =SUM(J40:M40) -> 50 | J40: =P40+V40 -> 50 | K40: =Q40+W40 -> 0 | L40: =R40+X40 -> 0 | M40: =S40+Y40 -> 0 | O40: =SUM(P40:S40) -> 50 | P40: 50 | U40: =SUM(V40:Y40) -> 0
A41: 1001090112 | B41: Máy RO-05/028 (CTGOLDTHINK.11) | C41: PC | D41: Máy TCM sx | E41: 10L | F41: OEM | G41: Goldthink | H41: 1808000 | I41: =SUM(J41:M41) -> 100 | J41: =P41+V41 -> 0 | K41: =Q41+W41 -> 50 | L41: =R41+X41 -> 0 | M41: =S41+Y41 -> 50 | O41: =SUM(P41:S41) -> 100 | Q41: 50 | S41: 50 | U41: =SUM(V41:Y41) -> 0
A42: 1001090113 | B42: Máy RO 9 cấp trụ x.ngọc SHK-7109 TN | C42: PC | D42: Máy TCM sx | E42: 10L Tủ | F42: OEM | G42: Sơn Hà | H42: 2365200 | I42: =SUM(J42:M42) -> 200 | J42: =P42+V42 -> 50 | K42: =Q42+W42 -> 50 | L42: =R42+X42 -> 50 | M42: =S42+Y42 -> 50 | O42: =SUM(P42:S42) -> 200 | P42: 50 | Q42: 50 | R42: 50 | S42: 50 | U42: =SUM(V42:Y42) -> 0
A43: 1001090115 | B43: Máy RO thế hệ mới 9 cấp TMK-7009 Toàn Mỹ | C43: PC | D43: Máy TCM sx | E43: 10L | F43: OEM | G43: Toàn Mỹ | H43: 2073000 | I43: =SUM(J43:M43) -> 0 | J43: =P43+V43 -> 0 | K43: =Q43+W43 -> 0 | L43: =R43+X43 -> 0 | M43: =S43+Y43 -> 0 | O43: =SUM(P43:S43) -> 0 | U43: =SUM(V43:Y43) -> 0
A44: 1001090116 | B44: Máy lọc nước RO 9 cấp Toàn Mỹ 7109-DK | C44: PC | D44: Máy TCM sx | E44: 10L Tủ | F44: OEM | G44: Toàn Mỹ | H44: 2073000 | I44: =SUM(J44:M44) -> 0 | J44: =P44+V44 -> 0 | K44: =Q44+W44 -> 0 | L44: =R44+X44 -> 0 | M44: =S44+Y44 -> 0 | O44: =SUM(P44:S44) -> 0 | U44: =SUM(V44:Y44) -> 0
A45: 1001090117 | B45: Máy RO 9 cấp trụ xanh SHK-7109 TX | C45: PC | D45: Máy TCM sx | E45: 10L Tủ | F45: OEM | G45: Sơn Hà | H45: 2365200 | I45: =SUM(J45:M45) -> 200 | J45: =P45+V45 -> 50 | K45: =Q45+W45 -> 50 | L45: =R45+X45 -> 50 | M45: =S45+Y45 -> 50 | O45: =SUM(P45:S45) -> 200 | P45: 50 | Q45: 50 | R45: 50 | S45: 50 | U45: =SUM(V45:Y45) -> 0
A46: 1001090118 | B46: Máy RO 9 cấp phố đỏ SHK-7109 PÐ | C46: PC | D46: Máy TCM sx | E46: 10L Tủ | F46: OEM | G46: Sơn Hà | H46: 2190000 | I46: =SUM(J46:M46) -> 200 | J46: =P46+V46 -> 50 | K46: =Q46+W46 -> 50 | L46: =R46+X46 -> 50 | M46: =S46+Y46 -> 50 | O46: =SUM(P46:S46) -> 200 | P46: 50 | Q46: 50 | R46: 50 | S46: 50 | U46: =SUM(V46:Y46) -> 0
A47: 1001090119 | B47: Máy NLN 9 cấp sao vàng SHK-7309 CSV | C47: PC | D47: Máy TCM sx | E47: Block | F47: OEM | G47: Sơn Hà | H47: 3567000 | I47: =SUM(J47:M47) -> 200 | J47: =P47+V47 -> 50 | K47: =Q47+W47 -> 50 | L47: =R47+X47 -> 50 | M47: =S47+Y47 -> 50 | O47: =SUM(P47:S47) -> 200 | P47: 50 | Q47: 50 | R47: 50 | S47: 50 | U47: =SUM(V47:Y47) -> 0
A48: 1001090120 | B48: Máy NLN 9 cấp mcxanh SHK-7309 MCX | C48: PC | D48: Máy TCM sx | E48: Block | F48: OEM | G48: Sơn Hà | H48: 3567000 | I48: =SUM(J48:M48) -> 200 | J48: =P48+V48 -> 50 | K48: =Q48+W48 -> 50 | L48: =R48+X48 -> 50 | M48: =S48+Y48 -> 50 | O48: =SUM(P48:S48) -> 200 | P48: 50 | Q48: 50 | R48: 50 | S48: 50 | U48: =SUM(V48:Y48) -> 0
A49: 1001090121 | B49: Máy NLN 9 cấp mcden SHK-7309 MCÐ | C49: PC | D49: Máy TCM sx | E49: Block | F49: OEM | G49: Sơn Hà | H49: 3567000 | I49: =SUM(J49:M49) -> 200 | J49: =P49+V49 -> 50 | K49: =Q49+W49 -> 50 | L49: =R49+X49 -> 50 | M49: =S49+Y49 -> 50 | O49: =SUM(P49:S49) -> 200 | P49: 50 | Q49: 50 | R49: 50 | S49: 50 | U49: =SUM(V49:Y49) -> 0
A50: 1001100058 | B50: Máy lọc nước RO 10 cấp Toàn Mỹ 7110-DK | C50: PC | D50: Máy TCM sx | E50: 10L Tủ | F50: OEM | G50: Toàn Mỹ | H50: 2073000 | I50: =SUM(J50:M50) -> 0 | J50: =P50+V50 -> 0 | K50: =Q50+W50 -> 0 | L50: =R50+X50 -> 0 | M50: =S50+Y50 -> 0 | O50: =SUM(P50:S50) -> 0 | U50: =SUM(V50:Y50) -> 0
A51: 1001100059 | B51: Máy lọc nước RO 9 cấp Toàn Mỹ 7109-HT | C51: PC | D51: Máy TCM sx | E51: 10L Tủ | F51: OEM | G51: Toàn Mỹ | H51: 2073000 | I51: =SUM(J51:M51) -> 0 | J51: =P51+V51 -> 0 | K51: =Q51+W51 -> 0 | L51: =R51+X51 -> 0 | M51: =S51+Y51 -> 0 | O51: =SUM(P51:S51) -> 0 | U51: =SUM(V51:Y51) -> 0
